Workbook

Sheet Base Insumos
A1: Código | B1: Descrição | C1: Custo Unit. (R$) | D1: Unidade | E1: Observação | F1: Últ. Atualização
A2: 000372 | B2: =IFERROR(VLOOKUP(A2,_Protheus_Cadastro!$A:$B,2,FALSE),"PENDENTE") | C2: =IFERROR(VLOOKUP(A2,_Protheus_Cadastro!$A:$G,7,FALSE),0) | D2: =IFERROR(VLOOKUP(A2,_Protheus_Cadastro!$A:$D,4,FALSE),"") | F2: 13/05/2026
A3: 000404 | B3: =IFERROR(VLOOKUP(A3,_Protheus_Cadastro!$A:$B,2,FALSE),"PENDENTE") | C3: =IFERROR(VLOOKUP(A3,_Protheus_Cadastro!$A:$G,7,FALSE),0) | D3: =IFERROR(VLOOKUP(A3,_Protheus_Cadastro!$A:$D,4,FALSE),"") | F3: 13/05/2026
A4: 000487 | B4: =IFERROR(VLOOKUP(A4,_Protheus_Cadastro!$A:$B,2,FALSE),"PENDENTE") | C4: =IFERROR(VLOOKUP(A4,_Protheus_Cadastro!$A:$G,7,FALSE),0) | D4: =IFERROR(VLOOKUP(A4,_Protheus_Cadastro!$A:$D,4,FALSE),"") | F4: 13/05/2026
A5: 000624 | B5: =IFERROR(VLOOKUP(A5,_Protheus_Cadastro!$A:$B,2,FALSE),"PENDENTE") | C5: =IFERROR(VLOOKUP(A5,_Protheus_Cadastro!$A:$G,7,FALSE),0) | D5: =IFERROR(VLOOKUP(A5,_Protheus_Cadastro!$A:$D,4,FALSE),"") | F5: 13/05/2026
A6: 001972 | B6: =IFERROR(VLOOKUP(A6,_Protheus_Cadastro!$A:$B,2,FALSE),"PENDENTE") | C6: =IFERROR(VLOOKUP(A6,_Protheus_Cadastro!$A:$G,7,FALSE),0) | D6: =IFERROR(VLOOKUP(A6,_Protheus_Cadastro!$A:$D,4,FALSE),"") | F6: 13/05/2026
A7: 000459 | B7: =IFERROR(VLOOKUP(A7,_Protheus_Cadastro!$A:$B,2,FALSE),"PENDENTE") | C7: =IFERROR(VLOOKUP(A7,_Protheus_Cadastro!$A:$G,7,FALSE),0) | D7: =IFERROR(VLOOKUP(A7,_Protheus_Cadastro!$A:$D,4,FALSE),"") | F7: 13/05/2026
A8: 000700 | B8: =IFERROR(VLOOKUP(A8,_Protheus_Cadastro!$A:$B,2,FALSE),"PENDENTE") | C8: =IFERROR(VLOOKUP(A8,_Protheus_Cadastro!$A:$G,7,FALSE),0) | D8: =IFERROR(VLOOKUP(A8,_Protheus_Cadastro!$A:$D,4,FALSE),"") | F8: 13/05/2026
A9: 000374 | B9: =IFERROR(VLOOKUP(A9,_Protheus_Cadastro!$A:$B,2,FALSE),"PENDENTE") | C9: =IFERROR(VLOOKUP(A9,_Protheus_Cadastro!$A:$G,7,FALSE),0) | D9: =IFERROR(VLOOKUP(A9,_Protheus_Cadastro!$A:$D,4,FALSE),"") | F9: 13/05/2026
A10: 000460 | B10: =IFERROR(VLOOKUP(A10,_Protheus_Cadastro!$A:$B,2,FALSE),"PENDENTE") | C10: =IFERROR(VLOOKUP(A10,_Protheus_Cadastro!$A:$G,7,FALSE),0) | D10: =IFERROR(VLOOKUP(A10,_Protheus_Cadastro!$A:$D,4,FALSE),"") | F10: 13/05/2026
A11: 000334 | B11: =IFERROR(VLOOKUP(A11,_Protheus_Cadastro!$A:$B,2,FALSE),"PENDENTE") | C11: =IFERROR(VLOOKUP(A11,_Protheus_Cadastro!$A:$G,7,FALSE),0) | D11: =IFERROR(VLOOKUP(A11,_Protheus_Cadastro!$A:$D,4,FALSE),"") | F11: 13/05/2026
A12: 000380 | B12: =IFERROR(VLOOKUP(A12,_Protheus_Cadastro!$A:$B,2,FALSE),"PENDENTE") | C12: =IFERROR(VLOOKUP(A12,_Protheus_Cadastro!$A:$G,7,FALSE),0) | D12: =IFERROR(VLOOKUP(A12,_Protheus_Cadastro!$A:$D,4,FALSE),"") | F12: 13/05/2026
A13: 000333 | B13: =IFERROR(VLOOKUP(A13,_Protheus_Cadastro!$A:$B,2,FALSE),"PENDENTE") | C13: =IFERROR(VLOOKUP(A13,_Protheus_Cadastro!$A:$G,7,FALSE),0) | D13: =IFERROR(VLOOKUP(A13,_Protheus_Cadastro!$A:$D,4,FALSE),"") | F13: 13/05/2026
... A21: 001975 | B21: =IFERROR(VLOOKUP(A21,_Protheus_Cadastro!$A:$B,2,FALSE),"PENDENTE") | C21: =IFERROR(VLOOKUP(A21,_Protheus_Cadastro!$A:$G,7,FALSE),0) | D21: =IFERROR(VLOOKUP(A21,_Protheus_Cadastro!$A:$D,4,FALSE),"") | F21: 13/05/2026
A22: 009947 | B22: =IFERROR(VLOOKUP(A22,_Protheus_Cadastro!$A:$B,2,FALSE),"PENDENTE") | C22: =IFERROR(VLOOKUP(A22,_Protheus_Cadastro!$A:$G,7,FALSE),0) | D22: =IFERROR(VLOOKUP(A22,_Protheus_Cadastro!$A:$D,4,FALSE),"") | E22: Muita diferença de valor para o de 100ml | F22: 13/05/2026
A23: 001176 | B23: =IFERROR(VLOOKUP(A23,_Protheus_Cadastro!$A:$B,2,FALSE),"PENDENTE") | C23: =IFERROR(VLOOKUP(A23,_Protheus_Cadastro!$A:$G,7,FALSE),0) | D23: =IFERROR(VLOOKUP(A23,_Protheus_Cadastro!$A:$D,4,FALSE),"") | F23: 13/05/2026
A24: 000337 | B24: =IFERROR(VLOOKUP(A24,_Protheus_Cadastro!$A:$B,2,FALSE),"PENDENTE") | C24: =IFERROR(VLOOKUP(A24,_Protheus_Cadastro!$A:$G,7,FALSE),0) | D24: =IFERROR(VLOOKUP(A24,_Protheus_Cadastro!$A:$D,4,FALSE),"") | F24: 13/05/2026
A25: 000345 | B25: =IFERROR(VLOOKUP(A25,_Protheus_Cadastro!$A:$B,2,FALSE),"PENDENTE") | C25: =IFERROR(VLOOKUP(A25,_Protheus_Cadastro!$A:$G,7,FALSE),0) | D25: =IFERROR(VLOOKUP(A25,_Protheus_Cadastro!$A:$D,4,FALSE),"") | F25: 13/05/2026
A26: 000377 | B26: =IFERROR(VLOOKUP(A26,_Protheus_Cadastro!$A:$B,2,FALSE),"PENDENTE") | C26: =IFERROR(VLOOKUP(A26,_Protheus_Cadastro!$A:$G,7,FALSE),0) | D26: =IFERROR(VLOOKUP(A26,_Protheus_Cadastro!$A:$D,4,FALSE),"") | F26: 13/05/2026
A27: 001043 | B27: =IFERROR(VLOOKUP(A27,_Protheus_Cadastro!$A:$B,2,FALSE),"PENDENTE") | C27: =IFERROR(VLOOKUP(A27,_Protheus_Cadastro!$A:$G,7,FALSE),0) | D27: =IFERROR(VLOOKUP(A27,_Protheus_Cadastro!$A:$D,4,FALSE),"") | F27: 13/05/2026
A28: 010225 | B28: =IFERROR(VLOOKUP(A28,_Protheus_Cadastro!$A:$B,2,FALSE),"PENDENTE") | C28: =IFERROR(VLOOKUP(A28,_Protheus_Cadastro!$A:$G,7,FALSE),0) | D28: =IFERROR(VLOOKUP(A28,_Protheus_Cadastro!$A:$D,4,FALSE),"") | F28: 13/05/2026
A29: 000747 | B29: =IFERROR(VLOOKUP(A29,_Protheus_Cadastro!$A:$B,2,FALSE),"PENDENTE") | C29: =IFERROR(VLOOKUP(A29,_Protheus_Cadastro!$A:$G,7,FALSE),0) | D29: =IFERROR(VLOOKUP(A29,_Protheus_Cadastro!$A:$D,4,FALSE),"") | F29: 13/05/2026
A30: 001995 | B30: =IFERROR(VLOOKUP(A30,_Protheus_Cadastro!$A:$B,2,FALSE),"PENDENTE") | C30: =IFERROR(VLOOKUP(A30,_Protheus_Cadastro!$A:$G,7,FALSE),0) | D30: =IFERROR(VLOOKUP(A30,_Protheus_Cadastro!$A:$D,4,FALSE),"") | F30: 13/05/2026
A31: 000426 | B31: =IFERROR(VLOOKUP(A31,_Protheus_Cadastro!$A:$B,2,FALSE),"PENDENTE") | C31: =IFERROR(VLOOKUP(A31,_Protheus_Cadastro!$A:$G,7,FALSE),0) | D31: =IFERROR(VLOOKUP(A31,_Protheus_Cadastro!$A:$D,4,FALSE),"") | F31: 13/05/2026
A32: 009487 | B32: =IFERROR(VLOOKUP(A32,_Protheus_Cadastro!$A:$B,2,FALSE),"PENDENTE") | C32: =IFERROR(VLOOKUP(A32,_Protheus_Cadastro!$A:$G,7,FALSE),0) | D32: =IFERROR(VLOOKUP(A32,_Protheus_Cadastro!$A:$D,4,FALSE),"") | F32: 13/05/2026
A33: 009486 | B33: =IFERROR(VLOOKUP(A33,_Protheus_Cadastro!$A:$B,2,FALSE),"PENDENTE") | C33: =IFERROR(VLOOKUP(A33,_Protheus_Cadastro!$A:$G,7,FALSE),0) | D33: =IFERROR(VLOOKUP(A33,_Protheus_Cadastro!$A:$D,4,FALSE),"") | F33: 13/05/2026
A34: 000488 | B34: =IFERROR(VLOOKUP(A34,_Protheus_Cadastro!$A:$B,2,FALSE),"PENDENTE") | C34: =IFERROR(VLOOKUP(A34,_Protheus_Cadastro!$A:$G,7,FALSE),0) | D34: =IFERROR(VLOOKUP(A34,_Protheus_Cadastro!$A:$D,4,FALSE),"") | F34: 13/05/2026
... A51: 000304 | B51: =IFERROR(VLOOKUP(A51,_Protheus_Cadastro!$A:$B,2,FALSE),"PENDENTE") | C51: =IFERROR(VLOOKUP(A51,_Protheus_Cadastro!$A:$G,7,FALSE),0) | D51: =IFERROR(VLOOKUP(A51,_Protheus_Cadastro!$A:$D,4,FALSE),"") | F51: 13/05/2026
A52: 000306 | B52: =IFERROR(VLOOKUP(A52,_Protheus_Cadastro!$A:$B,2,FALSE),"PENDENTE") | C52: =IFERROR(VLOOKUP(A52,_Protheus_Cadastro!$A:$G,7,FALSE),0) | D52: =IFERROR(VLOOKUP(A52,_Protheus_Cadastro!$A:$D,4,FALSE),"") | E52: Confirmar em qual PA usamos esse componente (prato novo?) | F52: 13/05/2026
A53: 009090 | B53: =IFERROR(VLOOKUP(A53,_Protheus_Cadastro!$A:$B,2,FALSE),"PENDENTE") | C53: =IFERROR(VLOOKUP(A53,_Protheus_Cadastro!$A:$G,7,FALSE),0) | D53: =IFERROR(VLOOKUP(A53,_Protheus_Cadastro!$A:$D,4,FALSE),"") | F53: 13/05/2026
A54: 001133 | B54: =IFERROR(VLOOKUP(A54,_Protheus_Cadastro!$A:$B,2,FALSE),"PENDENTE") | C54: =IFERROR(VLOOKUP(A54,_Protheus_Cadastro!$A:$G,7,FALSE),0) | D54: =IFERROR(VLOOKUP(A54,_Protheus_Cadastro!$A:$D,4,FALSE),"") | F54: 13/05/2026
A55: 000327 | B55: =IFERROR(VLOOKUP(A55,_Protheus_Cadastro!$A:$B,2,FALSE),"PENDENTE") | C55: =IFERROR(VLOOKUP(A55,_Protheus_Cadastro!$A:$G,7,FALSE),0) | D55: =IFERROR(VLOOKUP(A55,_Protheus_Cadastro!$A:$D,4,FALSE),"") | F55: 13/05/2026
A56: 000467 | B56: =IFERROR(VLOOKUP(A56,_Protheus_Cadastro!$A:$B,2,FALSE),"PENDENTE") | C56: =IFERROR(VLOOKUP(A56,_Protheus_Cadastro!$A:$G,7,FALSE),0) | D56: =IFERROR(VLOOKUP(A56,_Protheus_Cadastro!$A:$D,4,FALSE),"") | F56: 13/05/2026
A57: 000326 | B57: =IFERROR(VLOOKUP(A57,_Protheus_Cadastro!$A:$B,2,FALSE),"PENDENTE") | C57: =IFERROR(VLOOKUP(A57,_Protheus_Cadastro!$A:$G,7,FALSE),0) | D57: =IFERROR(VLOOKUP(A57,_Protheus_Cadastro!$A:$D,4,FALSE),"") | F57: 13/05/2026
A58: 001346 | B58: =IFERROR(VLOOKUP(A58,_Protheus_Cadastro!$A:$B,2,FALSE),"PENDENTE") | C58: =IFERROR(VLOOKUP(A58,_Protheus_Cadastro!$A:$G,7,FALSE),0) | D58: =IFERROR(VLOOKUP(A58,_Protheus_Cadastro!$A:$D,4,FALSE),"") | F58: 13/05/2026
A59: 001988 | B59: =IFERROR(VLOOKUP(A59,_Protheus_Cadastro!$A:$B,2,FALSE),"PENDENTE") | C59: =IFERROR(VLOOKUP(A59,_Protheus_Cadastro!$A:$G,7,FALSE),0) | D59: =IFERROR(VLOOKUP(A59,_Protheus_Cadastro!$A:$D,4,FALSE),"") | F59: 13/05/2026
A60: 000760 | B60: =IFERROR(VLOOKUP(A60,_Protheus_Cadastro!$A:$B,2,FALSE),"PENDENTE") | C60: =IFERROR(VLOOKUP(A60,_Protheus_Cadastro!$A:$G,7,FALSE),0) | D60: =IFERROR(VLOOKUP(A60,_Protheus_Cadastro!$A:$D,4,FALSE),"") | F60: 13/05/2026
A61: 000759 | B61: =IFERROR(VLOOKUP(A61,_Protheus_Cadastro!$A:$B,2,FALSE),"PENDENTE") | C61: =IFERROR(VLOOKUP(A61,_Protheus_Cadastro!$A:$G,7,FALSE),0) | D61: =IFERROR(VLOOKUP(A61,_Protheus_Cadastro!$A:$D,4,FALSE),"") | F61: 13/05/2026
A62: 000758 | B62: =IFERROR(VLOOKUP(A62,_Protheus_Cadastro!$A:$B,2,FALSE),"PENDENTE") | C62: =IFERROR(VLOOKUP(A62,_Protheus_Cadastro!$A:$G,7,FALSE),0) | D62: =IFERROR(VLOOKUP(A62,_Protheus_Cadastro!$A:$D,4,FALSE),"") | F62: 13/05/2026
A63: 000756 | B63: =IFERROR(VLOOKUP(A63,_Protheus_Cadastro!$A:$B,2,FALSE),"PENDENTE") | C63: =IFERROR(VLOOKUP(A63,_Protheus_Cadastro!$A:$G,7,FALSE),0) | D63: =IFERROR(VLOOKUP(A63,_Protheus_Cadastro!$A:$D,4,FALSE),"") | E63: Preciso do valor da garrafa | F63: 13/05/2026
A64: 000343 | B64: =IFERROR(VLOOKUP(A64,_Protheus_Cadastro!$A:$B,2,FALSE),"PENDENTE") | C64: =IFERROR(VLOOKUP(A64,_Protheus_Cadastro!$A:$G,7,FALSE),0) | D64: =IFERROR(VLOOKUP(A64,_Protheus_Cadastro!$A:$D,4,FALSE),"") | F64: 13/05/2026
A65: 001923 | B65: =IFERROR(VLOOKUP(A65,_Protheus_Cadastro!$A:$B,2,FALSE),"PENDENTE") | C65: =IFERROR(VLOOKUP(A65,_Protheus_Cadastro!$A:$G,7,FALSE),0) | D65: =IFERROR(VLOOKUP(A65,_Protheus_Cadastro!$A:$D,4,FALSE),"") | F65: 13/05/2026
A66: 000382 | B66: =IFERROR(VLOOKUP(A66,_Protheus_Cadastro!$A:$B,2,FALSE),"PENDENTE") | C66: =IFERROR(VLOOKUP(A66,_Protheus_Cadastro!$A:$G,7,FALSE),0) | D66: =IFERROR(VLOOKUP(A66,_Protheus_Cadastro!$A:$D,4,FALSE),"") | F66: 13/05/2026
A67: 000383 | B67: =IFERROR(VLOOKUP(A67,_Protheus_Cadastro!$A:$B,2,FALSE),"PENDENTE") | C67: =IFERROR(VLOOKUP(A67,_Protheus_Cadastro!$A:$G,7,FALSE),0) | D67: =IFERROR(VLOOKUP(A67,_Protheus_Cadastro!$A:$D,4,FALSE),"") | F67: 13/05/2026
A68: 000453 | B68: =IFERROR(VLOOKUP(A68,_Protheus_Cadastro!$A:$B,2,FALSE),"PENDENTE") | C68: =IFERROR(VLOOKUP(A68,_Protheus_Cadastro!$A:$G,7,FALSE),0) | D68: =IFERROR(VLOOKUP(A68,_Protheus_Cadastro!$A:$D,4,FALSE),"") | F68: 13/05/2026
A69: 000452 | B69: =IFERROR(VLOOKUP(A69,_Protheus_Cadastro!$A:$B,2,FALSE),"PENDENTE") | C69: =IFERROR(VLOOKUP(A69,_Protheus_Cadastro!$A:$G,7,FALSE),0) | D69: =IFERROR(VLOOKUP(A69,_Protheus_Cadastro!$A:$D,4,FALSE),"") | F69: 13/05/2026
A70: 000636 | B70: =IFERROR(VLOOKUP(A70,_Protheus_Cadastro!$A:$B,2,FALSE),"PENDENTE") | C70: =IFERROR(VLOOKUP(A70,_Protheus_Cadastro!$A:$G,7,FALSE),0) | D70: =IFERROR(VLOOKUP(A70,_Protheus_Cadastro!$A:$D,4,FALSE),"") | F70: 13/05/2026
A71: 001177 | B71: =IFERROR(VLOOKUP(A71,_Protheus_Cadastro!$A:$B,2,FALSE),"PENDENTE") | C71: =IFERROR(VLOOKUP(A71,_Protheus_Cadastro!$A:$G,7,FALSE),0) | D71: =IFERROR(VLOOKUP(A71,_Protheus_Cadastro!$A:$D,4,FALSE),"") | F71: 13/05/2026
A72: 1215608 | B72: =IFERROR(VLOOKUP(A72,_Protheus_Cadastro!$A:$B,2,FALSE),"PENDENTE") | C72: =IFERROR(VLOOKUP(A72,_Protheus_Cadastro!$A:$G,7,FALSE),0) | D72: =IFERROR(VLOOKUP(A72,_Protheus_Cadastro!$A:$D,4,FALSE),"") | F72: 13/05/2026
A73: 002220 | B73: =IFERROR(VLOOKUP(A73,_Protheus_Cadastro!$A:$B,2,FALSE),"PENDENTE") | C73: =IFERROR(VLOOKUP(A73,_Protheus_Cadastro!$A:$G,7,FALSE),0) | D73: =IFERROR(VLOOKUP(A73,_Protheus_Cadastro!$A:$D,4,FALSE),"") | F73: 13/05/2026
A74: 002222 | B74: =IFERROR(VLOOKUP(A74,_Protheus_Cadastro!$A:$B,2,FALSE),"PENDENTE") | C74: =IFERROR(VLOOKUP(A74,_Protheus_Cadastro!$A:$G,7,FALSE),0) | D74: =IFERROR(VLOOKUP(A74,_Protheus_Cadastro!$A:$D,4,FALSE),"") | F74: 13/05/2026
A75: 002221 | B75: =IFERROR(VLOOKUP(A75,_Protheus_Cadastro!$A:$B,2,FALSE),"PENDENTE") | C75: =IFERROR(VLOOKUP(A75,_Protheus_Cadastro!$A:$G,7,FALSE),0) | D75: =IFERROR(VLOOKUP(A75,_Protheus_Cadastro!$A:$D,4,FALSE),"") | F75: 13/05/2026
... A145: 000292 | B145: =IFERROR(VLOOKUP(A145,_Protheus_Cadastro!$A:$B,2,FALSE),"PENDENTE") | C145: =IFERROR(VLOOKUP(A145,_Protheus_Cadastro!$A:$G,7,FALSE),0) | D145: =IFERROR(VLOOKUP(A145,_Protheus_Cadastro!$A:$D,4,FALSE),"") | F145: 13/05/2026
A146: 000762 | B146: =IFERROR(VLOOKUP(A146,_Protheus_Cadastro!$A:$B,2,FALSE),"PENDENTE") | C146: =IFERROR(VLOOKUP(A146,_Protheus_Cadastro!$A:$G,7,FALSE),0) | D146: =IFERROR(VLOOKUP(A146,_Protheus_Cadastro!$A:$D,4,FALSE),"") | E146: Confirmar se o valor está correto (na nf esta 26,93) | F146: 13/05/2026
A147: 009537 | B147: =IFERROR(VLOOKUP(A147,_Protheus_Cadastro!$A:$B,2,FALSE),"PENDENTE") | C147: =IFERROR(VLOOKUP(A147,_Protheus_Cadastro!$A:$G,7,FALSE),0) | D147: =IFERROR(VLOOKUP(A147,_Protheus_Cadastro!$A:$D,4,FALSE),"") | F147: 13/05/2026
A148: 001138 | B148: =IFERROR(VLOOKUP(A148,_Protheus_Cadastro!$A:$B,2,FALSE),"PENDENTE") | C148: =IFERROR(VLOOKUP(A148,_Protheus_Cadastro!$A:$G,7,FALSE),0) | D148: =IFERROR(VLOOKUP(A148,_Protheus_Cadastro!$A:$D,4,FALSE),"") | F148: 13/05/2026
A149: 001139 | B149: =IFERROR(VLOOKUP(A149,_Protheus_Cadastro!$A:$B,2,FALSE),"PENDENTE") | C149: =IFERROR(VLOOKUP(A149,_Protheus_Cadastro!$A:$G,7,FALSE),0) | D149: =IFERROR(VLOOKUP(A149,_Protheus_Cadastro!$A:$D,4,FALSE),"") | F149: 13/05/2026
A150: 002061 | B150: =IFERROR(VLOOKUP(A150,_Protheus_Cadastro!$A:$B,2,FALSE),"PENDENTE") | C150: =IFERROR(VLOOKUP(A150,_Protheus_Cadastro!$A:$G,7,FALSE),0) | D150: =IFERROR(VLOOKUP(A150,_Protheus_Cadastro!$A:$D,4,FALSE),"") | F150: 13/05/2026
A151: 0001222 | B151: =IFERROR(VLOOKUP(A151,_Protheus_Cadastro!$A:$B,2,FALSE),"PENDENTE") | C151: =IFERROR(VLOOKUP(A151,_Protheus_Cadastro!$A:$G,7,FALSE),0) | D151: =IFERROR(VLOOKUP(A151,_Protheus_Cadastro!$A:$D,4,FALSE),"") | F151: 13/05/2026
A152: 000388 | B152: =IFERROR(VLOOKUP(A152,_Protheus_Cadastro!$A:$B,2,FALSE),"PENDENTE") | C152: =IFERROR(VLOOKUP(A152,_Protheus_Cadastro!$A:$G,7,FALSE),0) | D152: =IFERROR(VLOOKUP(A152,_Protheus_Cadastro!$A:$D,4,FALSE),"") | F152: 13/05/2026
A153: 000389 | B153: =IFERROR(VLOOKUP(A153,_Protheus_Cadastro!$A:$B,2,FALSE),"PENDENTE") | C153: =IFERROR(VLOOKUP(A153,_Protheus_Cadastro!$A:$G,7,FALSE),0) | D153: =IFERROR(VLOOKUP(A153,_Protheus_Cadastro!$A:$D,4,FALSE),"") | F153: 13/05/2026
A154: 000390 | B154: =IFERROR(VLOOKUP(A154,_Protheus_Cadastro!$A:$B,2,FALSE),"PENDENTE") | C154: =IFERROR(VLOOKUP(A154,_Protheus_Cadastro!$A:$G,7,FALSE),0) | D154: =IFERROR(VLOOKUP(A154,_Protheus_Cadastro!$A:$D,4,FALSE),"") | F154: 13/05/2026
A155: 002067 | B155: =IFERROR(VLOOKUP(A155,_Protheus_Cadastro!$A:$B,2,FALSE),"PENDENTE") | C155: =IFERROR(VLOOKUP(A155,_Protheus_Cadastro!$A:$G,7,FALSE),0) | D155: =IFERROR(VLOOKUP(A155,_Protheus_Cadastro!$A:$D,4,FALSE),"") | F155: 13/05/2026
A156: 000391 | B156: =IFERROR(VLOOKUP(A156,_Protheus_Cadastro!$A:$B,2,FALSE),"PENDENTE") | C156: =IFERROR(VLOOKUP(A156,_Protheus_Cadastro!$A:$G,7,FALSE),0) | D156: =IFERROR(VLOOKUP(A156,_Protheus_Cadastro!$A:$D,4,FALSE),"") | F156: 13/05/2026
A157: 000392 | B157: =IFERROR(VLOOKUP(A157,_Protheus_Cadastro!$A:$B,2,FALSE),"PENDENTE") | C157: =IFERROR(VLOOKUP(A157,_Protheus_Cadastro!$A:$G,7,FALSE),0) | D157: =IFERROR(VLOOKUP(A157,_Protheus_Cadastro!$A:$D,4,FALSE),"") | F157: 13/05/2026
A158: 002257 | B158: =IFERROR(VLOOKUP(A158,_Protheus_Cadastro!$A:$B,2,FALSE),"PENDENTE") | C158: =IFERROR(VLOOKUP(A158,_Protheus_Cadastro!$A:$G,7,FALSE),0) | D158: =IFERROR(VLOOKUP(A158,_Protheus_Cadastro!$A:$D,4,FALSE),"") | F158: 13/05/2026
... A161: 000475 | B161: =IFERROR(VLOOKUP(A161,_Protheus_Cadastro!$A:$B,2,FALSE),"PENDENTE") | C161: =IFERROR(VLOOKUP(A161,_Protheus_Cadastro!$A:$G,7,FALSE),0) | D161: =IFERROR(VLOOKUP(A161,_Protheus_Cadastro!$A:$D,4,FALSE),"") | F161: 13/05/2026
A162: 002224 | B162: =IFERROR(VLOOKUP(A162,_Protheus_Cadastro!$A:$B,2,FALSE),"PENDENTE") | C162: =IFERROR(VLOOKUP(A162,_Protheus_Cadastro!$A:$G,7,FALSE),0) | D162: =IFERROR(VLOOKUP(A162,_Protheus_Cadastro!$A:$D,4,FALSE),"") | E162: Confirmar se o valor está correto (na ultima nf está 110,00) | F162: 13/05/2026
A163: 000352 | B163: =IFERROR(VLOOKUP(A163,_Protheus_Cadastro!$A:$B,2,FALSE),"PENDENTE") | C163: =IFERROR(VLOOKUP(A163,_Protheus_Cadastro!$A:$G,7,FALSE),0) | D163: =IFERROR(VLOOKUP(A163,_Protheus_Cadastro!$A:$D,4,FALSE),"") | F163: 13/05/2026
A164: 000351 | B164: =IFERROR(VLOOKUP(A164,_Protheus_Cadastro!$A:$B,2,FALSE),"PENDENTE") | C164: =IFERROR(VLOOKUP(A164,_Protheus_Cadastro!$A:$G,7,FALSE),0) | D164: =IFERROR(VLOOKUP(A164,_Protheus_Cadastro!$A:$D,4,FALSE),"") | F164: 13/05/2026
A165: 001987 | B165: =IFERROR(VLOOKUP(A165,_Protheus_Cadastro!$A:$B,2,FALSE),"PENDENTE") | C165: =IFERROR(VLOOKUP(A165,_Protheus_Cadastro!$A:$G,7,FALSE),0) | D165: =IFERROR(VLOOKUP(A165,_Protheus_Cadastro!$A:$D,4,FALSE),"") | F165: 13/05/2026
A166: 000393 | B166: =IFERROR(VLOOKUP(A166,_Protheus_Cadastro!$A:$B,2,FALSE),"PENDENTE") | C166: =IFERROR(VLOOKUP(A166,_Protheus_Cadastro!$A:$G,7,FALSE),0) | D166: =IFERROR(VLOOKUP(A166,_Protheus_Cadastro!$A:$D,4,FALSE),"") | F166: 13/05/2026
A167: 001251 | B167: =IFERROR(VLOOKUP(A167,_Protheus_Cadastro!$A:$B,2,FALSE),"PENDENTE") | C167: =IFERROR(VLOOKUP(A167,_Protheus_Cadastro!$A:$G,7,FALSE),0) | D167: =IFERROR(VLOOKUP(A167,_Protheus_Cadastro!$A:$D,4,FALSE),"") | F167: 13/05/2026
A168: 001974 | B168: =IFERROR(VLOOKUP(A168,_Protheus_Cadastro!$A:$B,2,FALSE),"PENDENTE") | C168: =IFERROR(VLOOKUP(A168,_Protheus_Cadastro!$A:$G,7,FALSE),0) | D168: =IFERROR(VLOOKUP(A168,_Protheus_Cadastro!$A:$D,4,FALSE),"") | F168: 13/05/2026
A169: 001178 | B169: =IFERROR(VLOOKUP(A169,_Protheus_Cadastro!$A:$B,2,FALSE),"PENDENTE") | C169: =IFERROR(VLOOKUP(A169,_Protheus_Cadastro!$A:$G,7,FALSE),0) | D169: =IFERROR(VLOOKUP(A169,_Protheus_Cadastro!$A:$D,4,FALSE),"") | F169: 13/05/2026
A170: 000473 | B170: =IFERROR(VLOOKUP(A170,_Protheus_Cadastro!$A:$B,2,FALSE),"PENDENTE") | C170: =IFERROR(VLOOKUP(A170,_Protheus_Cadastro!$A:$G,7,FALSE),0) | D170: =IFERROR(VLOOKUP(A170,_Protheus_Cadastro!$A:$D,4,FALSE),"") | F170: 13/05/2026
A171: 009820 | B171: =IFERROR(VLOOKUP(A171,_Protheus_Cadastro!$A:$B,2,FALSE),"PENDENTE") | C171: =IFERROR(VLOOKUP(A171,_Protheus_Cadastro!$A:$G,7,FALSE),0) | D171: =IFERROR(VLOOKUP(A171,_Protheus_Cadastro!$A:$D,4,FALSE),"") | F171: 13/05/2026
A172: 009821 | B172: =IFERROR(VLOOKUP(A172,_Protheus_Cadastro!$A:$B,2,FALSE),"PENDENTE") | C172: =IFERROR(VLOOKUP(A172,_Protheus_Cadastro!$A:$G,7,FALSE),0) | D172: =IFERROR(VLOOKUP(A172,_Protheus_Cadastro!$A:$D,4,FALSE),"") | F172: 13/05/2026
A173: 000353 | B173: =IFERROR(VLOOKUP(A173,_Protheus_Cadastro!$A:$B,2,FALSE),"PENDENTE") | C173: =IFERROR(VLOOKUP(A173,_Protheus_Cadastro!$A:$G,7,FALSE),0) | D173: =IFERROR(VLOOKUP(A173,_Protheus_Cadastro!$A:$D,4,FALSE),"") | F173: 13/05/2026
A174: 000939 | B174: =IFERROR(VLOOKUP(A174,_Protheus_Cadastro!$A:$B,2,FALSE),"PENDENTE") | C174: =IFERROR(VLOOKUP(A174,_Protheus_Cadastro!$A:$G,7,FALSE),0) | D174: =IFERROR(VLOOKUP(A174,_Protheus_Cadastro!$A:$D,4,FALSE),"") | E174: Preciso do valor da garrafa | F174: 13/05/2026
A175: 009515 | B175: =IFERROR(VLOOKUP(A175,_Protheus_Cadastro!$A:$B,2,FALSE),"PENDENTE") | C175: =IFERROR(VLOOKUP(A175,_Protheus_Cadastro!$A:$G,7,FALSE),0) | D175: =IFERROR(VLOOKUP(A175,_Protheus_Cadastro!$A:$D,4,FALSE),"") | F175: 13/05/2026
A176: 001701 | B176: =IFERROR(VLOOKUP(A176,_Protheus_Cadastro!$A:$B,2,FALSE),"PENDENTE") | C176: =IFERROR(VLOOKUP(A176,_Protheus_Cadastro!$A:$G,7,FALSE),0) | D176: =IFERROR(VLOOKUP(A176,_Protheus_Cadastro!$A:$D,4,FALSE),"") | F176: 13/05/2026
A177: 001349 | B177: =IFERROR(VLOOKUP(A177,_Protheus_Cadastro!$A:$B,2,FALSE),"PENDENTE") | C177: =IFERROR(VLOOKUP(A177,_Protheus_Cadastro!$A:$G,7,FALSE),0) | D177: =IFERROR(VLOOKUP(A177,_Protheus_Cadastro!$A:$D,4,FALSE),"") | F177: 13/05/2026
A178: 001394 | B178: =IFERROR(VLOOKUP(A178,_Protheus_Cadastro!$A:$B,2,FALSE),"PENDENTE") | C178: =IFERROR(VLOOKUP(A178,_Protheus_Cadastro!$A:$G,7,FALSE),0) | D178: =IFERROR(VLOOKUP(A178,_Protheus_Cadastro!$A:$D,4,FALSE),"") | E178: NÃO COMPRAMOS DESDE 09/2025 | F178: 13/05/2026
A179: 001161 | B179: =IFERROR(VLOOKUP(A179,_Protheus_Cadastro!$A:$B,2,FALSE),"PENDENTE") | C179: =IFERROR(VLOOKUP(A179,_Protheus_Cadastro!$A:$G,7,FALSE),0) | D179: =IFERROR(VLOOKUP(A179,_Protheus_Cadastro!$A:$D,4,FALSE),"") | F179: 13/05/2026
A180: 000394 | B180: =IFERROR(VLOOKUP(A180,_Protheus_Cadastro!$A:$B,2,FALSE),"PENDENTE") | C180: =IFERROR(VLOOKUP(A180,_Protheus_Cadastro!$A:$G,7,FALSE),0) | D180: =IFERROR(VLOOKUP(A180,_Protheus_Cadastro!$A:$D,4,FALSE),"") | F180: 13/05/2026
A181: 000354 | B181: =IFERROR(VLOOKUP(A181,_Protheus_Cadastro!$A:$B,2,FALSE),"PENDENTE") | C181: =IFERROR(VLOOKUP(A181,_Protheus_Cadastro!$A:$G,7,FALSE),0) | D181: =IFERROR(VLOOKUP(A181,_Protheus_Cadastro!$A:$D,4,FALSE),"") | F181: 13/05/2026
A182: 000313 | B182: =IFERROR(VLOOKUP(A182,_Protheus_Cadastro!$A:$B,2,FALSE),"PENDENTE") | C182: =IFERROR(VLOOKUP(A182,_Protheus_Cadastro!$A:$G,7,FALSE),0) | D182: =IFERROR(VLOOKUP(A182,_Protheus_Cadastro!$A:$D,4,FALSE),"") | F182: 13/05/2026
A183: 000314 | B183: =IFERROR(VLOOKUP(A183,_Protheus_Cadastro!$A:$B,2,FALSE),"PENDENTE") | C183: =IFERROR(VLOOKUP(A183,_Protheus_Cadastro!$A:$G,7,FALSE),0) | D183: =IFERROR(VLOOKUP(A183,_Protheus_Cadastro!$A:$D,4,FALSE),"") | F183: 13/05/2026
A184: 000323 | B184: =IFERROR(VLOOKUP(A184,_Protheus_Cadastro!$A:$B,2,FALSE),"PENDENTE") | C184: =IFERROR(VLOOKUP(A184,_Protheus_Cadastro!$A:$G,7,FALSE),0) | D184: =IFERROR(VLOOKUP(A184,_Protheus_Cadastro!$A:$D,4,FALSE),"") | F184: 13/05/2026
A185: 000330 | B185: =IFERROR(VLOOKUP(A185,_Protheus_Cadastro!$A:$B,2,FALSE),"PENDENTE") | C185: =IFERROR(VLOOKUP(A185,_Protheus_Cadastro!$A:$G,7,FALSE),0) | D185: =IFERROR(VLOOKUP(A185,_Protheus_Cadastro!$A:$D,4,FALSE),"") | F185: 13/05/2026
A186: 000474 | B186: =IFERROR(VLOOKUP(A186,_Protheus_Cadastro!$A:$B,2,FALSE),"PENDENTE") | C186: =IFERROR(VLOOKUP(A186,_Protheus_Cadastro!$A:$G,7,FALSE),0) | D186: =IFERROR(VLOOKUP(A186,_Protheus_Cadastro!$A:$D,4,FALSE),"") | F186: 13/05/2026
A187: 000308 | B187: =IFERROR(VLOOKUP(A187,_Protheus_Cadastro!$A:$B,2,FALSE),"PENDENTE") | C187: =IFERROR(VLOOKUP(A187,_Protheus_Cadastro!$A:$G,7,FALSE),0) | D187: =IFERROR(VLOOKUP(A187,_Protheus_Cadastro!$A:$D,4,FALSE),"") | F187: 13/05/2026
A188: 001978 | B188: =IFERROR(VLOOKUP(A188,_Protheus_Cadastro!$A:$B,2,FALSE),"PENDENTE") | C188: =IFERROR(VLOOKUP(A188,_Protheus_Cadastro!$A:$G,7,FALSE),0) | D188: =IFERROR(VLOOKUP(A188,_Protheus_Cadastro!$A:$D,4,FALSE),"") | F188: 13/05/2026
A189: 001942 | B189: =IFERROR(VLOOKUP(A189,_Protheus_Cadastro!$A:$B,2,FALSE),"PENDENTE") | C189: =IFERROR(VLOOKUP(A189,_Protheus_Cadastro!$A:$G,7,FALSE),0) | D189: =IFERROR(VLOOKUP(A189,_Protheus_Cadastro!$A:$D,4,FALSE),"") | F189: 13/05/2026
A190: 001941 | B190: =IFERROR(VLOOKUP(A190,_Protheus_Cadastro!$A:$B,2,FALSE),"PENDENTE") | C190: =IFERROR(VLOOKUP(A190,_Protheus_Cadastro!$A:$G,7,FALSE),0) | D190: =IFERROR(VLOOKUP(A190,_Protheus_Cadastro!$A:$D,4,FALSE),"") | F190: 13/05/2026
... A197: 002254 | B197: =IFERROR(VLOOKUP(A197,_Protheus_Cadastro!$A:$B,2,FALSE),"PENDENTE") | C197: =IFERROR(VLOOKUP(A197,_Protheus_Cadastro!$A:$G,7,FALSE),0) | D197: =IFERROR(VLOOKUP(A197,_Protheus_Cadastro!$A:$D,4,FALSE),"") | F197: 13/05/2026
A198: 002049 | B198: =IFERROR(VLOOKUP(A198,_Protheus_Cadastro!$A:$B,2,FALSE),"PENDENTE") | C198: =IFERROR(VLOOKUP(A198,_Protheus_Cadastro!$A:$G,7,FALSE),0) | D198: =IFERROR(VLOOKUP(A198,_Protheus_Cadastro!$A:$D,4,FALSE),"") | E198: ULTIMA COMPRA 2025 | F198: 13/05/2026
A199: 000346 | B199: =IFERROR(VLOOKUP(A199,_Protheus_Cadastro!$A:$B,2,FALSE),"PENDENTE") | C199: =IFERROR(VLOOKUP(A199,_Protheus_Cadastro!$A:$G,7,FALSE),0) | D199: =IFERROR(VLOOKUP(A199,_Protheus_Cadastro!$A:$D,4,FALSE),"") | E199: ULTIMA COMPRA 2018 | F199: 13/05/2026
A200: 001920 | B200: =IFERROR(VLOOKUP(A200,_Protheus_Cadastro!$A:$B,2,FALSE),"PENDENTE") | C200: =IFERROR(VLOOKUP(A200,_Protheus_Cadastro!$A:$G,7,FALSE),0) | D200: =IFERROR(VLOOKUP(A200,_Protheus_Cadastro!$A:$D,4,FALSE),"") | F200: 13/05/2026
...

Sheet Estrutura Protheus
A1: Codigo | B1: Componente | C1: Descricao | D1: Sequencia | E1: Quantidade | F1: Cust Med Ini | G1: Cust Med Atu | H1: Indice Perda | I1: Potencia | J1: Armazem | K1: Fantasma? | L1: Lista | M1: Custo Medio
A2: 002238 | B2: 000454 | C2: BATATA MCAIM 9 MM 2,5KG | E2: 0.15 | F2: 0 | G2: 0 | H2: 0 | I2: 0 | M2: 0
A3: 000001 | B3: 000286 | C3: ESPETO BOVINO | E3: 7 | F3: 0 | G3: 0 | H3: 0 | I3: 0 | M3: 0
A4: 000002 | B4: 000287 | C4: ESPETO CALABRESA C/ PIMENTA | E4: 6 | F4: 0 | G4: 0 | H4: 0 | I4: 0 | M4: 0
A5: 000003 | B5: 000288 | C5: ESPETO CALABRESA S/ PIMENTA | E5: 6 | F5: 0 | G5: 0 | H5: 0 | I5: 0 | M5: 0
A6: 000004 | B6: 000289 | C6: ESPETO CORACAO | E6: 7 | F6: 3161.03 | G6: 0 | H6: 0 | I6: 0 | M6: 0
A7: 000005 | B7: 000290 | C7: ESPETO COSTELINHA BOVINA | E7: 7 | F7: 24252.4 | G7: 0 | H7: 0 | I7: 0 | M7: 0
A8: 000006 | B8: 000291 | C8: ESPETO FRANGO | E8: 7 | F8: 1983.5 | G8: 0 | H8: 0 | I8: 0 | M8: 0
A9: 000007 | B9: 000293 | C9: ESPETO KAFTA | E9: 7 | F9: 10882.88 | G9: 0 | H9: 0 | I9: 0 | M9: 0
A10: 000008 | B10: 000439 | C10: ESPETO QUEIJO COALHO | E10: 0.42 | F10: 0 | G10: 0 | H10: 0 | I10: 0 | M10: 0
A11: 000009 | B11: 000027 | C11: SALSICHAO | E11: 10 | F11: 0 | G11: 0 | H11: 0 | I11: 0 | M11: 0
A12: 000010 | B12: 000292 | C12: ESPETO TULIPA | E12: 5 | F12: 48.42 | G12: 0 | H12: 0 | I12: 0 | M12: 0
A13: 000011 | B13: 000297 | C13: ESPETO PICANHA C/ GORDURA | E13: 7 | F13: 11824.87 | G13: 0 | H13: 0 | I13: 0 | M13: 0
... A257: 001056 | B257: 001044 | C257: MINI CHURROS | E257: 4 | F257: 532.02 | G257: 0 | H257: 0 | I257: 0 | M257: 0
A258: 001069 | B258: 001050 | C258: MINI PASTEL DE CARNE | D258: 001 | E258: 3 | F258: 171.34 | G258: 0 | H258: 0 | I258: 0 | M258: 0
A259: 001069 | B259: 001051 | C259: MINI PASTEL DE QUEIJO | D259: 002 | E259: 2 | F259: 86.72 | G259: 0 | H259: 0 | I259: 0 | M259: 0
A260: 001070 | B260: 000445 | C260: TOLETE DE PUPUNHA 1,8KG | E260: 0.11 | F260: 0 | G260: 0 | H260: 0 | I260: 0 | M260: 0
A261: 001070 | B261: 000614 | C261: SAL REFINADO | E261: 0.001 | F261: 0 | G261: 0 | H261: 0 | I261: 0 | M261: 0
A262: 001070 | B262: 000667 | C262: TOMILHO | E262: 0.005 | F262: 0 | G262: 0 | H262: 0 | I262: 0 | M262: 0
A263: 001072 | B263: 000290 | C263: ESPETO COSTELINHA BOVINA | E263: 1 | F263: 0 | G263: 0 | H263: 0 | I263: 0 | M263: 0
A264: 001078 | B264: 000318 | C264: TONICA COMUM LATA | E264: 0.5 | F264: 0 | G264: 0 | H264: 0 | I264: 0 | M264: 0
A265: 001078 | B265: 000492 | C265: LIMAO TAITI FRUTA | E265: 0.05 | F265: 0 | G265: 0 | H265: 0 | I265: 0 | M265: 0
A266: 001078 | B266: 000668 | C266: ALECRIM | E266: 0.015 | F266: 0 | G266: 0 | H266: 0 | I266: 0 | M266: 0
A267: 001078 | B267: 001173 | C267: ZIMBRO | E267: 0.003 | F267: 0 | G267: 0 | H267: 0 | I267: 0 | M267: 0
A268: 001081 | B268: 000453 | C268: CANELA EM PAU (4CM) | E268: 0.01 | F268: 0 | G268: 0 | H268: 0 | I268: 0 | M268: 0
A269: 001081 | B269: 000490 | C269: LARANJA PERA FRUTA | E269: 0.12 | F269: 0 | G269: 0 | H269: 0 | I269: 0 | M269: 0
A270: 001081 | B270: 000749 | C270: RED BULL TROPICAL | E270: 1 | F270: 0 | G270: 0 | H270: 0 | I270: 0 | M270: 0
A271: 001082 | B271: 000292 | C271: ESPETO TULIPA | E271: 1 | F271: 0 | G271: 0 | H271: 0 | I271: 0 | M271: 0
... A617: 002023 | B617: 002068 | C617: MANTEIGA S/SAL 5KG | E617: 0.005 | F617: 0 | G617: 0 | H617: 0 | I617: 0 | M617: 0
A618: 002023 | B618: 002068 | C618: MANTEIGA S/SAL 5KG | D618: 001 | E618: 0.004 | F618: 0 | G618: 0 | H618: 0 | I618: 0 | M618: 0
A619: 002023 | B619: 002070 | C619: ALHO PORO | E619: 0.004 | F619: 0 | G619: 0 | H619: 0 | I619: 0 | M619: 0
A620: 002024 | B620: 000286 | C620: ESPETO BOVINO | E620: 4 | F620: 16513.59 | G620: 0 | H620: 0 | I620: 0 | M620: 0
A621: 002024 | B621: 000288 | C621: ESPETO CALABRESA S/ PIMENTA | E621: 3 | F621: 3320.34 | G621: 0 | H621: 0 | I621: 0 | M621: 0
A622: 002024 | B622: 000289 | C622: ESPETO CORACAO | E622: 3 | F622: 22784.8 | G622: 0 | H622: 0 | I622: 0 | M622: 0
A623: 002024 | B623: 000291 | C623: ESPETO FRANGO | E623: 4 | F623: 991.75 | G623: 0 | H623: 0 | I623: 0 | M623: 0
A624: 002024 | B624: 000296 | C624: ESPETO FILE MIGNON | E624: 4 | F624: 5713.51 | G624: 0 | H624: 0 | I624: 0 | M624: 0
A625: 002024 | B625: 000331 | C625: BARRIL CHOPP BRAHMA CLARO 50LT | E625: 0.003 | F625: 0 | G625: 0 | H625: 0 | I625: 0 | M625: 0
A626: 002024 | B626: 000377 | C626: ARROZ TIPO 1 | E626: 0.06 | F626: 0 | G626: 0 | H626: 0 | I626: 0 | M626: 0
A627: 002024 | B627: 000390 | C627: FARINHA DE TRIGO SOL | E627: 0.002 | F627: 0 | G627: 0 | H627: 0 | I627: 0 | M627: 0
A628: 002024 | B628: 000412 | C628: OLEO DE SOJA LIZA 900ML | E628: 0.059 | F628: 0 | G628: 0 | H628: 0 | I628: 0 | M628: 0
A629: 002024 | B629: 000414 | C629: PIMENTA DO REINO MOIDA | E629: 0.0006 | F629: 0 | G629: 0 | H629: 0 | I629: 0 | M629: 0
A630: 002024 | B630: 000424 | C630: VINAGRE AGRIN BRANCO NEVAL GARRAFA 750ML | E630: 0.007 | F630: 0 | G630: 0 | H630: 0 | I630: 0 | M630: 0
... A1162: 010379 | B1162: 002219 | C1162: BATATA WEDGERS RUSTICA - MCCAIN | E1162: 0.28 | F1162: 0 | G1162: 0 | H1162: 0 | I1162: 0 | M1162: 0

Sheet Fichas Flat
A1: Categoria | B1: Subcategoria | C1: Nome do PA | D1: Estrutura criada | E1: Código PA | F1: Cód. Componente | G1: Descrição Componente | H1: Qtd | I1: Und. | J1: Custo Unit. (R$) | K1: Custo Ingr. (R$) | L1: Preço Venda (R$) | M1: CMV (%) | N1: Observação
A2: Espetos | B2: Veggie | C2: Abóbora Assada | D2: =IF(ISERROR(VLOOKUP(E2,'Estrutura Protheus'!A:A,1,FALSE)),"Não","Sim") | E2: 002124 | F2: 000624 | G2: Abobora Japonesa | H2: 0.12 | I2: KG | J2: =IFERROR(VLOOKUP(F2,'Base Insumos'!$A:$C,3,FALSE()),"PENDENTE") | K2: =IFERROR(IF(J2="PENDENTE",0,J2*H2),0) | L2: 10.99 | M2: =IFERROR(K2/L2,0)
A3: Espetos | B3: Veggie | C3: Abobrinha Grelhada | D3: =IF(ISERROR(VLOOKUP(E3,'Estrutura Protheus'!A:A,1,FALSE)),"Não","Sim") | E3: 001508 | F3: 000459 | G3: Abobrinha Italiana | H3: 0.1 | I3: KG | J3: =IFERROR(VLOOKUP(F3,'Base Insumos'!$A:$C,3,FALSE()),"PENDENTE") | K3: =IFERROR(IF(J3="PENDENTE",0,J3*H3),0) | L3: 10.99 | M3: =IFERROR(K3/L3,0)
A4: Espetos | B4: Veggie | C4: Batata Bolinha | D4: =IF(ISERROR(VLOOKUP(E4,'Estrutura Protheus'!A:A,1,FALSE)),"Não","Sim") | E4: 001507 | F4: 000464 | G4: Batata Bolinha | H4: 0.1 | I4: KG | J4: =IFERROR(VLOOKUP(F4,'Base Insumos'!$A:$C,3,FALSE()),"PENDENTE") | K4: =IFERROR(IF(J4="PENDENTE",0,J4*H4),0) | L4: 10.99 | M4: =IFERROR(K4/L4,0)
A5: Espetos | B5: Veggie | C5: Berinjela Grelhada | D5: =IF(ISERROR(VLOOKUP(E5,'Estrutura Protheus'!A:A,1,FALSE)),"Não","Sim") | E5: 001505 | F5: 000466 | G5: Berinjela | H5: 0.1 | I5: KG | J5: =IFERROR(VLOOKUP(F5,'Base Insumos'!$A:$C,3,FALSE()),"PENDENTE") | K5: =IFERROR(IF(J5="PENDENTE",0,J5*H5),0) | L5: 10.99 | M5: =IFERROR(K5/L5,0)
A6: Espetos | B6: Premium | C6: Bolinho de Bacalhau | D6: =IF(ISERROR(VLOOKUP(E6,'Estrutura Protheus'!A:A,1,FALSE)),"Não","Sim") | E6: 000766 | F6: 000305 | G6: Bolinho de Bacalhau | H6: 4 | I6: UN | J6: =IFERROR(VLOOKUP(F6,'Base Insumos'!$A:$C,3,FALSE()),"PENDENTE") | K6: =IFERROR(IF(J6="PENDENTE",0,J6*H6),0) | L6: 14.99 | M6: =IFERROR(K6/L6,0)
A7: Espetos | B7: Boteco no Espeto | C7: Bolinho de Queijo | D7: =IF(ISERROR(VLOOKUP(E7,'Estrutura Protheus'!A:A,1,FALSE)),"Não","Sim") | E7: 000769 | F7: 000304 | G7: Bolinho de Queijo | H7: 4 | I7: UN | J7: =IFERROR(VLOOKUP(F7,'Base Insumos'!$A:$C,3,FALSE()),"PENDENTE") | K7: =IFERROR(IF(J7="PENDENTE",0,J7*H7),0) | L7: 14.99 | M7: =IFERROR(K7/L7,0)
A8: Espetos | B8: In Natura | C8: Bovino | D8: =IF(ISERROR(VLOOKUP(E8,'Estrutura Protheus'!A:A,1,FALSE)),"Não","Sim") | E8: 000001 | F8: 000286 | G8: Espeto Bovino | H8: 7 | I8: UN | J8: =IFERROR(VLOOKUP(F8,'Base Insumos'!$A:$C,3,FALSE()),"PENDENTE") | K8: =IFERROR(IF(J8="PENDENTE",0,J8*H8),0) | L8: 29.9 | M8: =IFERROR(K8/L8,0)
A9: Espetos | B9: Tradicional | C9: Calabresa com Pimenta | D9: =IF(ISERROR(VLOOKUP(E9,'Estrutura Protheus'!A:A,1,FALSE)),"Não","Sim") | E9: 000021 | F9: 000287 | G9: Espeto Calabresa c/ Pimenta | H9: 1 | I9: UN | J9: =IFERROR(VLOOKUP(F9,'Base Insumos'!$A:$C,3,FALSE()),"PENDENTE") | K9: =IFERROR(IF(J9="PENDENTE",0,J9*H9),0) | L9: 13.99 | M9: =IFERROR(K9/L9,0)
A10: Espetos | B10: In Natura | C10: Calabresa com Pimenta | D10: =IF(ISERROR(VLOOKUP(E10,'Estrutura Protheus'!A:A,1,FALSE)),"Não","Sim") | E10: 000002 | F10: 000287 | G10: Espeto Calabresa c/ Pimenta | H10: 6 | I10: UN | J10: =IFERROR(VLOOKUP(F10,'Base Insumos'!$A:$C,3,FALSE()),"PENDENTE") | K10: =IFERROR(IF(J10="PENDENTE",0,J10*H10),0) | L10: 34.9 | M10: =IFERROR(K10/L10,0)
A11: Espetos | B11: Tradicional | C11: Calabresa sem Pimenta | D11: =IF(ISERROR(VLOOKUP(E11,'Estrutura Protheus'!A:A,1,FALSE)),"Não","Sim") | E11: 000022 | F11: 000288 | G11: Espeto Calabresa s/ Pimenta | H11: 1 | I11: UN | J11: =IFERROR(VLOOKUP(F11,'Base Insumos'!$A:$C,3,FALSE()),"PENDENTE") | K11: =IFERROR(IF(J11="PENDENTE",0,J11*H11),0) | L11: 13.99 | M11: =IFERROR(K11/L11,0)
A12: Espetos | B12: In Natura | C12: Calabresa sem Pimenta | D12: =IF(ISERROR(VLOOKUP(E12,'Estrutura Protheus'!A:A,1,FALSE)),"Não","Sim") | E12: 000003 | F12: 000288 | G12: Espeto Calabresa s/ Pimenta | H12: 6 | I12: UN | J12: =IFERROR(VLOOKUP(F12,'Base Insumos'!$A:$C,3,FALSE()),"PENDENTE") | K12: =IFERROR(IF(J12="PENDENTE",0,J12*H12),0) | L12: 34.9 | M12: =IFERROR(K12/L12,0)
A13: Espetos | B13: Premium | C13: Camarão | D13: =IF(ISERROR(VLOOKUP(E13,'Estrutura Protheus'!A:A,1,FALSE)),"Não","Sim") | E13: 000364 | F13: 000302 | G13: Espeto Camarao Comum | H13: 1 | I13: UN | J13: =IFERROR(VLOOKUP(F13,'Base Insumos'!$A:$C,3,FALSE()),"PENDENTE") | K13: =IFERROR(IF(J13="PENDENTE",0,J13*H13),0) | L13: 19.99 | M13: =IFERROR(K13/L13,0)
... A42: Espetos | B42: Direto da Fazenda | C42: Queijo Coalho | D42: =IF(ISERROR(VLOOKUP(E42,'Estrutura Protheus'!A:A,1,FALSE)),"Não","Sim") | E42: 000282 | F42: 000439 | G42: Espeto Queijo Coalho | H42: 0.06 | I42: KG | J42: =IFERROR(VLOOKUP(F42,'Base Insumos'!$A:$C,3,FALSE()),"PENDENTE") | K42: =IFERROR(IF(J42="PENDENTE",0,J42*H42),0) | L42: 13.99 | M42: =IFERROR(K42/L42,0)
A43: Espetos | B43: In Natura | C43: Queijo Coalho | D43: =IF(ISERROR(VLOOKUP(E43,'Estrutura Protheus'!A:A,1,FALSE)),"Não","Sim") | E43: 000008 | F43: 000439 | G43: Espeto Queijo Coalho | H43: =0.06*7 | I43: KG | J43: =IFERROR(VLOOKUP(F43,'Base Insumos'!$A:$C,3,FALSE()),"PENDENTE") | K43: =IFERROR(IF(J43="PENDENTE",0,J43*H43),0) | L43: 29.9 | M43: =IFERROR(K43/L43,0)
A44: Espetos | B44: Tradicional | C44: Salsichão | D44: =IF(ISERROR(VLOOKUP(E44,'Estrutura Protheus'!A:A,1,FALSE)),"Não","Sim") | E44: 000027 | F44: 000298 | G44: Espeto Salsichao | H44: 1 | I44: UN | J44: =IFERROR(VLOOKUP(F44,'Base Insumos'!$A:$C,3,FALSE()),"PENDENTE") | K44: =IFERROR(IF(J44="PENDENTE",0,J44*H44),0) | L44: 14.99 | M44: =IFERROR(K44/L44,0)
A45: Espetos | B45: Premium | C45: Salsichão c/ Provolone | D45: =IF(ISERROR(VLOOKUP(E45,'Estrutura Protheus'!A:A,1,FALSE)),"Não","Sim") | E45: 000765 | F45: 000301 | G45: Espeto Salsichao c/ Provolone | H45: 1 | I45: UN | J45: =IFERROR(VLOOKUP(F45,'Base Insumos'!$A:$C,3,FALSE()),"PENDENTE") | K45: =IFERROR(IF(J45="PENDENTE",0,J45*H45),0) | L45: 17.99 | M45: =IFERROR(K45/L45,0)
A46: Espetos | B46: Boteco no Espeto | C46: Sticks de Muçarela | D46: =IF(ISERROR(VLOOKUP(E46,'Estrutura Protheus'!A:A,1,FALSE)),"Não","Sim") | E46: 001472 | F46: 001580 | G46: Palito Mussarela 1kg | H46: 0.1 | I46: KG | J46: =IFERROR(VLOOKUP(F46,'Base Insumos'!$A:$C,3,FALSE()),"PENDENTE") | K46: =IFERROR(IF(J46="PENDENTE",0,J46*H46),0) | L46: 14.99 | M46: =IFERROR(K46/L46,0)
A47: Espetos | B47: Premium | C47: Tulipa | D47: =IF(ISERROR(VLOOKUP(E47,'Estrutura Protheus'!A:A,1,FALSE)),"Não","Sim") | E47: 001082 | F47: 000292 | G47: Espeto Tulipa | H47: 1 | I47: UN | J47: =IFERROR(VLOOKUP(F47,'Base Insumos'!$A:$C,3,FALSE()),"PENDENTE") | K47: =IFERROR(IF(J47="PENDENTE",0,J47*H47),0) | L47: 13.99 | M47: =IFERROR(K47/L47,0)
A48: Espetos | B48: In Natura | C48: Tulipa | D48: =IF(ISERROR(VLOOKUP(E48,'Estrutura Protheus'!A:A,1,FALSE)),"Não","Sim") | E48: 000010 | F48: 000292 | G48: Espeto Tulipa | H48: 5 | I48: UN | J48: =IFERROR(VLOOKUP(F48,'Base Insumos'!$A:$C,3,FALSE()),"PENDENTE") | K48: =IFERROR(IF(J48="PENDENTE",0,J48*H48),0) | L48: 29.9 | M48: =IFERROR(K48/L48,0)
A49: Espetos | B49: Espetos | C49: Dadinho de Tapioca | D49: =IF(ISERROR(VLOOKUP(E49,'Estrutura Protheus'!A:A,1,FALSE)),"Não","Sim") | E49: 001254 | F49: 001250 | G49: Dadinho de Tapioca 0,750gr | H49: 0.1 | I49: KG | J49: =IFERROR(VLOOKUP(F49,'Base Insumos'!$A:$C,3,FALSE()),"PENDENTE") | K49: =IFERROR(IF(J49="PENDENTE",0,J49*H49),0) | L49: 15.99 | M49: =IFERROR(K49/L49,0)
A50: Espetos | B50: Espetos | C50: Dadinho de Tapioca | D50: =IF(ISERROR(VLOOKUP(E50,'Estrutura Protheus'!A:A,1,FALSE)),"Não","Sim") | E50: 001254 | F50: 000440 | G50: Não Encontrado na Base | H50: 0.02 | J50: =IFERROR(VLOOKUP(F50,'Base Insumos'!$A:$C,3,FALSE()),"PENDENTE") | K50: =IFERROR(IF(J50="PENDENTE",0,J50*H50),0) | L50: 15.99 | M50: =IFERROR(K50/L50,0)
A51: Espetos | B51: Espetos | C51: Dadinho de Tapioca | D51: =IF(ISERROR(VLOOKUP(E51,'Estrutura Protheus'!A:A,1,FALSE)),"Não","Sim") | E51: 001254 | F51: 001251 | G51: Geleia de Pimenta 1,2kg | H51: 0.005 | I51: KG | J51: =IFERROR(VLOOKUP(F51,'Base Insumos'!$A:$C,3,FALSE()),"PENDENTE") | K51: =IFERROR(IF(J51="PENDENTE",0,J51*H51),0) | L51: 15.99 | M51: =IFERROR(K51/L51,0)
A52: Espetos | B52: Espetos | C52: Espeto de Alho Poró com Tomate Cereja | D52: =IF(ISERROR(VLOOKUP(E52,'Estrutura Protheus'!A:A,1,FALSE)),"Não","Sim") | E52: 002122 | F52: 002070 | G52: Alho Poro | H52: 0.1 | I52: KG | J52: =IFERROR(VLOOKUP(F52,'Base Insumos'!$A:$C,3,FALSE()),"PENDENTE") | K52: =IFERROR(IF(J52="PENDENTE",0,J52*H52),0) | L52: 12.99 | M52: =IFERROR(K52/L52,0)
A53: Espetos | B53: Espetos | C53: Espeto de Alho Poró com Tomate Cereja | D53: =IF(ISERROR(VLOOKUP(E53,'Estrutura Protheus'!A:A,1,FALSE)),"Não","Sim") | E53: 002122 | F53: 000485 | G53: Tomate Cereja | H53: 0.04 | I53: KG | J53: =IFERROR(VLOOKUP(F53,'Base Insumos'!$A:$C,3,FALSE()),"PENDENTE") | K53: =IFERROR(IF(J53="PENDENTE",0,J53*H53),0) | L53: 12.99 | M53: =IFERROR(K53/L53,0)
A54: Espetos | B54: Espetos | C54: Espeto de Berinjela no Shoyu | D54: =IF(ISERROR(VLOOKUP(E54,'Estrutura Protheus'!A:A,1,FALSE)),"Não","Sim") | E54: 002125 | F54: 000466 | G54: Berinjela | H54: 0.12 | I54: KG | J54: =IFERROR(VLOOKUP(F54,'Base Insumos'!$A:$C,3,FALSE()),"PENDENTE") | K54: =IFERROR(IF(J54="PENDENTE",0,J54*H54),0) | L54: 12.99 | M54: =IFERROR(K54/L54,0)
A55: Espetos | B55: Espetos | C55: Espeto de Mussarela de Búfala com Rucula e Tomate Seco | D55: =IF(ISERROR(VLOOKUP(E55,'Estrutura Protheus'!A:A,1,FALSE)),"Não","Sim") | E55: 000279 | F55: 000442 | G55: Mussarela de Bufala | H55: 0.07 | I55: KG | J55: =IFERROR(VLOOKUP(F55,'Base Insumos'!$A:$C,3,FALSE()),"PENDENTE") | K55: =IFERROR(IF(J55="PENDENTE",0,J55*H55),0) | L55: 14.99 | M55: =IFERROR(K55/L55,0)
A56: Espetos | B56: Espetos | C56: Espeto de Mussarela de Búfala com Rucula e Tomate Seco | D56: =IF(ISERROR(VLOOKUP(E56,'Estrutura Protheus'!A:A,1,FALSE)),"Não","Sim") | E56: 000279 | F56: 000440 | G56: Não Encontrado na Base | H56: 0.02 | J56: =IFERROR(VLOOKUP(F56,'Base Insumos'!$A:$C,3,FALSE()),"PENDENTE") | K56: =IFERROR(IF(J56="PENDENTE",0,J56*H56),0) | L56: 14.99 | M56: =IFERROR(K56/L56,0)
A57: Espetos | B57: Espetos | C57: Espeto de Mussarela de Búfala com Rucula e Tomate Seco | D57: =IF(ISERROR(VLOOKUP(E57,'Estrutura Protheus'!A:A,1,FALSE)),"Não","Sim") | E57: 000279 | F57: 000444 | G57: Tomate Seco | H57: 0.025 | I57: KG | J57: =IFERROR(VLOOKUP(F57,'Base Insumos'!$A:$C,3,FALSE()),"PENDENTE") | K57: =IFERROR(IF(J57="PENDENTE",0,J57*H57),0) | L57: 14.99 | M57: =IFERROR(K57/L57,0)
A58: Espetos | B58: Espetos | C58: Espeto de Pupunha com Tomate Seco e Rúcula | D58: =IF(ISERROR(VLOOKUP(E58,'Estrutura Protheus'!A:A,1,FALSE)),"Não","Sim") | E58: 000280 | F58: 000445 | G58: Tolete de Pupunha 1,8kg | H58: 0.09 | I58: KG | J58: =IFERROR(VLOOKUP(F58,'Base Insumos'!$A:$C,3,FALSE()),"PENDENTE") | K58: =IFERROR(IF(J58="PENDENTE",0,J58*H58),0) | L58: 18.99 | M58: =IFERROR(K58/L58,0)
A59: Espetos | B59: Espetos | C59: Espeto de Pupunha com Tomate Seco e Rúcula | D59: =IF(ISERROR(VLOOKUP(E59,'Estrutura Protheus'!A:A,1,FALSE)),"Não","Sim") | E59: 000280 | F59: 000407 | G59: Molho Salada Ervas Finas 236ml | H59: 0.01 | I59: UN | J59: =IFERROR(VLOOKUP(F59,'Base Insumos'!$A:$C,3,FALSE()),"PENDENTE") | K59: =IFERROR(IF(J59="PENDENTE",0,J59*H59),0) | L59: 18.99 | M59: =IFERROR(K59/L59,0)
A60: Espetos | B60: Espetos | C60: Espeto de Pupunha com Tomate Seco e Rúcula | D60: =IF(ISERROR(VLOOKUP(E60,'Estrutura Protheus'!A:A,1,FALSE)),"Não","Sim") | E60: 000280 | F60: 000444 | G60: Tomate Seco | H60: 0.025 | I60: KG | J60: =IFERROR(VLOOKUP(F60,'Base Insumos'!$A:$C,3,FALSE()),"PENDENTE") | K60: =IFERROR(IF(J60="PENDENTE",0,J60*H60),0) | L60: 18.99 | M60: =IFERROR(K60/L60,0)
A61: Espetos | B61: Espetos | C61: Espeto de Pupunha com Tomate Seco e Rúcula | D61: =IF(ISERROR(VLOOKUP(E61,'Estrutura Protheus'!A:A,1,FALSE)),"Não","Sim") | E61: 000280 | F61: 000483 | G61: Rucula Hidroponica | H61: 0.01 | I61: KG | J61: =IFERROR(VLOOKUP(F61,'Base Insumos'!$A:$C,3,FALSE()),"PENDENTE") | K61: =IFERROR(IF(J61="PENDENTE",0,J61*H61),0) | L61: 18.99 | M61: =IFERROR(K61/L61,0)
A62: Espetos | B62: Espetos | C62: Pupunha na Brasa | D62: =IF(ISERROR(VLOOKUP(E62,'Estrutura Protheus'!A:A,1,FALSE)),"Não","Sim") | E62: 001070 | F62: 000445 | G62: Tolete de Pupunha 1,8kg | H62: 0.11 | I62: KG | J62: =IFERROR(VLOOKUP(F62,'Base Insumos'!$A:$C,3,FALSE()),"PENDENTE") | K62: =IFERROR(IF(J62="PENDENTE",0,J62*H62),0) | L62: 16.99 | M62: =IFERROR(K62/L62,0)
A63: Espetos | B63: Espetos | C63: Pupunha na Brasa | D63: =IF(ISERROR(VLOOKUP(E63,'Estrutura Protheus'!A:A,1,FALSE)),"Não","Sim") | E63: 001070 | F63: 000667 | G63: Tomilho | H63: 0.005 | I63: KG | J63: =IFERROR(VLOOKUP(F63,'Base Insumos'!$A:$C,3,FALSE()),"PENDENTE") | K63: =IFERROR(IF(J63="PENDENTE",0,J63*H63),0) | L63: 16.99 | M63: =IFERROR(K63/L63,0)
A64: Espetos | B64: Espetos | C64: Pupunha na Brasa | D64: =IF(ISERROR(VLOOKUP(E64,'Estrutura Protheus'!A:A,1,FALSE)),"Não","Sim") | E64: 001070 | F64: 000614 | G64: Sal Refinado | H64: 0.0008 | I64: KG | J64: =IFERROR(VLOOKUP(F64,'Base Insumos'!$A:$C,3,FALSE()),"PENDENTE") | K64: =IFERROR(IF(J64="PENDENTE",0,J64*H64),0) | L64: 16.99 | M64: =IFERROR(K64/L64,0)
A65: Espetos | B65: Espetos | C65: Ratatouile no Espeto | D65: =IF(ISERROR(VLOOKUP(E65,'Estrutura Protheus'!A:A,1,FALSE)),"Não","Sim") | E65: 002123 | F65: 000753 | G65: Cebola Roxa | H65: 0.05 | I65: KG | J65: =IFERROR(VLOOKUP(F65,'Base Insumos'!$A:$C,3,FALSE()),"PENDENTE") | K65: =IFERROR(IF(J65="PENDENTE",0,J65*H65),0) | L65: 11.9 | M65: =IFERROR(K65/L65,0)
A66: Espetos | B66: Espetos | C66: Ratatouile no Espeto | D66: =IF(ISERROR(VLOOKUP(E66,'Estrutura Protheus'!A:A,1,FALSE)),"Não","Sim") | E66: 002123 | F66: 000486 | G66: Tomate Salada | H66: 0.025 | I66: KG | J66: =IFERROR(VLOOKUP(F66,'Base Insumos'!$A:$C,3,FALSE()),"PENDENTE") | K66: =IFERROR(IF(J66="PENDENTE",0,J66*H66),0) | L66: 11.9 | M66: =IFERROR(K66/L66,0)
A67: Espetos | B67: Espetos | C67: Ratatouile no Espeto | D67: =IF(ISERROR(VLOOKUP(E67,'Estrutura Protheus'!A:A,1,FALSE)),"Não","Sim") | E67: 002123 | F67: 000459 | G67: Abobrinha Italiana | H67: 0.025 | I67: KG | J67: =IFERROR(VLOOKUP(F67,'Base Insumos'!$A:$C,3,FALSE()),"PENDENTE") | K67: =IFERROR(IF(J67="PENDENTE",0,J67*H67),0) | L67: 11.9 | M67: =IFERROR(K67/L67,0)
A68: Espetos | B68: Espetos | C68: Ratatouile no Espeto | D68: =IF(ISERROR(VLOOKUP(E68,'Estrutura Protheus'!A:A,1,FALSE)),"Não","Sim") | E68: 002123 | F68: 000617 | G68: Pimentao Amarelo | H68: 0.025 | I68: KG | J68: =IFERROR(VLOOKUP(F68,'Base Insumos'!$A:$C,3,FALSE()),"PENDENTE") | K68: =IFERROR(IF(J68="PENDENTE",0,J68*H68),0) | L68: 11.9 | M68: =IFERROR(K68/L68,0)
... A72: Espetos | B72: Espetos | C72: Espeto de Shimeji | D72: =IF(ISERROR(VLOOKUP(E72,'Estrutura Protheus'!A:A,1,FALSE)),"Não","Sim") | E72: 001470 | F72: 000667 | G72: Tomilho | H72: 0.005 | I72: KG | J72: =IFERROR(VLOOKUP(F72,'Base Insumos'!$A:$C,3,FALSE()),"PENDENTE") | K72: =IFERROR(IF(J72="PENDENTE",0,J72*H72),0) | L72: 15.99 | M72: =IFERROR(K72/L72,0)
A73: Espetos | B73: Espetos | C73: Espeto de Shimeji | D73: =IF(ISERROR(VLOOKUP(E73,'Estrutura Protheus'!A:A,1,FALSE)),"Não","Sim") | E73: 001470 | F73: 000440 | G73: Não Encontrado na Base | H73: 0.02 | J73: =IFERROR(VLOOKUP(F73,'Base Insumos'!$A:$C,3,FALSE()),"PENDENTE") | K73: =IFERROR(IF(J73="PENDENTE",0,J73*H73),0) | L73: 15.99 | M73: =IFERROR(K73/L73,0)
A74: Espetos | B74: Espetos | C74: Espeto de Shimeji | D74: =IF(ISERROR(VLOOKUP(E74,'Estrutura Protheus'!A:A,1,FALSE)),"Não","Sim") | E74: 001470 | F74: 002068 | G74: Manteiga S/sal 5kg | H74: 0.05 | I74: KG | J74: =IFERROR(VLOOKUP(F74,'Base Insumos'!$A:$C,3,FALSE()),"PENDENTE") | K74: =IFERROR(IF(J74="PENDENTE",0,J74*H74),0) | L74: 15.99 | M74: =IFERROR(K74/L74,0)
A75: Bebidas Frias | B75: Vinhos - Tinto | C75: Antares Carmenere, 2020 | D75: =IF(ISERROR(VLOOKUP(E75,'Estrutura Protheus'!A:A,1,FALSE)),"Não","Sim") | E75: 000281 | F75: 000371 | G75: Vinho Antares Carmenere 750ml | H75: 1 | I75: UN | J75: =IFERROR(VLOOKUP(F75,'Base Insumos'!$A:$C,3,FALSE()),"PENDENTE") | K75: =IFERROR(IF(J75="PENDENTE",0,J75*H75),0) | L75: 118.99 | M75: =IFERROR(K75/L75,0)
A76: Bebidas Frias | B76: Vinhos - Espumante | C76: Chandon Rose | D76: =IF(ISERROR(VLOOKUP(E76,'Estrutura Protheus'!A:A,1,FALSE)),"Não","Sim") | E76: 001147 | F76: 001139 | G76: Espumante Chandon Rose 750 Ml | H76: 1 | I76: UN | J76: =IFERROR(VLOOKUP(F76,'Base Insumos'!$A:$C,3,FALSE()),"PENDENTE") | K76: =IFERROR(IF(J76="PENDENTE",0,J76*H76),0) | L76: 239.99 | M76: =IFERROR(K76/L76,0)
A77: Bebidas Frias | B77: Vinhos - Espumante | C77: Espumante Brasileiro Viva La Vida Brut 750ml | D77: =IF(ISERROR(VLOOKUP(E77,'Estrutura Protheus'!A:A,1,FALSE)),"Não","Sim") | E77: 010032 | F77: 009537 | G77: Espumante Brasileiro Viva La Vida Brut 750ml | H77: 1 | I77: UN | J77: =IFERROR(VLOOKUP(F77,'Base Insumos'!$A:$C,3,FALSE()),"PENDENTE") | K77: =IFERROR(IF(J77="PENDENTE",0,J77*H77),0) | L77: 135.99 | M77: =IFERROR(K77/L77,0)
A78: Bebidas Frias | B78: Vinhos - Branco | C78: Norton Porteño Chardonay | D78: =IF(ISERROR(VLOOKUP(E78,'Estrutura Protheus'!A:A,1,FALSE)),"Não","Sim") | E78: 001391 | F78: 001387 | G78: Vinho Argentino Norton Porteno Chardonnay 750ml | H78: 1 | I78: UN | J78: =IFERROR(VLOOKUP(F78,'Base Insumos'!$A:$C,3,FALSE()),"PENDENTE") | K78: =IFERROR(IF(J78="PENDENTE",0,J78*H78),0) | L78: 99.99 | M78: =IFERROR(K78/L78,0)
A79: Bebidas Frias | B79: Vinhos - Tinto | C79: Norton Porteño Malbec | D79: =IF(ISERROR(VLOOKUP(E79,'Estrutura Protheus'!A:A,1,FALSE)),"Não","Sim") | E79: 001392 | F79: 001388 | G79: Vinho Argentino Norton Porteno Malbec 750ml | H79: 1 | I79: UN | J79: =IFERROR(VLOOKUP(F79,'Base Insumos'!$A:$C,3,FALSE()),"PENDENTE") | K79: =IFERROR(IF(J79="PENDENTE",0,J79*H79),0) | L79: 99.99 | M79: =IFERROR(K79/L79,0)
A80: Bebidas Frias | B80: Vinhos - Branco | C80: Villa Fabrizia Lambrusco | D80: =IF(ISERROR(VLOOKUP(E80,'Estrutura Protheus'!A:A,1,FALSE)),"Não","Sim") | E80: 000283 | F80: 000503 | G80: Não Encontrado na Base | H80: 1 | J80: =IFERROR(VLOOKUP(F80,'Base Insumos'!$A:$C,3,FALSE()),"PENDENTE") | K80: =IFERROR(IF(J80="PENDENTE",0,J80*H80),0) | L80: 135.99 | M80: =IFERROR(K80/L80,0)
A81: Bebidas Frias | B81: Cerveja | C81: Beck's Garrafa | D81: =IF(ISERROR(VLOOKUP(E81,'Estrutura Protheus'!A:A,1,FALSE)),"Não","Sim") | E81: 001017 | F81: 001016 | G81: Cerveja Becks 600 Ml | H81: 1 | I81: UN | J81: =IFERROR(VLOOKUP(F81,'Base Insumos'!$A:$C,3,FALSE()),"PENDENTE") | K81: =IFERROR(IF(J81="PENDENTE",0,J81*H81),0) | L81: 21.99 | M81: =IFERROR(K81/L81,0)
A82: Bebidas Frias | B82: Cerveja | C82: Beck's Long Neck | D82: =IF(ISERROR(VLOOKUP(E82,'Estrutura Protheus'!A:A,1,FALSE)),"Não","Sim") | E82: 001333 | F82: 001049 | G82: Cerveja Becks Long Neck | H82: 1 | I82: UN | J82: =IFERROR(VLOOKUP(F82,'Base Insumos'!$A:$C,3,FALSE()),"PENDENTE") | K82: =IFERROR(IF(J82="PENDENTE",0,J82*H82),0) | L82: 14.99 | M82: =IFERROR(K82/L82,0)
A83: Bebidas Frias | B83: Cerveja | C83: Brahma Duplo Malte Garrafa | D83: =IF(ISERROR(VLOOKUP(E83,'Estrutura Protheus'!A:A,1,FALSE)),"Não","Sim") | E83: 001057 | F83: 001052 | G83: Cerveja Brahma Duplo Malte 600 Ml | H83: 1 | I83: UN | J83: =IFERROR(VLOOKUP(F83,'Base Insumos'!$A:$C,3,FALSE()),"PENDENTE") | K83: =IFERROR(IF(J83="PENDENTE",0,J83*H83),0) | L83: 17.9 | M83: =IFERROR(K83/L83,0)
A84: Bebidas Frias | B84: Cerveja | C84: Budweiser Long Neck | D84: =IF(ISERROR(VLOOKUP(E84,'Estrutura Protheus'!A:A,1,FALSE)),"Não","Sim") | E84: 000904 | F84: 000326 | G84: Budweiser Long Neck | H84: 1 | I84: UN | J84: =IFERROR(VLOOKUP(F84,'Base Insumos'!$A:$C,3,FALSE()),"PENDENTE") | K84: =IFERROR(IF(J84="PENDENTE",0,J84*H84),0) | L84: 13.99 | M84: =IFERROR(K84/L84,0)
A85: Bebidas Frias | B85: Cerveja | C85: Budweiser Long Neck Zero | D85: =IF(ISERROR(VLOOKUP(E85,'Estrutura Protheus'!A:A,1,FALSE)),"Não","Sim") | E85: 001347 | F85: 001346 | G85: Budweiser Zero Long Neck | H85: 1 | I85: UN | J85: =IFERROR(VLOOKUP(F85,'Base Insumos'!$A:$C,3,FALSE()),"PENDENTE") | K85: =IFERROR(IF(J85="PENDENTE",0,J85*H85),0) | L85: 13.99 | M85: =IFERROR(K85/L85,0)
A86: Bebidas Frias | B86: Cerveja | C86: Cerveja do Quintal IPA Garrafa | D86: =IF(ISERROR(VLOOKUP(E86,'Estrutura Protheus'!A:A,1,FALSE)),"Não","Sim") | E86: 001414 | F86: 001412 | G86: Cerveja Quintal Ipa | H86: 1 | I86: UN | J86: =IFERROR(VLOOKUP(F86,'Base Insumos'!$A:$C,3,FALSE()),"PENDENTE") | K86: =IFERROR(IF(J86="PENDENTE",0,J86*H86),0) | L86: 28.99 | M86: =IFERROR(K86/L86,0)
A87: Bebidas Frias | B87: Cerveja | C87: Cerveja do Quintal Pilsen Garrafa | D87: =IF(ISERROR(VLOOKUP(E87,'Estrutura Protheus'!A:A,1,FALSE)),"Não","Sim") | E87: 001413 | F87: 001411 | G87: Cerveja Quntal Pilsen | H87: 1 | I87: UN | J87: =IFERROR(VLOOKUP(F87,'Base Insumos'!$A:$C,3,FALSE()),"PENDENTE") | K87: =IFERROR(IF(J87="PENDENTE",0,J87*H87),0) | L87: 23.99 | M87: =IFERROR(K87/L87,0)
A88: Bebidas Frias | B88: Cerveja | C88: Corona Garrafa | D88: =IF(ISERROR(VLOOKUP(E88,'Estrutura Protheus'!A:A,1,FALSE)),"Não","Sim") | E88: 001560 | F88: 001784 | G88: Cerveja Corona 600ml - Compras | H88: 1 | I88: UN | J88: =IFERROR(VLOOKUP(F88,'Base Insumos'!$A:$C,3,FALSE()),"PENDENTE") | K88: =IFERROR(IF(J88="PENDENTE",0,J88*H88),0) | L88: 22.99 | M88: =IFERROR(K88/L88,0)
A89: Bebidas Frias | B89: Cerveja | C89: Corona cero | D89: =IF(ISERROR(VLOOKUP(E89,'Estrutura Protheus'!A:A,1,FALSE)),"Não","Sim") | E89: 001660 | F89: 001654 | G89: Corona Extra Zero Long Neck | H89: 1 | I89: UN | J89: =IFERROR(VLOOKUP(F89,'Base Insumos'!$A:$C,3,FALSE()),"PENDENTE") | K89: =IFERROR(IF(J89="PENDENTE",0,J89*H89),0) | L89: 15.99 | M89: =IFERROR(K89/L89,0)
A90: Bebidas Frias | B90: Cerveja | C90: Corona Extra | D90: =IF(ISERROR(VLOOKUP(E90,'Estrutura Protheus'!A:A,1,FALSE)),"Não","Sim") | E90: 000917 | F90: 000203 | G90: Corona Extra Long Neck | H90: 1 | I90: UN | J90: =IFERROR(VLOOKUP(F90,'Base Insumos'!$A:$C,3,FALSE()),"PENDENTE") | K90: =IFERROR(IF(J90="PENDENTE",0,J90*H90),0) | L90: 15.99 | M90: =IFERROR(K90/L90,0)
A91: Bebidas Frias | B91: Cerveja | C91: Malzbier | D91: =IF(ISERROR(VLOOKUP(E91,'Estrutura Protheus'!A:A,1,FALSE)),"Não","Sim") | E91: 000903 | F91: 000324 | G91: Malzbier Long Neck | H91: 1 | I91: UN | J91: =IFERROR(VLOOKUP(F91,'Base Insumos'!$A:$C,3,FALSE()),"PENDENTE") | K91: =IFERROR(IF(J91="PENDENTE",0,J91*H91),0) | L91: 13.99 | M91: =IFERROR(K91/L91,0)
A92: Bebidas Frias | B92: Cerveja | C92: Original 600ml | D92: =IF(ISERROR(VLOOKUP(E92,'Estrutura Protheus'!A:A,1,FALSE)),"Não","Sim") | E92: 000894 | F92: 000310 | G92: Cerveja Original 600ml | H92: 1 | I92: UN | J92: =IFERROR(VLOOKUP(F92,'Base Insumos'!$A:$C,3,FALSE()),"PENDENTE") | K92: =IFERROR(IF(J92="PENDENTE",0,J92*H92),0) | L92: 19.99 | M92: =IFERROR(K92/L92,0)
... A97: Bebidas Frias | B97: Cerveja | C97: Stella s/ glúten | D97: =IF(ISERROR(VLOOKUP(E97,'Estrutura Protheus'!A:A,1,FALSE)),"Não","Sim") | E97: 001389 | F97: 001395 | G97: Stella Long Nec s/ Gluten | H97: 1 | I97: UN | J97: =IFERROR(VLOOKUP(F97,'Base Insumos'!$A:$C,3,FALSE()),"PENDENTE") | K97: =IFERROR(IF(J97="PENDENTE",0,J97*H97),0) | L97: 14.99 | M97: =IFERROR(K97/L97,0)
A98: Bebidas Frias | B98: Bebidas Prontas | C98: Beats Senses | D98: =IF(ISERROR(VLOOKUP(E98,'Estrutura Protheus'!A:A,1,FALSE)),"Não","Sim") | E98: 001336 | F98: 001158 | G98: Skol Beats Senses Long | H98: 1 | I98: UN | J98: =IFERROR(VLOOKUP(F98,'Base Insumos'!$A:$C,3,FALSE()),"PENDENTE") | K98: =IFERROR(IF(J98="PENDENTE",0,J98*H98),0) | L98: PENDENTE | M98: -
A99: Bebidas Frias | B99: Bebidas Prontas | C99: Smirnoff Ice | D99: =IF(ISERROR(VLOOKUP(E99,'Estrutura Protheus'!A:A,1,FALSE)),"Não","Sim") | E99: 000030 | F99: 000367 | G99: Long Smirnoff Ice | H99: 1 | I99: UN | J99: =IFERROR(VLOOKUP(F99,'Base Insumos'!$A:$C,3,FALSE()),"PENDENTE") | K99: =IFERROR(IF(J99="PENDENTE",0,J99*H99),0) | L99: 19.99 | M99: =IFERROR(K99/L99,0)
A100: Bebidas Frias | B100: Vodka | C100: Absolut | D100: =IF(ISERROR(VLOOKUP(E100,'Estrutura Protheus'!A:A,1,FALSE)),"Não","Sim") | E100: 000049 | F100: 000339 | G100: Vodka Absolut Natural 1lt | H100: 1 | I100: LT | J100: =IFERROR(VLOOKUP(F100,'Base Insumos'!$A:$C,3,FALSE()),"PENDENTE") | K100: =IFERROR(IF(J100="PENDENTE",0,J100*H100),0) | L100: PENDENTE | M100: -
A101: Bebidas Frias | B101: Gin | C101: Beefeater London Dry | D101: =IF(ISERROR(VLOOKUP(E101,'Estrutura Protheus'!A:A,1,FALSE)),"Não","Sim") | E101: 000052 | F101: 000353 | G101: Gin Beefeater 750 Ml | H101: 0.75 | I101: LT | J101: =IFERROR(VLOOKUP(F101,'Base Insumos'!$A:$C,3,FALSE()),"PENDENTE") | K101: =IFERROR(IF(J101="PENDENTE",0,J101*H101),0) | L101: 279.99 | M101: =IFERROR(K101/L101,0)
A102: Bebidas Frias | B102: Whiskies | C102: Black Label | D102: =IF(ISERROR(VLOOKUP(E102,'Estrutura Protheus'!A:A,1,FALSE)),"Não","Sim") | E102: 001338 | F102: 001137 | G102: Whisky Johnnie Walker Black Label 1lt | H102: 1 | I102: LT | J102: =IFERROR(VLOOKUP(F102,'Base Insumos'!$A:$C,3,FALSE()),"PENDENTE") | K102: =IFERROR(IF(J102="PENDENTE",0,J102*H102),0) | L102: 239.99 | M102: =IFERROR(K102/L102,0)
A103: Bebidas Frias | B103: Cachaça | C103: Cachaça do Quintal - Mel & Limão | D103: =IF(ISERROR(VLOOKUP(E103,'Estrutura Protheus'!A:A,1,FALSE)),"Não","Sim") | E103: 000957 | F103: 000760 | G103: Cachaca Quintal Mel e Limao 750ml | H103: 0.75 | I103: LT | J103: =IFERROR(VLOOKUP(F103,'Base Insumos'!$A:$C,3,FALSE()),"PENDENTE") | K103: =IFERROR(IF(J103="PENDENTE",0,J103*H103),0) | L103: 119.99 | M103: =IFERROR(K103/L103,0)
A104: Bebidas Frias | B104: Cachaça | C104: Cachaça do Quintal - Ouro | D104: =IF(ISERROR(VLOOKUP(E104,'Estrutura Protheus'!A:A,1,FALSE)),"Não","Sim") | E104: 000955 | F104: 000759 | G104: Cachaca Quintal Ouro 965ml | H104: 0.965 | I104: LT | J104: =IFERROR(VLOOKUP(F104,'Base Insumos'!$A:$C,3,FALSE()),"PENDENTE") | K104: =IFERROR(IF(J104="PENDENTE",0,J104*H104),0) | L104: 119.99 | M104: =IFERROR(K104/L104,0)
A105: Bebidas Frias | B105: Cachaça | C105: Cachaça do Quintal - Prata | D105: =IF(ISERROR(VLOOKUP(E105,'Estrutura Protheus'!A:A,1,FALSE)),"Não","Sim") | E105: 000953 | F105: 000758 | G105: Cachaca Quintal Prata 900ml | H105: 0.9 | I105: LT | J105: =IFERROR(VLOOKUP(F105,'Base Insumos'!$A:$C,3,FALSE()),"PENDENTE") | K105: =IFERROR(IF(J105="PENDENTE",0,J105*H105),0) | L105: 99.99 | M105: =IFERROR(K105/L105,0)
A106: Bebidas Frias | B106: Cachaça | C106: Campari | D106: =IF(ISERROR(VLOOKUP(E106,'Estrutura Protheus'!A:A,1,FALSE)),"Não","Sim") | E106: 000942 | F106: 000345 | G106: Aperitivo Campari 998ml | H106: 0.998 | I106: LT | J106: =IFERROR(VLOOKUP(F106,'Base Insumos'!$A:$C,3,FALSE()),"PENDENTE") | K106: =IFERROR(IF(J106="PENDENTE",0,J106*H106),0) | L106: 139.99 | M106: =IFERROR(K106/L106,0)
A107: Bebidas Frias | B107: Whiskies | C107: Chivas Regal 12 anos | D107: =IF(ISERROR(VLOOKUP(E107,'Estrutura Protheus'!A:A,1,FALSE)),"Não","Sim") | E107: 000050 | F107: 000344 | G107: Chivas Regal 12 Anos 1lt | H107: 1 | I107: LT | J107: =IFERROR(VLOOKUP(F107,'Base Insumos'!$A:$C,3,FALSE()),"PENDENTE") | K107: =IFERROR(IF(J107="PENDENTE",0,J107*H107),0) | L107: 390.99 | M107: =IFERROR(K107/L107,0)
A108: Bebidas Frias | B108: Gin | C108: Gin Bacco Quintal 700ml | D108: =IF(ISERROR(VLOOKUP(E108,'Estrutura Protheus'!A:A,1,FALSE)),"Não","Sim") | E108: 010011 | F108: 009821 | G108: Gin Bacco Quintal Garrafa 700ml | H108: 0.7 | I108: LT | J108: =IFERROR(VLOOKUP(F108,'Base Insumos'!$A:$C,3,FALSE()),"PENDENTE") | K108: =IFERROR(IF(J108="PENDENTE",0,J108*H108),0) | L108: PENDENTE | M108: -
A109: Bebidas Frias | B109: Whiskies | C109: Gold Label | D109: =IF(ISERROR(VLOOKUP(E109,'Estrutura Protheus'!A:A,1,FALSE)),"Não","Sim") | E109: 001334 | F109: 001192 | G109: Whisky Johnnie Walker Gold Label 750ml | H109: 0.75 | I109: LT | J109: =IFERROR(VLOOKUP(F109,'Base Insumos'!$A:$C,3,FALSE()),"PENDENTE") | K109: =IFERROR(IF(J109="PENDENTE",0,J109*H109),0) | L109: 690.99 | M109: =IFERROR(K109/L109,0)
A110: Bebidas Frias | B110: Whiskies | C110: Jack Daniel's | D110: =IF(ISERROR(VLOOKUP(E110,'Estrutura Protheus'!A:A,1,FALSE)),"Não","Sim") | E110: 001196 | F110: 001193 | G110: Whisky Jack Daniels Tennessee 1lt | H110: 1 | I110: LT | J110: =IFERROR(VLOOKUP(F110,'Base Insumos'!$A:$C,3,FALSE()),"PENDENTE") | K110: =IFERROR(IF(J110="PENDENTE",0,J110*H110),0) | L110: 390.99 | M110: =IFERROR(K110/L110,0)
A111: Bebidas Frias | B111: Whiskies | C111: Jack Daniel's Apple | D111: =IF(ISERROR(VLOOKUP(E111,'Estrutura Protheus'!A:A,1,FALSE)),"Não","Sim") | E111: 001320 | F111: 001317 | G111: Whisky Jack Apple 1lt | H111: 1 | I111: LT | J111: =IFERROR(VLOOKUP(F111,'Base Insumos'!$A:$C,3,FALSE()),"PENDENTE") | K111: =IFERROR(IF(J111="PENDENTE",0,J111*H111),0) | L111: 390.99 | M111: =IFERROR(K111/L111,0)
A112: Bebidas Frias | B112: Tequila | C112: Jose Cuervo Ouro | D112: =IF(ISERROR(VLOOKUP(E112,'Estrutura Protheus'!A:A,1,FALSE)),"Não","Sim") | E112: 000045 | F112: 000365 | G112: Tequila Jose Curvo Ouro 750ml | H112: 0.75 | I112: LT | J112: =IFERROR(VLOOKUP(F112,'Base Insumos'!$A:$C,3,FALSE()),"PENDENTE") | K112: =IFERROR(IF(J112="PENDENTE",0,J112*H112),0) | L112: 290.99 | M112: =IFERROR(K112/L112,0)
A113: Bebidas Frias | B113: Licor | C113: Licor 43 | D113: =IF(ISERROR(VLOOKUP(E113,'Estrutura Protheus'!A:A,1,FALSE)),"Não","Sim") | E113: 001225 | F113: 000206 | G113: Licor 43 700ml | H113: 0.7 | I113: LT | J113: =IFERROR(VLOOKUP(F113,'Base Insumos'!$A:$C,3,FALSE()),"PENDENTE") | K113: =IFERROR(IF(J113="PENDENTE",0,J113*H113),0) | L113: 349.99 | M113: =IFERROR(K113/L113,0)
A114: Bebidas Frias | B114: Whiskies | C114: Red Label | D114: =IF(ISERROR(VLOOKUP(E114,'Estrutura Protheus'!A:A,1,FALSE)),"Não","Sim") | E114: 001149 | F114: 001136 | G114: Whisky Johnnie Walker Red Label 1lt | H114: 1 | I114: LT | J114: =IFERROR(VLOOKUP(F114,'Base Insumos'!$A:$C,3,FALSE()),"PENDENTE") | K114: =IFERROR(IF(J114="PENDENTE",0,J114*H114),0) | L114: 269.99 | M114: =IFERROR(K114/L114,0)
A115: Bebidas Frias | B115: Cachaça | C115: São Francisco | D115: =IF(ISERROR(VLOOKUP(E115,'Estrutura Protheus'!A:A,1,FALSE)),"Não","Sim") | E115: 000051 | F115: 000343 | G115: Cachaca Sao Francisco 970ml | H115: 0.97 | I115: LT | J115: =IFERROR(VLOOKUP(F115,'Base Insumos'!$A:$C,3,FALSE()),"PENDENTE") | K115: =IFERROR(IF(J115="PENDENTE",0,J115*H115),0) | L115: 139.99 | M115: =IFERROR(K115/L115,0)
A116: Bebidas Frias | B116: Gin | C116: Tanqueray | D116: =IF(ISERROR(VLOOKUP(E116,'Estrutura Protheus'!A:A,1,FALSE)),"Não","Sim") | E116: 001128 | F116: 001161 | G116: Gin Tanqueray 750ml | H116: 0.75 | I116: LT | J116: =IFERROR(VLOOKUP(F116,'Base Insumos'!$A:$C,3,FALSE()),"PENDENTE") | K116: =IFERROR(IF(J116="PENDENTE",0,J116*H116),0) | L116: 299.99 | M116: =IFERROR(K116/L116,0)
A117: Bebidas Frias | B117: Vodka | C117: Vodka Bacco Quintal 1LT | D117: =IF(ISERROR(VLOOKUP(E117,'Estrutura Protheus'!A:A,1,FALSE)),"Não","Sim") | E117: 010012 | F117: 009824 | G117: Vodka Bacco 1lt | H117: 1 | I117: LT | J117: =IFERROR(VLOOKUP(F117,'Base Insumos'!$A:$C,3,FALSE()),"PENDENTE") | K117: =IFERROR(IF(J117="PENDENTE",0,J117*H117),0) | L117: PENDENTE | M117: -
A118: Bebidas Frias | B118: Soft Drinks | C118: Água de Coco | D118: =IF(ISERROR(VLOOKUP(E118,'Estrutura Protheus'!A:A,1,FALSE)),"Não","Sim") | E118: 000892 | F118: 000380 | G118: Agua de Coco 330ml | H118: 1 | I118: UN | J118: =IFERROR(VLOOKUP(F118,'Base Insumos'!$A:$C,3,FALSE()),"PENDENTE") | K118: =IFERROR(IF(J118="PENDENTE",0,J118*H118),0) | L118: 11.99 | M118: =IFERROR(K118/L118,0)
A119: Bebidas Frias | B119: Soft Drinks | C119: Água Mineral | D119: =IF(ISERROR(VLOOKUP(E119,'Estrutura Protheus'!A:A,1,FALSE)),"Não","Sim") | E119: 000878 | F119: 000333 | G119: Agua s/ Gas | H119: 1 | I119: UN | J119: =IFERROR(VLOOKUP(F119,'Base Insumos'!$A:$C,3,FALSE()),"PENDENTE") | K119: =IFERROR(IF(J119="PENDENTE",0,J119*H119),0) | L119: 6.99 | M119: =IFERROR(K119/L119,0)
A120: Bebidas Frias | B120: Soft Drinks | C120: Gelo de Coco | D120: =IF(ISERROR(VLOOKUP(E120,'Estrutura Protheus'!A:A,1,FALSE)),"Não","Sim") | E120: 001481 | F120: 001178 | G120: Gelo de Coco Cx com 30und | H120: 1 | I120: UN | J120: =IFERROR(VLOOKUP(F120,'Base Insumos'!$A:$C,3,FALSE()),"PENDENTE") | K120: =IFERROR(IF(J120="PENDENTE",0,J120*H120),0) | L120: 12.99 | M120: =IFERROR(K120/L120,0)
A121: Bebidas Frias | B121: Soft Drinks | C121: Guaraná Antarctica | D121: =IF(ISERROR(VLOOKUP(E121,'Estrutura Protheus'!A:A,1,FALSE)),"Não","Sim") | E121: 000882 | F121: 000313 | G121: Guarana Lata 350ml | H121: 1 | I121: UN | J121: =IFERROR(VLOOKUP(F121,'Base Insumos'!$A:$C,3,FALSE()),"PENDENTE") | K121: =IFERROR(IF(J121="PENDENTE",0,J121*H121),0) | L121: 9.99 | M121: =IFERROR(K121/L121,0)
A122: Bebidas Frias | B122: Soft Drinks | C122: H2OH | D122: =IF(ISERROR(VLOOKUP(E122,'Estrutura Protheus'!A:A,1,FALSE)),"Não","Sim") | E122: 000884 | F122: 000323 | G122: H2o 500ml | H122: 1 | I122: UN | J122: =IFERROR(VLOOKUP(F122,'Base Insumos'!$A:$C,3,FALSE()),"PENDENTE") | K122: =IFERROR(IF(J122="PENDENTE",0,J122*H122),0) | L122: 10.99 | M122: =IFERROR(K122/L122,0)
A123: Bebidas Frias | B123: Soft Drinks | C123: Pepsi | D123: =IF(ISERROR(VLOOKUP(E123,'Estrutura Protheus'!A:A,1,FALSE)),"Não","Sim") | E123: 000880 | F123: 000319 | G123: Pepsi Lata 350ml | H123: 1 | I123: UN | J123: =IFERROR(VLOOKUP(F123,'Base Insumos'!$A:$C,3,FALSE()),"PENDENTE") | K123: =IFERROR(IF(J123="PENDENTE",0,J123*H123),0) | L123: 9.99 | M123: =IFERROR(K123/L123,0)
A124: Bebidas Frias | B124: Soft Drinks | C124: Red Bull | D124: =IF(ISERROR(VLOOKUP(E124,'Estrutura Protheus'!A:A,1,FALSE)),"Não","Sim") | E124: 000891 | F124: 000368 | G124: Red Bull | H124: 1 | I124: UN | J124: =IFERROR(VLOOKUP(F124,'Base Insumos'!$A:$C,3,FALSE()),"PENDENTE") | K124: =IFERROR(IF(J124="PENDENTE",0,J124*H124),0) | L124: 20.99 | M124: =IFERROR(K124/L124,0)
A125: Bebidas Frias | B125: Soft Drinks | C125: Soda Limonada | D125: =IF(ISERROR(VLOOKUP(E125,'Estrutura Protheus'!A:A,1,FALSE)),"Não","Sim") | E125: 000883 | F125: 000316 | G125: Soda Lata 350ml | H125: 1 | I125: UN | J125: =IFERROR(VLOOKUP(F125,'Base Insumos'!$A:$C,3,FALSE()),"PENDENTE") | K125: =IFERROR(IF(J125="PENDENTE",0,J125*H125),0) | L125: 9.99 | M125: =IFERROR(K125/L125,0)
A126: Bebidas Frias | B126: Soft Drinks | C126: Sukita Laranja | D126: =IF(ISERROR(VLOOKUP(E126,'Estrutura Protheus'!A:A,1,FALSE)),"Não","Sim") | E126: 000881 | F126: 000322 | G126: Sukita Laranja Lata 350ml | H126: 1 | I126: UN | J126: =IFERROR(VLOOKUP(F126,'Base Insumos'!$A:$C,3,FALSE()),"PENDENTE") | K126: =IFERROR(IF(J126="PENDENTE",0,J126*H126),0) | L126: 9.99 | M126: =IFERROR(K126/L126,0)
A127: Guarnições | B127: Porção | C127: Anéis de Cebola | D127: =IF(ISERROR(VLOOKUP(E127,'Estrutura Protheus'!A:A,1,FALSE)),"Não","Sim") | E127: 001511 | F127: 001522 | G127: Aneis de Cebola 1,05kg | H127: 0.15 | I127: KG | J127: =IFERROR(VLOOKUP(F127,'Base Insumos'!$A:$C,3,FALSE()),"PENDENTE") | K127: =IFERROR(IF(J127="PENDENTE",0,J127*H127),0) | L127: 14.99 | M127: =IFERROR(K127/L127,0)
A128: Guarnições | B128: Porção | C128: Batata Frita | D128: =IF(ISERROR(VLOOKUP(E128,'Estrutura Protheus'!A:A,1,FALSE)),"Não","Sim") | E128: 001482 | F128: 000454 | G128: Batata Mcaim 9 Mm 2,5kg | H128: 0.15 | I128: KG | J128: =IFERROR(VLOOKUP(F128,'Base Insumos'!$A:$C,3,FALSE()),"PENDENTE") | K128: =IFERROR(IF(J128="PENDENTE",0,J128*H128),0) | L128: 16.99 | M128: =IFERROR(K128/L128,0)
A129: Guarnições | B129: Porção | C129: Batata Smiles - Mc Cain | D129: =IF(ISERROR(VLOOKUP(E129,'Estrutura Protheus'!A:A,1,FALSE)),"Não","Sim") | E129: 001506 | F129: 009293 | G129: Batata Smile Compra | H129: 0.19 | I129: KG | J129: =IFERROR(VLOOKUP(F129,'Base Insumos'!$A:$C,3,FALSE()),"PENDENTE") | K129: =IFERROR(IF(J129="PENDENTE",0,J129*H129),0) | L129: 17.99 | M129: =IFERROR(K129/L129,0)
... A137: Guarnições | B137: Guarnições | C137: Porção de arroz branco | D137: =IF(ISERROR(VLOOKUP(E137,'Estrutura Protheus'!A:A,1,FALSE)),"Não","Sim") | E137: 000900 | F137: 002068 | G137: Manteiga S/sal 5kg | H137: 0.005 | I137: KG | J137: =IFERROR(VLOOKUP(F137,'Base Insumos'!$A:$C,3,FALSE()),"PENDENTE") | K137: =IFERROR(IF(J137="PENDENTE",0,J137*H137),0) | L137: 9.99 | M137: =IFERROR(K137/L137,0)
A138: Guarnições | B138: Guarnições | C138: Porção de arroz biro biro | D138: =IF(ISERROR(VLOOKUP(E138,'Estrutura Protheus'!A:A,1,FALSE)),"Não","Sim") | E138: 000902 | F138: 000900 | G138: Não Encontrado na Base | H138: 0.15 | J138: =IFERROR(VLOOKUP(F138,'Base Insumos'!$A:$C,3,FALSE()),"PENDENTE") | K138: =IFERROR(IF(J138="PENDENTE",0,J138*H138),0) | L138: 15.99 | M138: =IFERROR(K138/L138,0)
A139: Guarnições | B139: Guarnições | C139: Porção de arroz biro biro | D139: =IF(ISERROR(VLOOKUP(E139,'Estrutura Protheus'!A:A,1,FALSE)),"Não","Sim") | E139: 000902 | F139: 000426 | G139: Bacon em Cubos | H139: 0.002 | I139: KG | J139: =IFERROR(VLOOKUP(F139,'Base Insumos'!$A:$C,3,FALSE()),"PENDENTE") | K139: =IFERROR(IF(J139="PENDENTE",0,J139*H139),0) | L139: 15.99 | M139: =IFERROR(K139/L139,0)
A140: Guarnições | B140: Guarnições | C140: Porção de arroz biro biro | D140: =IF(ISERROR(VLOOKUP(E140,'Estrutura Protheus'!A:A,1,FALSE)),"Não","Sim") | E140: 000902 | F140: 000478 | G140: Ovos Brancos | H140: 0.698 | I140: UN | J140: =IFERROR(VLOOKUP(F140,'Base Insumos'!$A:$C,3,FALSE()),"PENDENTE") | K140: =IFERROR(IF(J140="PENDENTE",0,J140*H140),0) | L140: 15.99 | M140: =IFERROR(K140/L140,0)
A141: Guarnições | B141: Guarnições | C141: Porção de arroz biro biro | D141: =IF(ISERROR(VLOOKUP(E141,'Estrutura Protheus'!A:A,1,FALSE)),"Não","Sim") | E141: 000902 | F141: 000469 | G141: Cebolinha | H141: 0.006 | I141: KG | J141: =IFERROR(VLOOKUP(F141,'Base Insumos'!$A:$C,3,FALSE()),"PENDENTE") | K141: =IFERROR(IF(J141="PENDENTE",0,J141*H141),0) | L141: 15.99 | M141: =IFERROR(K141/L141,0)
A142: Guarnições | B142: Guarnições | C142: Porção de arroz biro biro | D142: =IF(ISERROR(VLOOKUP(E142,'Estrutura Protheus'!A:A,1,FALSE)),"Não","Sim") | E142: 000902 | F142: 000664 | G142: Batata Palha | H142: 0.012 | I142: KG | J142: =IFERROR(VLOOKUP(F142,'Base Insumos'!$A:$C,3,FALSE()),"PENDENTE") | K142: =IFERROR(IF(J142="PENDENTE",0,J142*H142),0) | L142: 15.99 | M142: =IFERROR(K142/L142,0)
...

Sheet CMV Consolidado
A1: Identificação | F1: Semana Atual | L1: Semana Anterior | R1: Análise
A2: Categoria | B2: Subcategoria | C2: Item | D2: Nome da PA no Protheus | E2: Código PA | F2: Preço Venda (R$) | G2: Custo CMV (R$) | H2: CMV (%) | I2: Marg. Contrib. (R$) | J2: Marg. Contrib. (%) | K2: Preço Sugerido CMV 30% | L2: Preço Venda (R$) | M2: Custo CMV (R$) | N2: CMV (%) | O2: Marg. Contrib. (R$) | P2: Marg. Contrib. (%) | Q2: Data Ref. | R2: Variação CMV % | S2: No Cardápio Digital | T2: Status | U2: Ação | V2: Observação
A3: Bebidas Frias | B3: Vodka | C3: Absolut | D3: =VLOOKUP(E3,_Protheus_Cadastro!A:I,2,FALSE) | E3: 000049 | F3: =IFERROR(INDEX(Vendidos!$H:$H,MATCH(E3,Vendidos!$B:$B,0)),"—") | G3: =SUMIF('Fichas Flat'!$E$2:$E$880,E3,'Fichas Flat'!$K$2:$K$880) | H3: =IFERROR(G3/F3,0) | I3: =IFERROR(F3-G3,0) | J3: =IFERROR(I3/F3,0) | K3: =IFERROR(G3/0.3,0) | L3: PENDENTE | M3: 106.89997 | N3: - | O3: - | P3: - | Q3: 46148 | R3: =IFERROR(IF(M3="","—",H3-N3),"—") | S3: Sim | T3: =IFERROR(IF(H3=0,"—",IF(H3<=0.25,"✔ OK",IF(H3<=0.35,"⚠ Atenção","✖ Crítico"))),"—")
A4: Drinks | B4: Drinks | C4: Maracujack | D4: =VLOOKUP(E4,_Protheus_Cadastro!A:I,2,FALSE) | E4: 001202 | F4: =IFERROR(INDEX(Vendidos!$H:$H,MATCH(E4,Vendidos!$B:$B,0)),"—") | G4: =SUMIF('Fichas Flat'!$E$2:$E$880,E4,'Fichas Flat'!$K$2:$K$880) | H4: =IFERROR(G4/F4,0) | I4: =IFERROR(F4-G4,0) | J4: =IFERROR(I4/F4,0) | K4: =IFERROR(G4/0.3,0) | L4: PENDENTE | M4: 8.2542 | N4: - | O4: - | P4: - | Q4: 46148 | R4: =IFERROR(IF(M4="","—",H4-N4),"—") | S4: Não | T4: =IFERROR(IF(H4=0,"—",IF(H4<=0.25,"✔ OK",IF(H4<=0.35,"⚠ Atenção","✖ Crítico"))),"—")
A5: Bebidas Frias | B5: Bebidas Prontas | C5: Beats Senses | D5: =VLOOKUP(E5,_Protheus_Cadastro!A:I,2,FALSE) | E5: 001336 | F5: =IFERROR(INDEX(Vendidos!$H:$H,MATCH(E5,Vendidos!$B:$B,0)),"—") | G5: =SUMIF('Fichas Flat'!$E$2:$E$880,E5,'Fichas Flat'!$K$2:$K$880) | H5: =IFERROR(G5/F5,0) | I5: =IFERROR(F5-G5,0) | J5: =IFERROR(I5/F5,0) | K5: =IFERROR(G5/0.3,0) | L5: PENDENTE | M5: 230.90002 | N5: - | O5: - | P5: - | Q5: 46148 | R5: =IFERROR(IF(M5="","—",H5-N5),"—") | S5: Não | T5: =IFERROR(IF(H5=0,"—",IF(H5<=0.25,"✔ OK",IF(H5<=0.35,"⚠ Atenção","✖ Crítico"))),"—")
A6: Espetos | B6: Veggie | C6: Espeto de Brócolis com Couve Flor | D6: =VLOOKUP(E6,_Protheus_Cadastro!A:I,2,FALSE) | E6: PENDENTE | F6: =IFERROR(INDEX(Vendidos!$H:$H,MATCH(E6,Vendidos!$B:$B,0)),"—") | G6: =SUMIF('Fichas Flat'!$E$2:$E$880,E6,'Fichas Flat'!$K$2:$K$880) | H6: =IFERROR(G6/F6,0) | I6: =IFERROR(F6-G6,0) | J6: =IFERROR(I6/F6,0) | K6: =IFERROR(G6/0.3,0) | Q6: 46148 | R6: =IFERROR(IF(M6="","—",H6-N6),"—") | S6: Não | T6: =IFERROR(IF(H6=0,"—",IF(H6<=0.25,"✔ OK",IF(H6<=0.35,"⚠ Atenção","✖ Crítico"))),"—")
A7: Espetos | B7: Veggie | C7: Espeto de Mix de Legumes | D7: =VLOOKUP(E7,_Protheus_Cadastro!A:I,2,FALSE) | E7: PENDENTE | F7: =IFERROR(INDEX(Vendidos!$H:$H,MATCH(E7,Vendidos!$B:$B,0)),"—") | G7: =SUMIF('Fichas Flat'!$E$2:$E$880,E7,'Fichas Flat'!$K$2:$K$880) | H7: =IFERROR(G7/F7,0) | I7: =IFERROR(F7-G7,0) | J7: =IFERROR(I7/F7,0) | K7: =IFERROR(G7/0.3,0) | Q7: 46148 | R7: =IFERROR(IF(M7="","—",H7-N7),"—") | S7: Não | T7: =IFERROR(IF(H7=0,"—",IF(H7<=0.25,"✔ OK",IF(H7<=0.35,"⚠ Atenção","✖ Crítico"))),"—")
A8: Espetos | B8: Veggie | C8: Espeto de Queijo Coalho com Abobrinha | D8: =VLOOKUP(E8,_Protheus_Cadastro!A:I,2,FALSE) | E8: PENDENTE | F8: =IFERROR(INDEX(Vendidos!$H:$H,MATCH(E8,Vendidos!$B:$B,0)),"—") | G8: =SUMIF('Fichas Flat'!$E$2:$E$880,E8,'Fichas Flat'!$K$2:$K$880) | H8: =IFERROR(G8/F8,0) | I8: =IFERROR(F8-G8,0) | J8: =IFERROR(I8/F8,0) | K8: =IFERROR(G8/0.3,0) | Q8: 46148 | R8: =IFERROR(IF(M8="","—",H8-N8),"—") | S8: Sim | T8: =IFERROR(IF(H8=0,"—",IF(H8<=0.25,"✔ OK",IF(H8<=0.35,"⚠ Atenção","✖ Crítico"))),"—")
A9: Bebidas Frias | B9: Gin | C9: Gin Bacco Quintal 700ml | D9: =VLOOKUP(E9,_Protheus_Cadastro!A:I,2,FALSE) | E9: 010011 | F9: =IFERROR(INDEX(Vendidos!$H:$H,MATCH(E9,Vendidos!$B:$B,0)),"—") | G9: =SUMIF('Fichas Flat'!$E$2:$E$880,E9,'Fichas Flat'!$K$2:$K$880) | H9: =IFERROR(G9/F9,0) | I9: =IFERROR(F9-G9,0) | J9: =IFERROR(I9/F9,0) | K9: =IFERROR(G9/0.3,0) | L9: PENDENTE | M9: 5.4277 | N9: - | O9: - | P9: - | Q9: 46148 | R9: =IFERROR(IF(M9="","—",H9-N9),"—") | S9: Não | T9: =IFERROR(IF(H9=0,"—",IF(H9<=0.25,"✔ OK",IF(H9<=0.35,"⚠ Atenção","✖ Crítico"))),"—")
A10: Bebidas Frias | B10: Vodka | C10: Vodka Bacco Quintal 1LT | D10: =VLOOKUP(E10,_Protheus_Cadastro!A:I,2,FALSE) | E10: 010012 | F10: =IFERROR(INDEX(Vendidos!$H:$H,MATCH(E10,Vendidos!$B:$B,0)),"—") | G10: =SUMIF('Fichas Flat'!$E$2:$E$880,E10,'Fichas Flat'!$K$2:$K$880) | H10: =IFERROR(G10/F10,0) | I10: =IFERROR(F10-G10,0) | J10: =IFERROR(I10/F10,0) | K10: =IFERROR(G10/0.3,0) | L10: PENDENTE | M10: 37.24 | N10: - | O10: - | P10: - | Q10: 46148 | R10: =IFERROR(IF(M10="","—",H10-N10),"—") | S10: Não | T10: =IFERROR(IF(H10=0,"—",IF(H10<=0.25,"✔ OK",IF(H10<=0.35,"⚠ Atenção","✖ Crítico"))),"—")
A11: Saladas e Molhos | B11: Saladas | C11: Salada Caprese | D11: =VLOOKUP(E11,_Protheus_Cadastro!A:I,2,FALSE) | E11: 000869 | F11: =IFERROR(INDEX(Vendidos!$H:$H,MATCH(E11,Vendidos!$B:$B,0)),"—") | G11: =SUMIF('Fichas Flat'!$E$2:$E$880,E11,'Fichas Flat'!$K$2:$K$880) | H11: =IFERROR(G11/F11,0) | I11: =IFERROR(F11-G11,0) | J11: =IFERROR(I11/F11,0) | K11: =IFERROR(G11/0.3,0) | Q11: 46148 | R11: =IFERROR(IF(M11="","—",H11-N11),"—") | S11: Sim | T11: =IFERROR(IF(H11=0,"—",IF(H11<=0.25,"✔ OK",IF(H11<=0.35,"⚠ Atenção","✖ Crítico"))),"—")
A12: Saladas e Molhos | B12: Saladas | C12: Salada da Casa | D12: =VLOOKUP(E12,_Protheus_Cadastro!A:I,2,FALSE) | E12: 000870 | F12: =IFERROR(INDEX(Vendidos!$H:$H,MATCH(E12,Vendidos!$B:$B,0)),"—") | G12: =SUMIF('Fichas Flat'!$E$2:$E$880,E12,'Fichas Flat'!$K$2:$K$880) | H12: =IFERROR(G12/F12,0) | I12: =IFERROR(F12-G12,0) | J12: =IFERROR(I12/F12,0) | K12: =IFERROR(G12/0.3,0) | Q12: 46148 | R12: =IFERROR(IF(M12="","—",H12-N12),"—") | S12: Sim | T12: =IFERROR(IF(H12=0,"—",IF(H12<=0.25,"✔ OK",IF(H12<=0.35,"⚠ Atenção","✖ Crítico"))),"—")
A13: Saladas e Molhos | B13: Saladas | C13: Salada Juliana | D13: =VLOOKUP(E13,_Protheus_Cadastro!A:I,2,FALSE) | E13: 000871 | F13: =IFERROR(INDEX(Vendidos!$H:$H,MATCH(E13,Vendidos!$B:$B,0)),"—") | G13: =SUMIF('Fichas Flat'!$E$2:$E$880,E13,'Fichas Flat'!$K$2:$K$880) | H13: =IFERROR(G13/F13,0) | I13: =IFERROR(F13-G13,0) | J13: =IFERROR(I13/F13,0) | K13: =IFERROR(G13/0.3,0) | Q13: 46148 | R13: =IFERROR(IF(M13="","—",H13-N13),"—") | S13: Sim | T13: =IFERROR(IF(H13=0,"—",IF(H13<=0.25,"✔ OK",IF(H13<=0.35,"⚠ Atenção","✖ Crítico"))),"—")
A14: Saladas e Molhos | B14: Saladas | C14: Salada California | D14: =VLOOKUP(E14,_Protheus_Cadastro!A:I,2,FALSE) | E14: 002215 | F14: =IFERROR(INDEX(Vendidos!$H:$H,MATCH(E14,Vendidos!$B:$B,0)),"—") | G14: =SUMIF('Fichas Flat'!$E$2:$E$880,E14,'Fichas Flat'!$K$2:$K$880) | H14: =IFERROR(G14/F14,0) | I14: =IFERROR(F14-G14,0) | J14: =IFERROR(I14/F14,0) | K14: =IFERROR(G14/0.3,0) | Q14: 46148 | R14: =IFERROR(IF(M14="","—",H14-N14),"—") | S14: Não | T14: =IFERROR(IF(H14=0,"—",IF(H14<=0.25,"✔ OK",IF(H14<=0.35,"⚠ Atenção","✖ Crítico"))),"—")
A15: Saladas e Molhos | B15: Saladas | C15: Mini Salada Quintal | D15: =VLOOKUP(E15,_Protheus_Cadastro!A:I,2,FALSE) | E15: 002262 | F15: =IFERROR(INDEX(Vendidos!$H:$H,MATCH(E15,Vendidos!$B:$B,0)),"—") | G15: =SUMIF('Fichas Flat'!$E$2:$E$880,E15,'Fichas Flat'!$K$2:$K$880) | H15: =IFERROR(G15/F15,0) | I15: =IFERROR(F15-G15,0) | J15: =IFERROR(I15/F15,0) | K15: =IFERROR(G15/0.3,0) | Q15: 46148 | R15: =IFERROR(IF(M15="","—",H15-N15),"—") | S15: Não | T15: =IFERROR(IF(H15=0,"—",IF(H15<=0.25,"✔ OK",IF(H15<=0.35,"⚠ Atenção","✖ Crítico"))),"—")
A16: Saladas e Molhos | B16: Saladas | C16: Mini Salada Fresca | D16: =IFERROR(VLOOKUP(E16,_Protheus_Cadastro!$A:$B,2,FALSE),"—") | E16: 002239 | F16: =IFERROR(INDEX(Vendidos!$H:$H,MATCH(E16,Vendidos!$B:$B,0)),"—") | G16: =SUMIF('Fichas Flat'!$E$2:$E$880,E16,'Fichas Flat'!$K$2:$K$880) | H16: =IFERROR(G16/F16,0) | I16: =IFERROR(F16-G16,0) | J16: =IFERROR(I16/F16,0) | K16: =IFERROR(G16/0.3,0) | R16: =IFERROR(IF(G16=0,"—",IF(H16<=0.25,"✔ OK",IF(H16<=0.35,"⚠ Atenção","✖ Crítico"))),"—") | S16: Não
A17: Cardápio Principal | B17: Sazonais | C17: Caldo de Feijão | D17: =VLOOKUP(E17,_Protheus_Cadastro!A:I,2,FALSE) | E17: 001340 | F17: =IFERROR(INDEX(Vendidos!$H:$H,MATCH(E17,Vendidos!$B:$B,0)),"—") | G17: =SUMIF('Fichas Flat'!$E$2:$E$880,E17,'Fichas Flat'!$K$2:$K$880) | H17: =IFERROR(G17/F17,0) | I17: =IFERROR(F17-G17,0) | J17: =IFERROR(I17/F17,0) | K17: =IFERROR(G17/0.3,0) | Q17: 46148 | R17: =IFERROR(IF(M16="","—",H17-N16),"—") | S17: Sim | T17: =IFERROR(IF(H16=0,"—",IF(H16<=0.25,"✔ OK",IF(H16<=0.35,"⚠ Atenção","✖ Crítico"))),"—")
A18: Saladas e Molhos | B18: Sazonais | C18: Caldo Verde | D18: =VLOOKUP(E18,_Protheus_Cadastro!A:I,2,FALSE) | E18: 001341 | F18: =IFERROR(INDEX(Vendidos!$H:$H,MATCH(E18,Vendidos!$B:$B,0)),"—") | G18: =SUMIF('Fichas Flat'!$E$2:$E$880,E18,'Fichas Flat'!$K$2:$K$880) | H18: =IFERROR(G18/F18,0) | I18: =IFERROR(F18-G18,0) | J18: =IFERROR(I18/F18,0) | K18: =IFERROR(G18/0.3,0) | Q18: 46148 | R18: =IFERROR(IF(M17="","—",H18-N17),"—") | S18: Sim | T18: =IFERROR(IF(H17=0,"—",IF(H17<=0.25,"✔ OK",IF(H17<=0.35,"⚠ Atenção","✖ Crítico"))),"—")
A19: Saladas e Molhos | B19: Sazonais | C19: Vinho Quente | D19: =VLOOKUP(E19,_Protheus_Cadastro!A:I,2,FALSE) | E19: 001076 | F19: =IFERROR(INDEX(Vendidos!$H:$H,MATCH(E19,Vendidos!$B:$B,0)),"—") | G19: =SUMIF('Fichas Flat'!$E$2:$E$880,E19,'Fichas Flat'!$K$2:$K$880) | H19: =IFERROR(G19/F19,0) | I19: =IFERROR(F19-G19,0) | J19: =IFERROR(I19/F19,0) | K19: =IFERROR(G19/0.3,0) | Q19: 46148 | R19: =IFERROR(IF(M18="","—",H19-N18),"—") | S19: Sim | T19: =IFERROR(IF(H18=0,"—",IF(H18<=0.25,"✔ OK",IF(H18<=0.35,"⚠ Atenção","✖ Crítico"))),"—")
A20: Saladas e Molhos | B20: Molhos | C20: Chimichurri do Quintal | D20: =VLOOKUP(E20,_Protheus_Cadastro!A:I,2,FALSE) | E20: PENDENTE | F20: =IFERROR(INDEX(Vendidos!$H:$H,MATCH(E20,Vendidos!$B:$B,0)),"—") | G20: =SUMIF('Fichas Flat'!$E$2:$E$880,E20,'Fichas Flat'!$K$2:$K$880) | H20: =IFERROR(G20/F20,0) | I20: =IFERROR(F20-G20,0) | J20: =IFERROR(I20/F20,0) | K20: =IFERROR(G20/0.3,0) | Q20: 46148 | R20: =IFERROR(IF(M19="","—",H20-N19),"—") | S20: Não | T20: =IFERROR(IF(H19=0,"—",IF(H19<=0.25,"✔ OK",IF(H19<=0.35,"⚠ Atenção","✖ Crítico"))),"—")
A21: Saladas e Molhos | B21: Molhos | C21: Geleia de Pimenta | D21: =VLOOKUP(E21,_Protheus_Cadastro!A:I,2,FALSE) | E21: PENDENTE | F21: =IFERROR(INDEX(Vendidos!$H:$H,MATCH(E21,Vendidos!$B:$B,0)),"—") | G21: =SUMIF('Fichas Flat'!$E$2:$E$880,E21,'Fichas Flat'!$K$2:$K$880) | H21: =IFERROR(G21/F21,0) | I21: =IFERROR(F21-G21,0) | J21: =IFERROR(I21/F21,0) | K21: =IFERROR(G21/0.3,0) | Q21: 46148 | R21: =IFERROR(IF(M20="","—",H21-N20),"—") | S21: Não | T21: =IFERROR(IF(H20=0,"—",IF(H20<=0.25,"✔ OK",IF(H20<=0.35,"⚠ Atenção","✖ Crítico"))),"—")
A22: Saladas e Molhos | B22: Molhos | C22: Maionese de Alho e Sal Quintal | D22: =VLOOKUP(E22,_Protheus_Cadastro!A:I,2,FALSE) | E22: PENDENTE | F22: =IFERROR(INDEX(Vendidos!$H:$H,MATCH(E22,Vendidos!$B:$B,0)),"—") | G22: =SUMIF('Fichas Flat'!$E$2:$E$880,E22,'Fichas Flat'!$K$2:$K$880) | H22: =IFERROR(G22/F22,0) | I22: =IFERROR(F22-G22,0) | J22: =IFERROR(I22/F22,0) | K22: =IFERROR(G22/0.3,0) | Q22: 46148 | R22: =IFERROR(IF(M21="","—",H22-N21),"—") | S22: Não | T22: =IFERROR(IF(H21=0,"—",IF(H21<=0.25,"✔ OK",IF(H21<=0.35,"⚠ Atenção","✖ Crítico"))),"—")
A23: Saladas e Molhos | B23: Molhos | C23: Molho Pesto | D23: =VLOOKUP(E23,_Protheus_Cadastro!A:I,2,FALSE) | E23: PENDENTE | F23: =IFERROR(INDEX(Vendidos!$H:$H,MATCH(E23,Vendidos!$B:$B,0)),"—") | G23: =SUMIF('Fichas Flat'!$E$2:$E$880,E23,'Fichas Flat'!$K$2:$K$880) | H23: =IFERROR(G23/F23,0) | I23: =IFERROR(F23-G23,0) | J23: =IFERROR(I23/F23,0) | K23: =IFERROR(G23/0.3,0) | Q23: 46148 | R23: =IFERROR(IF(M22="","—",H23-N22),"—") | S23: Não | T23: =IFERROR(IF(H22=0,"—",IF(H22<=0.25,"✔ OK",IF(H22<=0.35,"⚠ Atenção","✖ Crítico"))),"—")
A24: Saladas e Molhos | B24: Molhos | C24: Molho Mostarda e Mel | D24: =VLOOKUP(E24,_Protheus_Cadastro!A:I,2,FALSE) | E24: PENDENTE | F24: =IFERROR(INDEX(Vendidos!$H:$H,MATCH(E24,Vendidos!$B:$B,0)),"—") | G24: =SUMIF('Fichas Flat'!$E$2:$E$880,E24,'Fichas Flat'!$K$2:$K$880) | H24: =IFERROR(G24/F24,0) | I24: =IFERROR(F24-G24,0) | J24: =IFERROR(I24/F24,0) | K24: =IFERROR(G24/0.3,0) | Q24: 46148 | R24: =IFERROR(IF(M23="","—",H24-N23),"—") | S24: Não | T24: =IFERROR(IF(H23=0,"—",IF(H23<=0.25,"✔ OK",IF(H23<=0.35,"⚠ Atenção","✖ Crítico"))),"—")
A25: Saladas e Molhos | B25: Molhos | C25: Molho de Hortelã | D25: =VLOOKUP(E25,_Protheus_Cadastro!A:I,2,FALSE) | E25: PENDENTE | F25: =IFERROR(INDEX(Vendidos!$H:$H,MATCH(E25,Vendidos!$B:$B,0)),"—") | G25: =SUMIF('Fichas Flat'!$E$2:$E$880,E25,'Fichas Flat'!$K$2:$K$880) | H25: =IFERROR(G25/F25,0) | I25: =IFERROR(F25-G25,0) | J25: =IFERROR(I25/F25,0) | K25: =IFERROR(G25/0.3,0) | Q25: 46148 | R25: =IFERROR(IF(M24="","—",H25-N24),"—") | S25: Sim | T25: =IFERROR(IF(H24=0,"—",IF(H24<=0.25,"✔ OK",IF(H24<=0.35,"⚠ Atenção","✖ Crítico"))),"—")
A26: Saladas e Molhos | B26: Molhos | C26: Molho Azeite de Ervas | D26: =VLOOKUP(E26,_Protheus_Cadastro!A:I,2,FALSE) | E26: PENDENTE | F26: =IFERROR(INDEX(Vendidos!$H:$H,MATCH(E26,Vendidos!$B:$B,0)),"—") | G26: =SUMIF('Fichas Flat'!$E$2:$E$880,E26,'Fichas Flat'!$K$2:$K$880) | H26: =IFERROR(G26/F26,0) | I26: =IFERROR(F26-G26,0) | J26: =IFERROR(I26/F26,0) | K26: =IFERROR(G26/0.3,0) | Q26: 46148 | R26: =IFERROR(IF(M25="","—",H26-N25),"—") | S26: Não | T26: =IFERROR(IF(H25=0,"—",IF(H25<=0.25,"✔ OK",IF(H25<=0.35,"⚠ Atenção","✖ Crítico"))),"—")
A27: Saladas e Molhos | B27: Molhos | C27: Molho Manteiga | D27: =VLOOKUP(E27,_Protheus_Cadastro!A:I,2,FALSE) | E27: PENDENTE | F27: =IFERROR(INDEX(Vendidos!$H:$H,MATCH(E27,Vendidos!$B:$B,0)),"—") | G27: =SUMIF('Fichas Flat'!$E$2:$E$880,E27,'Fichas Flat'!$K$2:$K$880) | H27: =IFERROR(G27/F27,0) | I27: =IFERROR(F27-G27,0) | J27: =IFERROR(I27/F27,0) | K27: =IFERROR(G27/0.3,0) | Q27: 46148 | R27: =IFERROR(IF(M26="","—",H27-N26),"—") | S27: Não | T27: =IFERROR(IF(H26=0,"—",IF(H26<=0.25,"✔ OK",IF(H26<=0.35,"⚠ Atenção","✖ Crítico"))),"—")
A28: Drinks | B28: Drinks | C28: Soda italiana - Maracujá | D28: =VLOOKUP(E28,_Protheus_Cadastro!A:I,2,FALSE) | E28: 010314 | F28: =IFERROR(INDEX(Vendidos!$H:$H,MATCH(E28,Vendidos!$B:$B,0)),"—") | G28: =SUMIF('Fichas Flat'!$E$2:$E$880,E28,'Fichas Flat'!$K$2:$K$880) | H28: =IFERROR(G28/F28,0) | I28: =IFERROR(F28-G28,0) | J28: =IFERROR(I28/F28,0) | K28: =IFERROR(G28/0.3,0) | L28: 16.99 | M28: 1.0778 | N28: 0.063437316 | O28: 15.9122 | P28: 0.93656268 | Q28: 46148 | R28: =IFERROR(IF(M11="","—",H11-N11),"—") | S28: Não | T28: =IFERROR(IF(H11=0,"—",IF(H11<=0.25,"✔ OK",IF(H11<=0.35,"⚠ Atenção","✖ Crítico"))),"—")
A29: Drinks | B29: Drinks | C29: Soda italiana - Limão Siciliano | D29: =VLOOKUP(E29,_Protheus_Cadastro!A:I,2,FALSE) | E29: 010315 | F29: =IFERROR(INDEX(Vendidos!$H:$H,MATCH(E29,Vendidos!$B:$B,0)),"—") | G29: =SUMIF('Fichas Flat'!$E$2:$E$880,E29,'Fichas Flat'!$K$2:$K$880) | H29: =IFERROR(G29/F29,0) | I29: =IFERROR(F29-G29,0) | J29: =IFERROR(I29/F29,0) | K29: =IFERROR(G29/0.3,0) | L29: 16.99 | M29: 13.633278 | N29: 0.80242955 | O29: 3.356722 | P29: 0.19757045 | Q29: 46148 | R29: =IFERROR(IF(M12="","—",H12-N12),"—") | S29: Não | T29: =IFERROR(IF(H12=0,"—",IF(H12<=0.25,"✔ OK",IF(H12<=0.35,"⚠ Atenção","✖ Crítico"))),"—")
A30: Drinks | B30: Drinks | C30: Jack Fire Ginger | D30: =VLOOKUP(E30,_Protheus_Cadastro!A:I,2,FALSE) | E30: 001324 | F30: =IFERROR(INDEX(Vendidos!$H:$H,MATCH(E30,Vendidos!$B:$B,0)),"—") | G30: =SUMIF('Fichas Flat'!$E$2:$E$880,E30,'Fichas Flat'!$K$2:$K$880) | H30: =IFERROR(G30/F30,0) | I30: =IFERROR(F30-G30,0) | J30: =IFERROR(I30/F30,0) | K30: =IFERROR(G30/0.3,0) | Q30: 46148 | R30: =IFERROR(IF(M29="","—",H30-N29),"—") | S30: Não | T30: =IFERROR(IF(H29=0,"—",IF(H29<=0.25,"✔ OK",IF(H29<=0.35,"⚠ Atenção","✖ Crítico"))),"—")
A31: Drinks | B31: Drinks | C31: Jack Honey e Lemonade | D31: =VLOOKUP(E31,_Protheus_Cadastro!A:I,2,FALSE) | E31: PENDENTE | F31: =IFERROR(INDEX(Vendidos!$H:$H,MATCH(E31,Vendidos!$B:$B,0)),"—") | G31: =SUMIF('Fichas Flat'!$E$2:$E$880,E31,'Fichas Flat'!$K$2:$K$880) | H31: =IFERROR(G31/F31,0) | I31: =IFERROR(F31-G31,0) | J31: =IFERROR(I31/F31,0) | K31: =IFERROR(G31/0.3,0) | Q31: 46148 | R31: =IFERROR(IF(M30="","—",H31-N30),"—") | S31: Não | T31: =IFERROR(IF(H30=0,"—",IF(H30<=0.25,"✔ OK",IF(H30<=0.35,"⚠ Atenção","✖ Crítico"))),"—")
A32: Drinks | B32: Drinks | C32: Gin Tônica Maça Verde | D32: =VLOOKUP(E32,_Protheus_Cadastro!A:I,2,FALSE) | E32: 001966 | F32: =IFERROR(INDEX(Vendidos!$H:$H,MATCH(E32,Vendidos!$B:$B,0)),"—") | G32: =SUMIF('Fichas Flat'!$E$2:$E$880,E32,'Fichas Flat'!$K$2:$K$880) | H32: =IFERROR(G32/F32,0) | I32: =IFERROR(F32-G32,0) | J32: =IFERROR(I32/F32,0) | K32: =IFERROR(G32/0.3,0) | Q32: 46148 | R32: =IFERROR(IF(M13="","—",H13-N13),"—") | S32: Não | T32: =IFERROR(IF(H13=0,"—",IF(H13<=0.25,"✔ OK",IF(H13<=0.35,"⚠ Atenção","✖ Crítico"))),"—")
A33: Drinks | B33: Sucos | C33: Jarra Suco de Maracujá | D33: =VLOOKUP(E33,_Protheus_Cadastro!A:I,2,FALSE) | E33: 002029 | F33: =IFERROR(INDEX(Vendidos!$H:$H,MATCH(E33,Vendidos!$B:$B,0)),"—") | G33: =SUMIF('Fichas Flat'!$E$2:$E$880,E33,'Fichas Flat'!$K$2:$K$880) | H33: =IFERROR(G33/F33,0) | I33: =IFERROR(F33-G33,0) | J33: =IFERROR(I33/F33,0) | K33: =IFERROR(G33/0.3,0) | Q33: 46148 | R33: =IFERROR(IF(M14="","—",H14-N14),"—") | S33: Não | T33: =IFERROR(IF(H14=0,"—",IF(H14<=0.25,"✔ OK",IF(H14<=0.35,"⚠ Atenção","✖ Crítico"))),"—")
A34: Drinks | B34: Sucos | C34: Jarra Suco de Laranja | D34: =VLOOKUP(E34,_Protheus_Cadastro!A:I,2,FALSE) | E34: 002026 | F34: =IFERROR(INDEX(Vendidos!$H:$H,MATCH(E34,Vendidos!$B:$B,0)),"—") | G34: =SUMIF('Fichas Flat'!$E$2:$E$880,E34,'Fichas Flat'!$K$2:$K$880) | H34: =IFERROR(G34/F34,0) | I34: =IFERROR(F34-G34,0) | J34: =IFERROR(I34/F34,0) | K34: =IFERROR(G34/0.3,0) | Q34: 46148 | R34: =IFERROR(IF(M15="","—",H15-N15),"—") | S34: Não | T34: =IFERROR(IF(H15=0,"—",IF(H15<=0.25,"✔ OK",IF(H15<=0.35,"⚠ Atenção","✖ Crítico"))),"—")
A35: Drinks | B35: Sucos | C35: Jarra Suco de Limão | D35: =VLOOKUP(E35,_Protheus_Cadastro!A:I,2,FALSE) | E35: 002028 | F35: =IFERROR(INDEX(Vendidos!$H:$H,MATCH(E35,Vendidos!$B:$B,0)),"—") | G35: =SUMIF('Fichas Flat'!$E$2:$E$880,E35,'Fichas Flat'!$K$2:$K$880) | H35: =IFERROR(G35/F35,0) | I35: =IFERROR(F35-G35,0) | J35: =IFERROR(I35/F35,0) | K35: =IFERROR(G35/0.3,0) | Q35: 46148 | R35: =IFERROR(IF(M16="","—",H16-N16),"—") | S35: Não | T35: =IFERROR(IF(H16=0,"—",IF(H16<=0.25,"✔ OK",IF(H16<=0.35,"⚠ Atenção","✖ Crítico"))),"—")
A36: Drinks | B36: Sucos | C36: Jarra Suco de Morango | D36: =VLOOKUP(E36,_Protheus_Cadastro!A:I,2,FALSE) | E36: 002031 | F36: =IFERROR(INDEX(Vendidos!$H:$H,MATCH(E36,Vendidos!$B:$B,0)),"—") | G36: =SUMIF('Fichas Flat'!$E$2:$E$880,E36,'Fichas Flat'!$K$2:$K$880) | H36: =IFERROR(G36/F36,0) | I36: =IFERROR(F36-G36,0) | J36: =IFERROR(I36/F36,0) | K36: =IFERROR(G36/0.3,0) | Q36: 46148 | R36: =IFERROR(IF(M17="","—",H17-N17),"—") | S36: Não | T36: =IFERROR(IF(H17=0,"—",IF(H17<=0.25,"✔ OK",IF(H17<=0.35,"⚠ Atenção","✖ Crítico"))),"—")
A37: Drinks | B37: Sucos | C37: Jarra Suco de Abacaxi com Hortelã | D37: =VLOOKUP(E37,_Protheus_Cadastro!A:I,2,FALSE) | E37: 002032 | F37: =IFERROR(INDEX(Vendidos!$H:$H,MATCH(E37,Vendidos!$B:$B,0)),"—") | G37: =SUMIF('Fichas Flat'!$E$2:$E$880,E37,'Fichas Flat'!$K$2:$K$880) | H37: =IFERROR(G37/F37,0) | I37: =IFERROR(F37-G37,0) | J37: =IFERROR(I37/F37,0) | K37: =IFERROR(G37/0.3,0) | Q37: 46148 | R37: =IFERROR(IF(M18="","—",H18-N18),"—") | S37: Não | T37: =IFERROR(IF(H18=0,"—",IF(H18<=0.25,"✔ OK",IF(H18<=0.35,"⚠ Atenção","✖ Crítico"))),"—")
A38: Drinks | B38: Sucos | C38: Jarra Suco de Abacaxi | D38: =VLOOKUP(E38,_Protheus_Cadastro!A:I,2,FALSE) | E38: 002056 | F38: =IFERROR(INDEX(Vendidos!$H:$H,MATCH(E38,Vendidos!$B:$B,0)),"—") | G38: =SUMIF('Fichas Flat'!$E$2:$E$880,E38,'Fichas Flat'!$K$2:$K$880) | H38: =IFERROR(G38/F38,0) | I38: =IFERROR(F38-G38,0) | J38: =IFERROR(I38/F38,0) | K38: =IFERROR(G38/0.3,0) | Q38: 46148 | R38: =IFERROR(IF(M19="","—",H19-N19),"—") | S38: Não | T38: =IFERROR(IF(H19=0,"—",IF(H19<=0.25,"✔ OK",IF(H19<=0.35,"⚠ Atenção","✖ Crítico"))),"—")
A39: Caipirinhas | B39: Caipirinha | C39: Cachaça do Quintal - Ouro | D39: =VLOOKUP(E39,_Protheus_Cadastro!A:I,2,FALSE) | E39: 000959 | F39: =IFERROR(INDEX(Vendidos!$H:$H,MATCH(E39,Vendidos!$B:$B,0)),"—") | G39: =SUMIF('Fichas Flat'!$E$2:$E$880,E39,'Fichas Flat'!$K$2:$K$880) | H39: =IFERROR(G39/F39,0) | I39: =IFERROR(F39-G39,0) | J39: =IFERROR(I39/F39,0) | K39: =IFERROR(G39/0.3,0) | Q39: 46148 | R39: =IFERROR(IF(M36="","—",H36-N36),"—") | S39: Sim | T39: =IFERROR(IF(H36=0,"—",IF(H36<=0.25,"✔ OK",IF(H36<=0.35,"⚠ Atenção","✖ Crítico"))),"—")
A40: Caipirinhas | B40: Caipirinha | C40: Cachaça do Quintal - Prata | D40: =VLOOKUP(E40,_Protheus_Cadastro!A:I,2,FALSE) | E40: 000958 | F40: =IFERROR(INDEX(Vendidos!$H:$H,MATCH(E40,Vendidos!$B:$B,0)),"—") | G40: =SUMIF('Fichas Flat'!$E$2:$E$880,E40,'Fichas Flat'!$K$2:$K$880) | H40: =IFERROR(G40/F40,0) | I40: =IFERROR(F40-G40,0) | J40: =IFERROR(I40/F40,0) | K40: =IFERROR(G40/0.3,0) | Q40: 46148 | R40: =IFERROR(IF(M37="","—",H37-N37),"—") | S40: Sim | T40: =IFERROR(IF(H37=0,"—",IF(H37<=0.25,"✔ OK",IF(H37<=0.35,"⚠ Atenção","✖ Crítico"))),"—")
A41: Caipirinhas | B41: Caipirinha | C41: Especial - Absolut | D41: =VLOOKUP(E41,_Protheus_Cadastro!A:I,2,FALSE) | E41: 000966 | F41: =IFERROR(INDEX(Vendidos!$H:$H,MATCH(E41,Vendidos!$B:$B,0)),"—") | G41: =SUMIF('Fichas Flat'!$E$2:$E$880,E41,'Fichas Flat'!$K$2:$K$880) | H41: =IFERROR(G41/F41,0) | I41: =IFERROR(F41-G41,0) | J41: =IFERROR(I41/F41,0) | K41: =IFERROR(G41/0.3,0) | Q41: 46148 | R41: =IFERROR(IF(M38="","—",H38-N38),"—") | S41: Sim | T41: =IFERROR(IF(H38=0,"—",IF(H38<=0.25,"✔ OK",IF(H38<=0.35,"⚠ Atenção","✖ Crítico"))),"—")
A42: Caipirinhas | B42: Caipirinha | C42: Especial - Cachaça do Quintal - Mel & Limão | D42: =VLOOKUP(E42,_Protheus_Cadastro!A:I,2,FALSE) | E42: 000960 | F42: =IFERROR(INDEX(Vendidos!$H:$H,MATCH(E42,Vendidos!$B:$B,0)),"—") | G42: =SUMIF('Fichas Flat'!$E$2:$E$880,E42,'Fichas Flat'!$K$2:$K$880) | H42: =IFERROR(G42/F42,0) | I42: =IFERROR(F42-G42,0) | J42: =IFERROR(I42/F42,0) | K42: =IFERROR(G42/0.3,0) | Q42: 46148 | R42: =IFERROR(IF(M39="","—",H39-N39),"—") | S42: Sim | T42: =IFERROR(IF(H39=0,"—",IF(H39<=0.25,"✔ OK",IF(H39<=0.35,"⚠ Atenção","✖ Crítico"))),"—")
A43: Caipirinhas | B43: Caipirinha | C43: Especial - São Francisco | D43: =VLOOKUP(E43,_Protheus_Cadastro!A:I,2,FALSE) | E43: 001032 | F43: =IFERROR(INDEX(Vendidos!$H:$H,MATCH(E43,Vendidos!$B:$B,0)),"—") | G43: =SUMIF('Fichas Flat'!$E$2:$E$880,E43,'Fichas Flat'!$K$2:$K$880) | H43: =IFERROR(G43/F43,0) | I43: =IFERROR(F43-G43,0) | J43: =IFERROR(I43/F43,0) | K43: =IFERROR(G43/0.3,0) | Q43: 46148 | R43: =IFERROR(IF(M40="","—",H40-N40),"—") | S43: Sim | T43: =IFERROR(IF(H40=0,"—",IF(H40<=0.25,"✔ OK",IF(H40<=0.35,"⚠ Atenção","✖ Crítico"))),"—")
A44: Caipirinhas | B44: Caipirinha | C44: Tradicional - Cachaça | D44: =VLOOKUP(E44,_Protheus_Cadastro!A:I,2,FALSE) | E44: 001023 | F44: =IFERROR(INDEX(Vendidos!$H:$H,MATCH(E44,Vendidos!$B:$B,0)),"—") | G44: =SUMIF('Fichas Flat'!$E$2:$E$880,E44,'Fichas Flat'!$K$2:$K$880) | H44: =IFERROR(G44/F44,0) | I44: =IFERROR(F44-G44,0) | J44: =IFERROR(I44/F44,0) | K44: =IFERROR(G44/0.3,0) | Q44: 46148 | R44: =IFERROR(IF(M41="","—",H41-N41),"—") | S44: Sim | T44: =IFERROR(IF(H41=0,"—",IF(H41<=0.25,"✔ OK",IF(H41<=0.35,"⚠ Atenção","✖ Crítico"))),"—")
A45: Caipirinhas | B45: Caipirinha | C45: Tradicional - Sake | D45: =VLOOKUP(E45,_Protheus_Cadastro!A:I,2,FALSE) | E45: 000922 | F45: =IFERROR(INDEX(Vendidos!$H:$H,MATCH(E45,Vendidos!$B:$B,0)),"—") | G45: =SUMIF('Fichas Flat'!$E$2:$E$880,E45,'Fichas Flat'!$K$2:$K$880) | H45: =IFERROR(G45/F45,0) | I45: =IFERROR(F45-G45,0) | J45: =IFERROR(I45/F45,0) | K45: =IFERROR(G45/0.3,0) | Q45: 46148 | R45: =IFERROR(IF(M42="","—",H42-N42),"—") | S45: Sim | T45: =IFERROR(IF(H42=0,"—",IF(H42<=0.25,"✔ OK",IF(H42<=0.35,"⚠ Atenção","✖ Crítico"))),"—")
A46: Caipirinhas | B46: Caipirinha | C46: Tradicional - Vodka | D46: =VLOOKUP(E46,_Protheus_Cadastro!A:I,2,FALSE) | E46: 001027 | F46: =IFERROR(INDEX(Vendidos!$H:$H,MATCH(E46,Vendidos!$B:$B,0)),"—") | G46: =SUMIF('Fichas Flat'!$E$2:$E$880,E46,'Fichas Flat'!$K$2:$K$880) | H46: =IFERROR(G46/F46,0) | I46: =IFERROR(F46-G46,0) | J46: =IFERROR(I46/F46,0) | K46: =IFERROR(G46/0.3,0) | Q46: 46148 | R46: =IFERROR(IF(M43="","—",H43-N43),"—") | S46: Sim | T46: =IFERROR(IF(H43=0,"—",IF(H43<=0.25,"✔ OK",IF(H43<=0.35,"⚠ Atenção","✖ Crítico"))),"—")
A47: Espetos | B47: In Natura | C47: Bovino | D47: =VLOOKUP(E47,_Protheus_Cadastro!A:I,2,FALSE) | E47: 000001 | F47: =IFERROR(INDEX(Vendidos!$H:$H,MATCH(E47,Vendidos!$B:$B,0)),"—") | G47: =SUMIF('Fichas Flat'!$E$2:$E$880,E47,'Fichas Flat'!$K$2:$K$880) | H47: =IFERROR(G47/F47,0) | I47: =IFERROR(F47-G47,0) | J47: =IFERROR(I47/F47,0) | K47: =IFERROR(G47/0.3,0) | L47: 29.9 | M47: 0 | N47: 0 | O47: 29.9 | P47: 1 | Q47: 46148 | R47: =IFERROR(IF(M46="","—",H47-N46),"—") | S47: Sim | T47: =IFERROR(IF(H46=0,"—",IF(H46<=0.25,"✔ OK",IF(H46<=0.35,"⚠ Atenção","✖ Crítico"))),"—")
A48: Espetos | B48: Boteco no Espeto | C48: Sticks de Muçarela | D48: =VLOOKUP(E48,_Protheus_Cadastro!A:I,2,FALSE) | E48: 001472 | F48: =IFERROR(INDEX(Vendidos!$H:$H,MATCH(E48,Vendidos!$B:$B,0)),"—") | G48: =SUMIF('Fichas Flat'!$E$2:$E$880,E48,'Fichas Flat'!$K$2:$K$880) | H48: =IFERROR(G48/F48,0) | I48: =IFERROR(F48-G48,0) | J48: =IFERROR(I48/F48,0) | K48: =IFERROR(G48/0.3,0) | L48: 14.99 | M48: 2.199 | N48: 0.1466978 | O48: 12.791 | P48: 0.8533022 | Q48: 46148 | R48: =IFERROR(IF(M47="","—",H48-N47),"—") | S48: Sim | T48: =IFERROR(IF(H47=0,"—",IF(H47<=0.25,"✔ OK",IF(H47<=0.35,"⚠ Atenção","✖ Crítico"))),"—")
A49: Drinks | B49: Drinks | C49: Fiufiu cajá lemon | D49: =VLOOKUP(E49,_Protheus_Cadastro!A:I,2,FALSE) | E49: 002015 | F49: =IFERROR(INDEX(Vendidos!$H:$H,MATCH(E49,Vendidos!$B:$B,0)),"—") | G49: =SUMIF('Fichas Flat'!$E$2:$E$880,E49,'Fichas Flat'!$K$2:$K$880) | H49: =IFERROR(G49/F49,0) | I49: =IFERROR(F49-G49,0) | J49: =IFERROR(I49/F49,0) | K49: =IFERROR(G49/0.3,0) | L49: 34 | M49: 9.9375 | N49: 0.29227941 | O49: 24.0625 | P49: 0.70772059 | Q49: 46148 | R49: =IFERROR(IF(M48="","—",H49-N48),"—") | S49: Sim | T49: =IFERROR(IF(H48=0,"—",IF(H48<=0.25,"✔ OK",IF(H48<=0.35,"⚠ Atenção","✖ Crítico"))),"—")
A50: Espetos | B50: In Natura | C50: Coração | D50: =VLOOKUP(E50,_Protheus_Cadastro!A:I,2,FALSE) | E50: 000004 | F50: =IFERROR(INDEX(Vendidos!$H:$H,MATCH(E50,Vendidos!$B:$B,0)),"—") | G50: =SUMIF('Fichas Flat'!$E$2:$E$880,E50,'Fichas Flat'!$K$2:$K$880) | H50: =IFERROR(G50/F50,0) | I50: =IFERROR(F50-G50,0) | J50: =IFERROR(I50/F50,0) | K50: =IFERROR(G50/0.3,0) | L50: 29.9 | M50: 10.5 | N50: 0.35117057 | O50: 19.4 | P50: 0.64882943 | Q50: 46148 | R50: =IFERROR(IF(M49="","—",H50-N49),"—") | S50: Sim | T50: =IFERROR(IF(H49=0,"—",IF(H49<=0.25,"✔ OK",IF(H49<=0.35,"⚠ Atenção","✖ Crítico"))),"—")
A51: Espetos | B51: In Natura | C51: Picanha | D51: =VLOOKUP(E51,_Protheus_Cadastro!A:I,2,FALSE) | E51: 000011 | F51: =IFERROR(INDEX(Vendidos!$H:$H,MATCH(E51,Vendidos!$B:$B,0)),"—") | G51: =SUMIF('Fichas Flat'!$E$2:$E$880,E51,'Fichas Flat'!$K$2:$K$880) | H51: =IFERROR(G51/F51,0) | I51: =IFERROR(F51-G51,0) | J51: =IFERROR(I51/F51,0) | K51: =IFERROR(G51/0.3,0) | L51: 69.9 | M51: 20.9 | N51: 0.29899857 | O51: 49 | P51: 0.70100143 | Q51: 46148 | R51: =IFERROR(IF(M50="","—",H51-N50),"—") | S51: Sim | T51: =IFERROR(IF(H50=0,"—",IF(H50<=0.25,"✔ OK",IF(H50<=0.35,"⚠ Atenção","✖ Crítico"))),"—")
A52: Espetos | B52: In Natura | C52: Cordeiro | D52: =VLOOKUP(E52,_Protheus_Cadastro!A:I,2,FALSE) | E52: 000016 | F52: =IFERROR(INDEX(Vendidos!$H:$H,MATCH(E52,Vendidos!$B:$B,0)),"—") | G52: =SUMIF('Fichas Flat'!$E$2:$E$880,E52,'Fichas Flat'!$K$2:$K$880) | H52: =IFERROR(G52/F52,0) | I52: =IFERROR(F52-G52,0) | J52: =IFERROR(I52/F52,0) | K52: =IFERROR(G52/0.3,0) | L52: 69.9 | M52: 11.858 | N52: 0.16964235 | O52: 58.042 | P52: 0.83035765 | Q52: 46148 | R52: =IFERROR(IF(M51="","—",H52-N51),"—") | S52: Sim | T52: =IFERROR(IF(H51=0,"—",IF(H51<=0.25,"✔ OK",IF(H51<=0.35,"⚠ Atenção","✖ Crítico"))),"—")
A53: Bebidas Frias | B53: Whiskies | C53: Black Label | D53: =VLOOKUP(E53,_Protheus_Cadastro!A:I,2,FALSE) | E53: 001338 | F53: =IFERROR(INDEX(Vendidos!$H:$H,MATCH(E53,Vendidos!$B:$B,0)),"—") | G53: =SUMIF('Fichas Flat'!$E$2:$E$880,E53,'Fichas Flat'!$K$2:$K$880) | H53: =IFERROR(G53/F53,0) | I53: =IFERROR(F53-G53,0) | J53: =IFERROR(I53/F53,0) | K53: =IFERROR(G53/0.3,0) | L53: 239.99 | M53: 0 | N53: 0 | O53: 239.99 | P53: 1 | Q53: 46148 | R53: =IFERROR(IF(M52="","—",H53-N52),"—") | S53: Sim | T53: =IFERROR(IF(H52=0,"—",IF(H52<=0.25,"✔ OK",IF(H52<=0.35,"⚠ Atenção","✖ Crítico"))),"—")
A54: Drinks | B54: Drinks | C54: Combo Tanqueray com 3 Red Bull | D54: =VLOOKUP(E54,_Protheus_Cadastro!A:I,2,FALSE) | E54: 001204 | F54: =IFERROR(INDEX(Vendidos!$H:$H,MATCH(E54,Vendidos!$B:$B,0)),"—") | G54: =SUMIF('Fichas Flat'!$E$2:$E$880,E54,'Fichas Flat'!$K$2:$K$880) | H54: =IFERROR(G54/F54,0) | I54: =IFERROR(F54-G54,0) | J54: =IFERROR(I54/F54,0) | K54: =IFERROR(G54/0.3,0) | L54: 329.99 | M54: 2.10467 | N54: 0.0063779812 | O54: 327.88533 | P54: 0.99362202 | Q54: 46148 | R54: =IFERROR(IF(M53="","—",H54-N53),"—") | S54: Sim | T54: =IFERROR(IF(H53=0,"—",IF(H53<=0.25,"✔ OK",IF(H53<=0.35,"⚠ Atenção","✖ Crítico"))),"—")
A55: Delivery | B55: Delivery | C55: Prato Feito Quintal | D55: =VLOOKUP(E55,_Protheus_Cadastro!A:I,2,FALSE) | E55: 002216 | F55: =IFERROR(INDEX(Vendidos!$H:$H,MATCH(E55,Vendidos!$B:$B,0)),"—") | G55: =SUMIF('Fichas Flat'!$E$2:$E$880,E55,'Fichas Flat'!$K$2:$K$880) | H55: =IFERROR(G55/F55,0) | I55: =IFERROR(F55-G55,0) | J55: =IFERROR(I55/F55,0) | K55: =IFERROR(G55/0.3,0) | L55: 39.9 | M55: 1.783836 | N55: 0.044707669 | O55: 38.116164 | P55: 0.95529233 | Q55: 46148 | R55: =IFERROR(IF(M54="","—",H55-N54),"—") | S55: Não | T55: =IFERROR(IF(H54=0,"—",IF(H54<=0.25,"✔ OK",IF(H54<=0.35,"⚠ Atenção","✖ Crítico"))),"—")
A56: Delivery | B56: Delivery | C56: Combo Quintal Feliz | D56: =VLOOKUP(E56,_Protheus_Cadastro!A:I,2,FALSE) | E56: 009844 | F56: =IFERROR(INDEX(Vendidos!$H:$H,MATCH(E56,Vendidos!$B:$B,0)),"—") | G56: =SUMIF('Fichas Flat'!$E$2:$E$880,E56,'Fichas Flat'!$K$2:$K$880) | H56: =IFERROR(G56/F56,0) | I56: =IFERROR(F56-G56,0) | J56: =IFERROR(I56/F56,0) | K56: =IFERROR(G56/0.3,0) | L56: 49.99 | M56: 0.947255 | N56: 0.01894889 | O56: 49.042745 | P56: 0.98105111 | Q56: 46148 | R56: =IFERROR(IF(M55="","—",H56-N55),"—") | S56: Sim | T56: =IFERROR(IF(H55=0,"—",IF(H55<=0.25,"✔ OK",IF(H55<=0.35,"⚠ Atenção","✖ Crítico"))),"—")
A57: Bebidas Frias | B57: Tequila | C57: Jose Cuervo Ouro | D57: =VLOOKUP(E57,_Protheus_Cadastro!A:I,2,FALSE) | E57: 000045 | F57: =IFERROR(INDEX(Vendidos!$H:$H,MATCH(E57,Vendidos!$B:$B,0)),"—") | G57: =SUMIF('Fichas Flat'!$E$2:$E$880,E57,'Fichas Flat'!$K$2:$K$880) | H57: =IFERROR(G57/F57,0) | I57: =IFERROR(F57-G57,0) | J57: =IFERROR(I57/F57,0) | K57: =IFERROR(G57/0.3,0) | L57: 290.99 | M57: 5.89 | N57: 0.020241245 | O57: 285.1 | P57: 0.97975875 | Q57: 46148 | R57: =IFERROR(IF(M56="","—",H57-N56),"—") | S57: Sim | T57: =IFERROR(IF(H56=0,"—",IF(H56<=0.25,"✔ OK",IF(H56<=0.35,"⚠ Atenção","✖ Crítico"))),"—")
A58: Bebidas Frias | B58: Whiskies | C58: Gold Label | D58: =VLOOKUP(E58,_Protheus_Cadastro!A:I,2,FALSE) | E58: 001334 | F58: =IFERROR(INDEX(Vendidos!$H:$H,MATCH(E58,Vendidos!$B:$B,0)),"—") | G58: =SUMIF('Fichas Flat'!$E$2:$E$880,E58,'Fichas Flat'!$K$2:$K$880) | H58: =IFERROR(G58/F58,0) | I58: =IFERROR(F58-G58,0) | J58: =IFERROR(I58/F58,0) | K58: =IFERROR(G58/0.3,0) | L58: 690.99 | M58: 4.0117 | N58: 0.005805728 | O58: 686.9783 | P58: 0.99419427 | Q58: 46148 | R58: =IFERROR(IF(M57="","—",H58-N57),"—") | S58: Sim | T58: =IFERROR(IF(H57=0,"—",IF(H57<=0.25,"✔ OK",IF(H57<=0.35,"⚠ Atenção","✖ Crítico"))),"—")
... A241: Guarnições | B241: Guarnições | C241: Feijão | D241: =VLOOKUP(E241,_Protheus_Cadastro!A:I,2,FALSE) | E241: 002209 | F241: =IFERROR(INDEX(Vendidos!$H:$H,MATCH(E241,Vendidos!$B:$B,0)),"—") | G241: =SUMIF('Fichas Flat'!$E$2:$E$880,E241,'Fichas Flat'!$K$2:$K$880) | H241: =IFERROR(G241/F241,0) | I241: =IFERROR(F241-G241,0) | J241: =IFERROR(I241/F241,0) | K241: =IFERROR(G241/0.3,0) | L241: 9.9 | M241: 185.58 | N241: 18.745455 | O241: -175.68 | P241: -17.745455 | Q241: 46148 | R241: =IFERROR(IF(M240="","—",H241-N240),"—") | S241: Sim | T241: =IFERROR(IF(H240=0,"—",IF(H240<=0.25,"✔ OK",IF(H240<=0.35,"⚠ Atenção","✖ Crítico"))),"—")

Sheet Vendidos
A1: Identificação Protheus | H1: Dados ZIG | N1: Locais
A2: Origem | B2: Código Protheus | C2: Nome PA (Protheus) | D2: Tipo | E2: Und. | F2: Estrutura Protheus | G2: Bloqueado Protheus | H2: Preço Venda (ZIG) | I2: SKU ZIG | J2: Nome (ZIG) | K2: Categoria (ZIG) | L2: Status Validação | M2: Situação ZIG | N2: Locais (completo) | O2: Carinás | P2: Lapa | Q2: Tatuapé | R2: Pavão | S2: Chac. | T2: V. Madalena | U2: V. Mariana | V2: Perdizes | W2: Santana | X2: Sto. André | Y2: Del. Carinás | Z2: Del. Lapa | AA2: Del. Tatuapé | AB2: Del. Pavão | AC2: Del. Chac. | AD2: Del. V. Madalena | AE2: Del. V. Mariana | AF2: Del. Perdizes | AG2: Del. Santana | AH2: Del. Sto. André | AI2: Interlagos | AJ2: Quiosque | AK2: Observação
A3: Protheus | B3: 001408 | C3: =IF(B3="—","—",IFERROR(VLOOKUP(B3,_Protheus_Cadastro!$A:$B,2,FALSE),"—")) | D3: =IF(B3="—",IFERROR(INDEX(_ZIG_Cadastro!$D:$D,MATCH(H3,_ZIG_Cadastro!$A:$A,0)),"Produto"),IFERROR(VLOOKUP(B3,_Protheus_Cadastro!$A:$C,3,FALSE),"—")) | E3: =IF(B3="—","—",IFERROR(VLOOKUP(B3,_Protheus_Cadastro!$A:$D,4,FALSE),"—")) | F3: =IF(ISERROR(VLOOKUP(B3,'Estrutura Protheus'!A:A,1,FALSE)),"Não","Sim") | G3: =IFERROR(INDEX(_Protheus_Cadastro!$H:$H,MATCH(B3,_Protheus_Cadastro!$A:$A,0)),"—") | H3: =IFERROR(INDEX(_ZIG_Precos!$D:$D,MATCH(I3,_ZIG_Precos!$F:$F,0)),"—") | I3: =IFERROR(VLOOKUP(B3,_Protheus_Cadastro!$A:$I,9,FALSE),"—") | J3: =IFERROR(INDEX(_ZIG_Cadastro!$B:$B,MATCH(I3,_ZIG_Cadastro!$A:$A,0)),IFERROR(INDEX(_Entradas_ZIG!$B:$B,MATCH(I3,_Entradas_ZIG!$C:$C,0)),"—")) | K3: =IFERROR(INDEX(_ZIG_Cadastro!$C:$C,MATCH(I3,_ZIG_Cadastro!$A:$A,0)),IFERROR(INDEX(_Entradas_ZIG!$D:$D,MATCH(I3,_Entradas_ZIG!$C:$C,0)),"—")) | L3: =IF(I3="","Sem SKU ZIG",IF(I3="—","Sem SKU ZIG",IF(NOT(ISERROR(MATCH(I3,_ZIG_Cadastro!$A:$A,0))),IF(EXACT(UPPER(TRIM(C3)),UPPER(TRIM(INDEX(_ZIG_Cadastro!$B:$B,MATCH(I3,_ZIG_Cadastro!$A:$A,0))))),"OK","Atencao - Nome diverge"),IF(NOT(ISERROR(MATCH(I3,_Entradas_ZIG!$C:$C,0))),"OK","Erro - SKU nao encontrado")))) | M3: =IFERROR(INDEX(_ZIG_Cadastro!$G:$G,MATCH(I3,_ZIG_Cadastro!$A:$A,0)),IF(NOT(ISERROR(MATCH(I3,_Entradas_ZIG!$C:$C,0))),"Ativo","—")) | N3: =IFERROR(INDEX(_ZIG_Cadastro!$E:$E,MATCH(I3,_ZIG_Cadastro!$A:$A,0)),IFERROR(INDEX(_Entradas_ZIG!$F:$F,MATCH(I3,_Entradas_ZIG!$C:$C,0)),"—")) | O3: =IF(AND(ISNUMBER(SEARCH("Espeto",N3)),ISNUMBER(SEARCH("Carin",N3))),"SIM","") | P3: =IF(AND(ISNUMBER(SEARCH("Espeto",N3)),ISNUMBER(SEARCH("Lapa",N3))),"SIM","") | Q3: =IF(AND(ISNUMBER(SEARCH("Espeto",N3)),ISNUMBER(SEARCH("Tatuapé",N3))),"SIM","") | R3: =IF(AND(ISNUMBER(SEARCH("Espeto",N3)),ISNUMBER(SEARCH("Pavão",N3))),"SIM","") | S3: =IF(AND(ISNUMBER(SEARCH("Espeto",N3)),ISNUMBER(SEARCH("Chac",N3))),"SIM","") | T3: =IF(AND(ISNUMBER(SEARCH("Espeto",N3)),ISNUMBER(SEARCH("Madalena",N3))),"SIM","") | U3: =IF(AND(ISNUMBER(SEARCH("Espeto",N3)),ISNUMBER(SEARCH("Mariana",N3))),"SIM","") | V3: =IF(AND(ISNUMBER(SEARCH("Espeto",N3)),ISNUMBER(SEARCH("Perdizes",N3))),"SIM","") | W3: =IF(AND(ISNUMBER(SEARCH("Espeto",N3)),ISNUMBER(SEARCH("Santana",N3))),"SIM","") | X3: =IF(AND(ISNUMBER(SEARCH("Espeto",N3)),ISNUMBER(SEARCH("André",N3))),"SIM","") | Y3: =IF(AND(ISNUMBER(SEARCH("Delivery",N3)),ISNUMBER(SEARCH("Carin",N3))),"SIM","") | Z3: =IF(AND(ISNUMBER(SEARCH("Delivery",N3)),ISNUMBER(SEARCH("Lapa",N3))),"SIM","") | AA3: =IF(AND(ISNUMBER(SEARCH("Delivery",N3)),ISNUMBER(SEARCH("Tatuapé",N3))),"SIM","") | AB3: =IF(AND(ISNUMBER(SEARCH("Delivery",N3)),ISNUMBER(SEARCH("Pavão",N3))),"SIM","") | AC3: =IF(AND(ISNUMBER(SEARCH("Delivery",N3)),ISNUMBER(SEARCH("Chac",N3))),"SIM","") | AD3: =IF(AND(ISNUMBER(SEARCH("Delivery",N3)),ISNUMBER(SEARCH("Madalena",N3))),"SIM","") | AE3: =IF(AND(ISNUMBER(SEARCH("Delivery",N3)),ISNUMBER(SEARCH("Mariana",N3))),"SIM","") | AF3: =IF(AND(ISNUMBER(SEARCH("Delivery",N3)),ISNUMBER(SEARCH("Perdizes",N3))),"SIM","") | AG3: =IF(AND(ISNUMBER(SEARCH("Delivery",N3)),ISNUMBER(SEARCH("Santana",N3))),"SIM","") | AH3: =IF(AND(ISNUMBER(SEARCH("Delivery",N3)),ISNUMBER(SEARCH("André",N3))),"SIM","") | AI3: =IF(ISNUMBER(SEARCH("Interlagos",N3)),"SIM","") | AJ3: =IF(ISNUMBER(SEARCH("Quiosque",N3)),"SIM","")
A4: Protheus | B4: 001257 | C4: =IF(B4="—","—",IFERROR(VLOOKUP(B4,_Protheus_Cadastro!$A:$B,2,FALSE),"—")) | D4: =IF(B4="—",IFERROR(INDEX(_ZIG_Cadastro!$D:$D,MATCH(H4,_ZIG_Cadastro!$A:$A,0)),"Produto"),IFERROR(VLOOKUP(B4,_Protheus_Cadastro!$A:$C,3,FALSE),"—")) | E4: =IF(B4="—","—",IFERROR(VLOOKUP(B4,_Protheus_Cadastro!$A:$D,4,FALSE),"—")) | F4: =IF(ISERROR(VLOOKUP(B4,'Estrutura Protheus'!A:A,1,FALSE)),"Não","Sim") | G4: =IFERROR(INDEX(_Protheus_Cadastro!$H:$H,MATCH(B4,_Protheus_Cadastro!$A:$A,0)),"—") | H4: =IFERROR(INDEX(_ZIG_Precos!$D:$D,MATCH(I4,_ZIG_Precos!$F:$F,0)),"—") | I4: =IFERROR(VLOOKUP(B4,_Protheus_Cadastro!$A:$I,9,FALSE),"—") | J4: =IFERROR(INDEX(_ZIG_Cadastro!$B:$B,MATCH(I4,_ZIG_Cadastro!$A:$A,0)),IFERROR(INDEX(_Entradas_ZIG!$B:$B,MATCH(I4,_Entradas_ZIG!$C:$C,0)),"—")) | K4: =IFERROR(INDEX(_ZIG_Cadastro!$C:$C,MATCH(I4,_ZIG_Cadastro!$A:$A,0)),IFERROR(INDEX(_Entradas_ZIG!$D:$D,MATCH(I4,_Entradas_ZIG!$C:$C,0)),"—")) | L4: =IF(I4="","Sem SKU ZIG",IF(I4="—","Sem SKU ZIG",IF(NOT(ISERROR(MATCH(I4,_ZIG_Cadastro!$A:$A,0))),IF(EXACT(UPPER(TRIM(C4)),UPPER(TRIM(INDEX(_ZIG_Cadastro!$B:$B,MATCH(I4,_ZIG_Cadastro!$A:$A,0))))),"OK","Atencao - Nome diverge"),IF(NOT(ISERROR(MATCH(I4,_Entradas_ZIG!$C:$C,0))),"OK","Erro - SKU nao encontrado")))) | M4: =IFERROR(INDEX(_ZIG_Cadastro!$G:$G,MATCH(I4,_ZIG_Cadastro!$A:$A,0)),IF(NOT(ISERROR(MATCH(I4,_Entradas_ZIG!$C:$C,0))),"Ativo","—")) | N4: =IFERROR(INDEX(_ZIG_Cadastro!$E:$E,MATCH(I4,_ZIG_Cadastro!$A:$A,0)),IFERROR(INDEX(_Entradas_ZIG!$F:$F,MATCH(I4,_Entradas_ZIG!$C:$C,0)),"—")) | O4: =IF(AND(ISNUMBER(SEARCH("Espeto",N4)),ISNUMBER(SEARCH("Carin",N4))),"SIM","") | P4: =IF(AND(ISNUMBER(SEARCH("Espeto",N4)),ISNUMBER(SEARCH("Lapa",N4))),"SIM","") | Q4: =IF(AND(ISNUMBER(SEARCH("Espeto",N4)),ISNUMBER(SEARCH("Tatuapé",N4))),"SIM","") | R4: =IF(AND(ISNUMBER(SEARCH("Espeto",N4)),ISNUMBER(SEARCH("Pavão",N4))),"SIM","") | S4: =IF(AND(ISNUMBER(SEARCH("Espeto",N4)),ISNUMBER(SEARCH("Chac",N4))),"SIM","") | T4: =IF(AND(ISNUMBER(SEARCH("Espeto",N4)),ISNUMBER(SEARCH("Madalena",N4))),"SIM","") | U4: =IF(AND(ISNUMBER(SEARCH("Espeto",N4)),ISNUMBER(SEARCH("Mariana",N4))),"SIM","") | V4: =IF(AND(ISNUMBER(SEARCH("Espeto",N4)),ISNUMBER(SEARCH("Perdizes",N4))),"SIM","") | W4: =IF(AND(ISNUMBER(SEARCH("Espeto",N4)),ISNUMBER(SEARCH("Santana",N4))),"SIM","") | X4: =IF(AND(ISNUMBER(SEARCH("Espeto",N4)),ISNUMBER(SEARCH("André",N4))),"SIM","") | Y4: =IF(AND(ISNUMBER(SEARCH("Delivery",N4)),ISNUMBER(SEARCH("Carin",N4))),"SIM","") | Z4: =IF(AND(ISNUMBER(SEARCH("Delivery",N4)),ISNUMBER(SEARCH("Lapa",N4))),"SIM","") | AA4: =IF(AND(ISNUMBER(SEARCH("Delivery",N4)),ISNUMBER(SEARCH("Tatuapé",N4))),"SIM","") | AB4: =IF(AND(ISNUMBER(SEARCH("Delivery",N4)),ISNUMBER(SEARCH("Pavão",N4))),"SIM","") | AC4: =IF(AND(ISNUMBER(SEARCH("Delivery",N4)),ISNUMBER(SEARCH("Chac",N4))),"SIM","") | AD4: =IF(AND(ISNUMBER(SEARCH("Delivery",N4)),ISNUMBER(SEARCH("Madalena",N4))),"SIM","") | AE4: =IF(AND(ISNUMBER(SEARCH("Delivery",N4)),ISNUMBER(SEARCH("Mariana",N4))),"SIM","") | AF4: =IF(AND(ISNUMBER(SEARCH("Delivery",N4)),ISNUMBER(SEARCH("Perdizes",N4))),"SIM","") | AG4: =IF(AND(ISNUMBER(SEARCH("Delivery",N4)),ISNUMBER(SEARCH("Santana",N4))),"SIM","") | AH4: =IF(AND(ISNUMBER(SEARCH("Delivery",N4)),ISNUMBER(SEARCH("André",N4))),"SIM","") | AI4: =IF(ISNUMBER(SEARCH("Interlagos",N4)),"SIM","") | AJ4: =IF(ISNUMBER(SEARCH("Quiosque",N4)),"SIM","")
A5: Protheus | B5: 001266 | C5: =IF(B5="—","—",IFERROR(VLOOKUP(B5,_Protheus_Cadastro!$A:$B,2,FALSE),"—")) | D5: =IF(B5="—",IFERROR(INDEX(_ZIG_Cadastro!$D:$D,MATCH(H5,_ZIG_Cadastro!$A:$A,0)),"Produto"),IFERROR(VLOOKUP(B5,_Protheus_Cadastro!$A:$C,3,FALSE),"—")) | E5: =IF(B5="—","—",IFERROR(VLOOKUP(B5,_Protheus_Cadastro!$A:$D,4,FALSE),"—")) | F5: =IF(ISERROR(VLOOKUP(B5,'Estrutura Protheus'!A:A,1,FALSE)),"Não","Sim") | G5: =IFERROR(INDEX(_Protheus_Cadastro!$H:$H,MATCH(B5,_Protheus_Cadastro!$A:$A,0)),"—") | H5: =IFERROR(INDEX(_ZIG_Precos!$D:$D,MATCH(I5,_ZIG_Precos!$F:$F,0)),"—") | I5: =IFERROR(VLOOKUP(B5,_Protheus_Cadastro!$A:$I,9,FALSE),"—") | J5: =IFERROR(INDEX(_ZIG_Cadastro!$B:$B,MATCH(I5,_ZIG_Cadastro!$A:$A,0)),IFERROR(INDEX(_Entradas_ZIG!$B:$B,MATCH(I5,_Entradas_ZIG!$C:$C,0)),"—")) | K5: =IFERROR(INDEX(_ZIG_Cadastro!$C:$C,MATCH(I5,_ZIG_Cadastro!$A:$A,0)),IFERROR(INDEX(_Entradas_ZIG!$D:$D,MATCH(I5,_Entradas_ZIG!$C:$C,0)),"—")) | L5: =IF(I5="","Sem SKU ZIG",IF(I5="—","Sem SKU ZIG",IF(NOT(ISERROR(MATCH(I5,_ZIG_Cadastro!$A:$A,0))),IF(EXACT(UPPER(TRIM(C5)),UPPER(TRIM(INDEX(_ZIG_Cadastro!$B:$B,MATCH(I5,_ZIG_Cadastro!$A:$A,0))))),"OK","Atencao - Nome diverge"),IF(NOT(ISERROR(MATCH(I5,_Entradas_ZIG!$C:$C,0))),"OK","Erro - SKU nao encontrado")))) | M5: =IFERROR(INDEX(_ZIG_Cadastro!$G:$G,MATCH(I5,_ZIG_Cadastro!$A:$A,0)),IF(NOT(ISERROR(MATCH(I5,_Entradas_ZIG!$C:$C,0))),"Ativo","—")) | N5: =IFERROR(INDEX(_ZIG_Cadastro!$E:$E,MATCH(I5,_ZIG_Cadastro!$A:$A,0)),IFERROR(INDEX(_Entradas_ZIG!$F:$F,MATCH(I5,_Entradas_ZIG!$C:$C,0)),"—")) | O5: =IF(AND(ISNUMBER(SEARCH("Espeto",N5)),ISNUMBER(SEARCH("Carin",N5))),"SIM","") | P5: =IF(AND(ISNUMBER(SEARCH("Espeto",N5)),ISNUMBER(SEARCH("Lapa",N5))),"SIM","") | Q5: =IF(AND(ISNUMBER(SEARCH("Espeto",N5)),ISNUMBER(SEARCH("Tatuapé",N5))),"SIM","") | R5: =IF(AND(ISNUMBER(SEARCH("Espeto",N5)),ISNUMBER(SEARCH("Pavão",N5))),"SIM","") | S5: =IF(AND(ISNUMBER(SEARCH("Espeto",N5)),ISNUMBER(SEARCH("Chac",N5))),"SIM","") | T5: =IF(AND(ISNUMBER(SEARCH("Espeto",N5)),ISNUMBER(SEARCH("Madalena",N5))),"SIM","") | U5: =IF(AND(ISNUMBER(SEARCH("Espeto",N5)),ISNUMBER(SEARCH("Mariana",N5))),"SIM","") | V5: =IF(AND(ISNUMBER(SEARCH("Espeto",N5)),ISNUMBER(SEARCH("Perdizes",N5))),"SIM","") | W5: =IF(AND(ISNUMBER(SEARCH("Espeto",N5)),ISNUMBER(SEARCH("Santana",N5))),"SIM","") | X5: =IF(AND(ISNUMBER(SEARCH("Espeto",N5)),ISNUMBER(SEARCH("André",N5))),"SIM","") | Y5: =IF(AND(ISNUMBER(SEARCH("Delivery",N5)),ISNUMBER(SEARCH("Carin",N5))),"SIM","") | Z5: =IF(AND(ISNUMBER(SEARCH("Delivery",N5)),ISNUMBER(SEARCH("Lapa",N5))),"SIM","") | AA5: =IF(AND(ISNUMBER(SEARCH("Delivery",N5)),ISNUMBER(SEARCH("Tatuapé",N5))),"SIM","") | AB5: =IF(AND(ISNUMBER(SEARCH("Delivery",N5)),ISNUMBER(SEARCH("Pavão",N5))),"SIM","") | AC5: =IF(AND(ISNUMBER(SEARCH("Delivery",N5)),ISNUMBER(SEARCH("Chac",N5))),"SIM","") | AD5: =IF(AND(ISNUMBER(SEARCH("Delivery",N5)),ISNUMBER(SEARCH("Madalena",N5))),"SIM","") | AE5: =IF(AND(ISNUMBER(SEARCH("Delivery",N5)),ISNUMBER(SEARCH("Mariana",N5))),"SIM","") | AF5: =IF(AND(ISNUMBER(SEARCH("Delivery",N5)),ISNUMBER(SEARCH("Perdizes",N5))),"SIM","") | AG5: =IF(AND(ISNUMBER(SEARCH("Delivery",N5)),ISNUMBER(SEARCH("Santana",N5))),"SIM","") | AH5: =IF(AND(ISNUMBER(SEARCH("Delivery",N5)),ISNUMBER(SEARCH("André",N5))),"SIM","") | AI5: =IF(ISNUMBER(SEARCH("Interlagos",N5)),"SIM","") | AJ5: =IF(ISNUMBER(SEARCH("Quiosque",N5)),"SIM","")
A6: Protheus | B6: 001267 | C6: =IF(B6="—","—",IFERROR(VLOOKUP(B6,_Protheus_Cadastro!$A:$B,2,FALSE),"—")) | D6: =IF(B6="—",IFERROR(INDEX(_ZIG_Cadastro!$D:$D,MATCH(H6,_ZIG_Cadastro!$A:$A,0)),"Produto"),IFERROR(VLOOKUP(B6,_Protheus_Cadastro!$A:$C,3,FALSE),"—")) | E6: =IF(B6="—","—",IFERROR(VLOOKUP(B6,_Protheus_Cadastro!$A:$D,4,FALSE),"—")) | F6: =IF(ISERROR(VLOOKUP(B6,'Estrutura Protheus'!A:A,1,FALSE)),"Não","Sim") | G6: =IFERROR(INDEX(_Protheus_Cadastro!$H:$H,MATCH(B6,_Protheus_Cadastro!$A:$A,0)),"—") | H6: =IFERROR(INDEX(_ZIG_Precos!$D:$D,MATCH(I6,_ZIG_Precos!$F:$F,0)),"—") | I6: =IFERROR(VLOOKUP(B6,_Protheus_Cadastro!$A:$I,9,FALSE),"—") | J6: =IFERROR(INDEX(_ZIG_Cadastro!$B:$B,MATCH(I6,_ZIG_Cadastro!$A:$A,0)),IFERROR(INDEX(_Entradas_ZIG!$B:$B,MATCH(I6,_Entradas_ZIG!$C:$C,0)),"—")) | K6: =IFERROR(INDEX(_ZIG_Cadastro!$C:$C,MATCH(I6,_ZIG_Cadastro!$A:$A,0)),IFERROR(INDEX(_Entradas_ZIG!$D:$D,MATCH(I6,_Entradas_ZIG!$C:$C,0)),"—")) | L6: =IF(I6="","Sem SKU ZIG",IF(I6="—","Sem SKU ZIG",IF(NOT(ISERROR(MATCH(I6,_ZIG_Cadastro!$A:$A,0))),IF(EXACT(UPPER(TRIM(C6)),UPPER(TRIM(INDEX(_ZIG_Cadastro!$B:$B,MATCH(I6,_ZIG_Cadastro!$A:$A,0))))),"OK","Atencao - Nome diverge"),IF(NOT(ISERROR(MATCH(I6,_Entradas_ZIG!$C:$C,0))),"OK","Erro - SKU nao encontrado")))) | M6: =IFERROR(INDEX(_ZIG_Cadastro!$G:$G,MATCH(I6,_ZIG_Cadastro!$A:$A,0)),IF(NOT(ISERROR(MATCH(I6,_Entradas_ZIG!$C:$C,0))),"Ativo","—")) | N6: =IFERROR(INDEX(_ZIG_Cadastro!$E:$E,MATCH(I6,_ZIG_Cadastro!$A:$A,0)),IFERROR(INDEX(_Entradas_ZIG!$F:$F,MATCH(I6,_Entradas_ZIG!$C:$C,0)),"—")) | O6: =IF(AND(ISNUMBER(SEARCH("Espeto",N6)),ISNUMBER(SEARCH("Carin",N6))),"SIM","") | P6: =IF(AND(ISNUMBER(SEARCH("Espeto",N6)),ISNUMBER(SEARCH("Lapa",N6))),"SIM","") | Q6: =IF(AND(ISNUMBER(SEARCH("Espeto",N6)),ISNUMBER(SEARCH("Tatuapé",N6))),"SIM","") | R6: =IF(AND(ISNUMBER(SEARCH("Espeto",N6)),ISNUMBER(SEARCH("Pavão",N6))),"SIM","") | S6: =IF(AND(ISNUMBER(SEARCH("Espeto",N6)),ISNUMBER(SEARCH("Chac",N6))),"SIM","") | T6: =IF(AND(ISNUMBER(SEARCH("Espeto",N6)),ISNUMBER(SEARCH("Madalena",N6))),"SIM","") | U6: =IF(AND(ISNUMBER(SEARCH("Espeto",N6)),ISNUMBER(SEARCH("Mariana",N6))),"SIM","") | V6: =IF(AND(ISNUMBER(SEARCH("Espeto",N6)),ISNUMBER(SEARCH("Perdizes",N6))),"SIM","") | W6: =IF(AND(ISNUMBER(SEARCH("Espeto",N6)),ISNUMBER(SEARCH("Santana",N6))),"SIM","") | X6: =IF(AND(ISNUMBER(SEARCH("Espeto",N6)),ISNUMBER(SEARCH("André",N6))),"SIM","") | Y6: =IF(AND(ISNUMBER(SEARCH("Delivery",N6)),ISNUMBER(SEARCH("Carin",N6))),"SIM","") | Z6: =IF(AND(ISNUMBER(SEARCH("Delivery",N6)),ISNUMBER(SEARCH("Lapa",N6))),"SIM","") | AA6: =IF(AND(ISNUMBER(SEARCH("Delivery",N6)),ISNUMBER(SEARCH("Tatuapé",N6))),"SIM","") | AB6: =IF(AND(ISNUMBER(SEARCH("Delivery",N6)),ISNUMBER(SEARCH("Pavão",N6))),"SIM","") | AC6: =IF(AND(ISNUMBER(SEARCH("Delivery",N6)),ISNUMBER(SEARCH("Chac",N6))),"SIM","") | AD6: =IF(AND(ISNUMBER(SEARCH("Delivery",N6)),ISNUMBER(SEARCH("Madalena",N6))),"SIM","") | AE6: =IF(AND(ISNUMBER(SEARCH("Delivery",N6)),ISNUMBER(SEARCH("Mariana",N6))),"SIM","") | AF6: =IF(AND(ISNUMBER(SEARCH("Delivery",N6)),ISNUMBER(SEARCH("Perdizes",N6))),"SIM","") | AG6: =IF(AND(ISNUMBER(SEARCH("Delivery",N6)),ISNUMBER(SEARCH("Santana",N6))),"SIM","") | AH6: =IF(AND(ISNUMBER(SEARCH("Delivery",N6)),ISNUMBER(SEARCH("André",N6))),"SIM","") | AI6: =IF(ISNUMBER(SEARCH("Interlagos",N6)),"SIM","") | AJ6: =IF(ISNUMBER(SEARCH("Quiosque",N6)),"SIM","")
A7: Protheus | B7: 001329 | C7: =IF(B7="—","—",IFERROR(VLOOKUP(B7,_Protheus_Cadastro!$A:$B,2,FALSE),"—")) | D7: =IF(B7="—",IFERROR(INDEX(_ZIG_Cadastro!$D:$D,MATCH(H7,_ZIG_Cadastro!$A:$A,0)),"Produto"),IFERROR(VLOOKUP(B7,_Protheus_Cadastro!$A:$C,3,FALSE),"—")) | E7: =IF(B7="—","—",IFERROR(VLOOKUP(B7,_Protheus_Cadastro!$A:$D,4,FALSE),"—")) | F7: =IF(ISERROR(VLOOKUP(B7,'Estrutura Protheus'!A:A,1,FALSE)),"Não","Sim") | G7: =IFERROR(INDEX(_Protheus_Cadastro!$H:$H,MATCH(B7,_Protheus_Cadastro!$A:$A,0)),"—") | H7: =IFERROR(INDEX(_ZIG_Precos!$D:$D,MATCH(I7,_ZIG_Precos!$F:$F,0)),"—") | I7: =IFERROR(VLOOKUP(B7,_Protheus_Cadastro!$A:$I,9,FALSE),"—") | J7: =IFERROR(INDEX(_ZIG_Cadastro!$B:$B,MATCH(I7,_ZIG_Cadastro!$A:$A,0)),IFERROR(INDEX(_Entradas_ZIG!$B:$B,MATCH(I7,_Entradas_ZIG!$C:$C,0)),"—")) | K7: =IFERROR(INDEX(_ZIG_Cadastro!$C:$C,MATCH(I7,_ZIG_Cadastro!$A:$A,0)),IFERROR(INDEX(_Entradas_ZIG!$D:$D,MATCH(I7,_Entradas_ZIG!$C:$C,0)),"—")) | L7: =IF(I7="","Sem SKU ZIG",IF(I7="—","Sem SKU ZIG",IF(NOT(ISERROR(MATCH(I7,_ZIG_Cadastro!$A:$A,0))),IF(EXACT(UPPER(TRIM(C7)),UPPER(TRIM(INDEX(_ZIG_Cadastro!$B:$B,MATCH(I7,_ZIG_Cadastro!$A:$A,0))))),"OK","Atencao - Nome diverge"),IF(NOT(ISERROR(MATCH(I7,_Entradas_ZIG!$C:$C,0))),"OK","Erro - SKU nao encontrado")))) | M7: =IFERROR(INDEX(_ZIG_Cadastro!$G:$G,MATCH(I7,_ZIG_Cadastro!$A:$A,0)),IF(NOT(ISERROR(MATCH(I7,_Entradas_ZIG!$C:$C,0))),"Ativo","—")) | N7: =IFERROR(INDEX(_ZIG_Cadastro!$E:$E,MATCH(I7,_ZIG_Cadastro!$A:$A,0)),IFERROR(INDEX(_Entradas_ZIG!$F:$F,MATCH(I7,_Entradas_ZIG!$C:$C,0)),"—")) | O7: =IF(AND(ISNUMBER(SEARCH("Espeto",N7)),ISNUMBER(SEARCH("Carin",N7))),"SIM","") | P7: =IF(AND(ISNUMBER(SEARCH("Espeto",N7)),ISNUMBER(SEARCH("Lapa",N7))),"SIM","") | Q7: =IF(AND(ISNUMBER(SEARCH("Espeto",N7)),ISNUMBER(SEARCH("Tatuapé",N7))),"SIM","") | R7: =IF(AND(ISNUMBER(SEARCH("Espeto",N7)),ISNUMBER(SEARCH("Pavão",N7))),"SIM","") | S7: =IF(AND(ISNUMBER(SEARCH("Espeto",N7)),ISNUMBER(SEARCH("Chac",N7))),"SIM","") | T7: =IF(AND(ISNUMBER(SEARCH("Espeto",N7)),ISNUMBER(SEARCH("Madalena",N7))),"SIM","") | U7: =IF(AND(ISNUMBER(SEARCH("Espeto",N7)),ISNUMBER(SEARCH("Mariana",N7))),"SIM","") | V7: =IF(AND(ISNUMBER(SEARCH("Espeto",N7)),ISNUMBER(SEARCH("Perdizes",N7))),"SIM","") | W7: =IF(AND(ISNUMBER(SEARCH("Espeto",N7)),ISNUMBER(SEARCH("Santana",N7))),"SIM","") | X7: =IF(AND(ISNUMBER(SEARCH("Espeto",N7)),ISNUMBER(SEARCH("André",N7))),"SIM","") | Y7: =IF(AND(ISNUMBER(SEARCH("Delivery",N7)),ISNUMBER(SEARCH("Carin",N7))),"SIM","") | Z7: =IF(AND(ISNUMBER(SEARCH("Delivery",N7)),ISNUMBER(SEARCH("Lapa",N7))),"SIM","") | AA7: =IF(AND(ISNUMBER(SEARCH("Delivery",N7)),ISNUMBER(SEARCH("Tatuapé",N7))),"SIM","") | AB7: =IF(AND(ISNUMBER(SEARCH("Delivery",N7)),ISNUMBER(SEARCH("Pavão",N7))),"SIM","") | AC7: =IF(AND(ISNUMBER(SEARCH("Delivery",N7)),ISNUMBER(SEARCH("Chac",N7))),"SIM","") | AD7: =IF(AND(ISNUMBER(SEARCH("Delivery",N7)),ISNUMBER(SEARCH("Madalena",N7))),"SIM","") | AE7: =IF(AND(ISNUMBER(SEARCH("Delivery",N7)),ISNUMBER(SEARCH("Mariana",N7))),"SIM","") | AF7: =IF(AND(ISNUMBER(SEARCH("Delivery",N7)),ISNUMBER(SEARCH("Perdizes",N7))),"SIM","") | AG7: =IF(AND(ISNUMBER(SEARCH("Delivery",N7)),ISNUMBER(SEARCH("Santana",N7))),"SIM","") | AH7: =IF(AND(ISNUMBER(SEARCH("Delivery",N7)),ISNUMBER(SEARCH("André",N7))),"SIM","") | AI7: =IF(ISNUMBER(SEARCH("Interlagos",N7)),"SIM","") | AJ7: =IF(ISNUMBER(SEARCH("Quiosque",N7)),"SIM","")
A8: Protheus | B8: 001330 | C8: =IF(B8="—","—",IFERROR(VLOOKUP(B8,_Protheus_Cadastro!$A:$B,2,FALSE),"—")) | D8: =IF(B8="—",IFERROR(INDEX(_ZIG_Cadastro!$D:$D,MATCH(H8,_ZIG_Cadastro!$A:$A,0)),"Produto"),IFERROR(VLOOKUP(B8,_Protheus_Cadastro!$A:$C,3,FALSE),"—")) | E8: =IF(B8="—","—",IFERROR(VLOOKUP(B8,_Protheus_Cadastro!$A:$D,4,FALSE),"—")) | F8: =IF(ISERROR(VLOOKUP(B8,'Estrutura Protheus'!A:A,1,FALSE)),"Não","Sim") | G8: =IFERROR(INDEX(_Protheus_Cadastro!$H:$H,MATCH(B8,_Protheus_Cadastro!$A:$A,0)),"—") | H8: =IFERROR(INDEX(_ZIG_Precos!$D:$D,MATCH(I8,_ZIG_Precos!$F:$F,0)),"—") | I8: =IFERROR(VLOOKUP(B8,_Protheus_Cadastro!$A:$I,9,FALSE),"—") | J8: =IFERROR(INDEX(_ZIG_Cadastro!$B:$B,MATCH(I8,_ZIG_Cadastro!$A:$A,0)),IFERROR(INDEX(_Entradas_ZIG!$B:$B,MATCH(I8,_Entradas_ZIG!$C:$C,0)),"—")) | K8: =IFERROR(INDEX(_ZIG_Cadastro!$C:$C,MATCH(I8,_ZIG_Cadastro!$A:$A,0)),IFERROR(INDEX(_Entradas_ZIG!$D:$D,MATCH(I8,_Entradas_ZIG!$C:$C,0)),"—")) | L8: =IF(I8="","Sem SKU ZIG",IF(I8="—","Sem SKU ZIG",IF(NOT(ISERROR(MATCH(I8,_ZIG_Cadastro!$A:$A,0))),IF(EXACT(UPPER(TRIM(C8)),UPPER(TRIM(INDEX(_ZIG_Cadastro!$B:$B,MATCH(I8,_ZIG_Cadastro!$A:$A,0))))),"OK","Atencao - Nome diverge"),IF(NOT(ISERROR(MATCH(I8,_Entradas_ZIG!$C:$C,0))),"OK","Erro - SKU nao encontrado")))) | M8: =IFERROR(INDEX(_ZIG_Cadastro!$G:$G,MATCH(I8,_ZIG_Cadastro!$A:$A,0)),IF(NOT(ISERROR(MATCH(I8,_Entradas_ZIG!$C:$C,0))),"Ativo","—")) | N8: =IFERROR(INDEX(_ZIG_Cadastro!$E:$E,MATCH(I8,_ZIG_Cadastro!$A:$A,0)),IFERROR(INDEX(_Entradas_ZIG!$F:$F,MATCH(I8,_Entradas_ZIG!$C:$C,0)),"—")) | O8: =IF(AND(ISNUMBER(SEARCH("Espeto",N8)),ISNUMBER(SEARCH("Carin",N8))),"SIM","") | P8: =IF(AND(ISNUMBER(SEARCH("Espeto",N8)),ISNUMBER(SEARCH("Lapa",N8))),"SIM","") | Q8: =IF(AND(ISNUMBER(SEARCH("Espeto",N8)),ISNUMBER(SEARCH("Tatuapé",N8))),"SIM","") | R8: =IF(AND(ISNUMBER(SEARCH("Espeto",N8)),ISNUMBER(SEARCH("Pavão",N8))),"SIM","") | S8: =IF(AND(ISNUMBER(SEARCH("Espeto",N8)),ISNUMBER(SEARCH("Chac",N8))),"SIM","") | T8: =IF(AND(ISNUMBER(SEARCH("Espeto",N8)),ISNUMBER(SEARCH("Madalena",N8))),"SIM","") | U8: =IF(AND(ISNUMBER(SEARCH("Espeto",N8)),ISNUMBER(SEARCH("Mariana",N8))),"SIM","") | V8: =IF(AND(ISNUMBER(SEARCH("Espeto",N8)),ISNUMBER(SEARCH("Perdizes",N8))),"SIM","") | W8: =IF(AND(ISNUMBER(SEARCH("Espeto",N8)),ISNUMBER(SEARCH("Santana",N8))),"SIM","") | X8: =IF(AND(ISNUMBER(SEARCH("Espeto",N8)),ISNUMBER(SEARCH("André",N8))),"SIM","") | Y8: =IF(AND(ISNUMBER(SEARCH("Delivery",N8)),ISNUMBER(SEARCH("Carin",N8))),"SIM","") | Z8: =IF(AND(ISNUMBER(SEARCH("Delivery",N8)),ISNUMBER(SEARCH("Lapa",N8))),"SIM","") | AA8: =IF(AND(ISNUMBER(SEARCH("Delivery",N8)),ISNUMBER(SEARCH("Tatuapé",N8))),"SIM","") | AB8: =IF(AND(ISNUMBER(SEARCH("Delivery",N8)),ISNUMBER(SEARCH("Pavão",N8))),"SIM","") | AC8: =IF(AND(ISNUMBER(SEARCH("Delivery",N8)),ISNUMBER(SEARCH("Chac",N8))),"SIM","") | AD8: =IF(AND(ISNUMBER(SEARCH("Delivery",N8)),ISNUMBER(SEARCH("Madalena",N8))),"SIM","") | AE8: =IF(AND(ISNUMBER(SEARCH("Delivery",N8)),ISNUMBER(SEARCH("Mariana",N8))),"SIM","") | AF8: =IF(AND(ISNUMBER(SEARCH("Delivery",N8)),ISNUMBER(SEARCH("Perdizes",N8))),"SIM","") | AG8: =IF(AND(ISNUMBER(SEARCH("Delivery",N8)),ISNUMBER(SEARCH("Santana",N8))),"SIM","") | AH8: =IF(AND(ISNUMBER(SEARCH("Delivery",N8)),ISNUMBER(SEARCH("André",N8))),"SIM","") | AI8: =IF(ISNUMBER(SEARCH("Interlagos",N8)),"SIM","") | AJ8: =IF(ISNUMBER(SEARCH("Quiosque",N8)),"SIM","")
A9: Protheus | B9: 001260 | C9: =IF(B9="—","—",IFERROR(VLOOKUP(B9,_Protheus_Cadastro!$A:$B,2,FALSE),"—")) | D9: =IF(B9="—",IFERROR(INDEX(_ZIG_Cadastro!$D:$D,MATCH(H9,_ZIG_Cadastro!$A:$A,0)),"Produto"),IFERROR(VLOOKUP(B9,_Protheus_Cadastro!$A:$C,3,FALSE),"—")) | E9: =IF(B9="—","—",IFERROR(VLOOKUP(B9,_Protheus_Cadastro!$A:$D,4,FALSE),"—")) | F9: =IF(ISERROR(VLOOKUP(B9,'Estrutura Protheus'!A:A,1,FALSE)),"Não","Sim") | G9: =IFERROR(INDEX(_Protheus_Cadastro!$H:$H,MATCH(B9,_Protheus_Cadastro!$A:$A,0)),"—") | H9: =IFERROR(INDEX(_ZIG_Precos!$D:$D,MATCH(I9,_ZIG_Precos!$F:$F,0)),"—") | I9: =IFERROR(VLOOKUP(B9,_Protheus_Cadastro!$A:$I,9,FALSE),"—") | J9: =IFERROR(INDEX(_ZIG_Cadastro!$B:$B,MATCH(I9,_ZIG_Cadastro!$A:$A,0)),IFERROR(INDEX(_Entradas_ZIG!$B:$B,MATCH(I9,_Entradas_ZIG!$C:$C,0)),"—")) | K9: =IFERROR(INDEX(_ZIG_Cadastro!$C:$C,MATCH(I9,_ZIG_Cadastro!$A:$A,0)),IFERROR(INDEX(_Entradas_ZIG!$D:$D,MATCH(I9,_Entradas_ZIG!$C:$C,0)),"—")) | L9: =IF(I9="","Sem SKU ZIG",IF(I9="—","Sem SKU ZIG",IF(NOT(ISERROR(MATCH(I9,_ZIG_Cadastro!$A:$A,0))),IF(EXACT(UPPER(TRIM(C9)),UPPER(TRIM(INDEX(_ZIG_Cadastro!$B:$B,MATCH(I9,_ZIG_Cadastro!$A:$A,0))))),"OK","Atencao - Nome diverge"),IF(NOT(ISERROR(MATCH(I9,_Entradas_ZIG!$C:$C,0))),"OK","Erro - SKU nao encontrado")))) | M9: =IFERROR(INDEX(_ZIG_Cadastro!$G:$G,MATCH(I9,_ZIG_Cadastro!$A:$A,0)),IF(NOT(ISERROR(MATCH(I9,_Entradas_ZIG!$C:$C,0))),"Ativo","—")) | N9: =IFERROR(INDEX(_ZIG_Cadastro!$E:$E,MATCH(I9,_ZIG_Cadastro!$A:$A,0)),IFERROR(INDEX(_Entradas_ZIG!$F:$F,MATCH(I9,_Entradas_ZIG!$C:$C,0)),"—")) | O9: =IF(AND(ISNUMBER(SEARCH("Espeto",N9)),ISNUMBER(SEARCH("Carin",N9))),"SIM","") | P9: =IF(AND(ISNUMBER(SEARCH("Espeto",N9)),ISNUMBER(SEARCH("Lapa",N9))),"SIM","") | Q9: =IF(AND(ISNUMBER(SEARCH("Espeto",N9)),ISNUMBER(SEARCH("Tatuapé",N9))),"SIM","") | R9: =IF(AND(ISNUMBER(SEARCH("Espeto",N9)),ISNUMBER(SEARCH("Pavão",N9))),"SIM","") | S9: =IF(AND(ISNUMBER(SEARCH("Espeto",N9)),ISNUMBER(SEARCH("Chac",N9))),"SIM","") | T9: =IF(AND(ISNUMBER(SEARCH("Espeto",N9)),ISNUMBER(SEARCH("Madalena",N9))),"SIM","") | U9: =IF(AND(ISNUMBER(SEARCH("Espeto",N9)),ISNUMBER(SEARCH("Mariana",N9))),"SIM","") | V9: =IF(AND(ISNUMBER(SEARCH("Espeto",N9)),ISNUMBER(SEARCH("Perdizes",N9))),"SIM","") | W9: =IF(AND(ISNUMBER(SEARCH("Espeto",N9)),ISNUMBER(SEARCH("Santana",N9))),"SIM","") | X9: =IF(AND(ISNUMBER(SEARCH("Espeto",N9)),ISNUMBER(SEARCH("André",N9))),"SIM","") | Y9: =IF(AND(ISNUMBER(SEARCH("Delivery",N9)),ISNUMBER(SEARCH("Carin",N9))),"SIM","") | Z9: =IF(AND(ISNUMBER(SEARCH("Delivery",N9)),ISNUMBER(SEARCH("Lapa",N9))),"SIM","") | AA9: =IF(AND(ISNUMBER(SEARCH("Delivery",N9)),ISNUMBER(SEARCH("Tatuapé",N9))),"SIM","") | AB9: =IF(AND(ISNUMBER(SEARCH("Delivery",N9)),ISNUMBER(SEARCH("Pavão",N9))),"SIM","") | AC9: =IF(AND(ISNUMBER(SEARCH("Delivery",N9)),ISNUMBER(SEARCH("Chac",N9))),"SIM","") | AD9: =IF(AND(ISNUMBER(SEARCH("Delivery",N9)),ISNUMBER(SEARCH("Madalena",N9))),"SIM","") | AE9: =IF(AND(ISNUMBER(SEARCH("Delivery",N9)),ISNUMBER(SEARCH("Mariana",N9))),"SIM","") | AF9: =IF(AND(ISNUMBER(SEARCH("Delivery",N9)),ISNUMBER(SEARCH("Perdizes",N9))),"SIM","") | AG9: =IF(AND(ISNUMBER(SEARCH("Delivery",N9)),ISNUMBER(SEARCH("Santana",N9))),"SIM","") | AH9: =IF(AND(ISNUMBER(SEARCH("Delivery",N9)),ISNUMBER(SEARCH("André",N9))),"SIM","") | AI9: =IF(ISNUMBER(SEARCH("Interlagos",N9)),"SIM","") | AJ9: =IF(ISNUMBER(SEARCH("Quiosque",N9)),"SIM","")
A10: Protheus | B10: 001313 | C10: =IF(B10="—","—",IFERROR(VLOOKUP(B10,_Protheus_Cadastro!$A:$B,2,FALSE),"—")) | D10: =IF(B10="—",IFERROR(INDEX(_ZIG_Cadastro!$D:$D,MATCH(H10,_ZIG_Cadastro!$A:$A,0)),"Produto"),IFERROR(VLOOKUP(B10,_Protheus_Cadastro!$A:$C,3,FALSE),"—")) | E10: =IF(B10="—","—",IFERROR(VLOOKUP(B10,_Protheus_Cadastro!$A:$D,4,FALSE),"—")) | F10: =IF(ISERROR(VLOOKUP(B10,'Estrutura Protheus'!A:A,1,FALSE)),"Não","Sim") | G10: =IFERROR(INDEX(_Protheus_Cadastro!$H:$H,MATCH(B10,_Protheus_Cadastro!$A:$A,0)),"—") | H10: =IFERROR(INDEX(_ZIG_Precos!$D:$D,MATCH(I10,_ZIG_Precos!$F:$F,0)),"—") | I10: =IFERROR(VLOOKUP(B10,_Protheus_Cadastro!$A:$I,9,FALSE),"—") | J10: =IFERROR(INDEX(_ZIG_Cadastro!$B:$B,MATCH(I10,_ZIG_Cadastro!$A:$A,0)),IFERROR(INDEX(_Entradas_ZIG!$B:$B,MATCH(I10,_Entradas_ZIG!$C:$C,0)),"—")) | K10: =IFERROR(INDEX(_ZIG_Cadastro!$C:$C,MATCH(I10,_ZIG_Cadastro!$A:$A,0)),IFERROR(INDEX(_Entradas_ZIG!$D:$D,MATCH(I10,_Entradas_ZIG!$C:$C,0)),"—")) | L10: =IF(I10="","Sem SKU ZIG",IF(I10="—","Sem SKU ZIG",IF(NOT(ISERROR(MATCH(I10,_ZIG_Cadastro!$A:$A,0))),IF(EXACT(UPPER(TRIM(C10)),UPPER(TRIM(INDEX(_ZIG_Cadastro!$B:$B,MATCH(I10,_ZIG_Cadastro!$A:$A,0))))),"OK","Atencao - Nome diverge"),IF(NOT(ISERROR(MATCH(I10,_Entradas_ZIG!$C:$C,0))),"OK","Erro - SKU nao encontrado")))) | M10: =IFERROR(INDEX(_ZIG_Cadastro!$G:$G,MATCH(I10,_ZIG_Cadastro!$A:$A,0)),IF(NOT(ISERROR(MATCH(I10,_Entradas_ZIG!$C:$C,0))),"Ativo","—")) | N10: =IFERROR(INDEX(_ZIG_Cadastro!$E:$E,MATCH(I10,_ZIG_Cadastro!$A:$A,0)),IFERROR(INDEX(_Entradas_ZIG!$F:$F,MATCH(I10,_Entradas_ZIG!$C:$C,0)),"—")) | O10: =IF(AND(ISNUMBER(SEARCH("Espeto",N10)),ISNUMBER(SEARCH("Carin",N10))),"SIM","") | P10: =IF(AND(ISNUMBER(SEARCH("Espeto",N10)),ISNUMBER(SEARCH("Lapa",N10))),"SIM","") | Q10: =IF(AND(ISNUMBER(SEARCH("Espeto",N10)),ISNUMBER(SEARCH("Tatuapé",N10))),"SIM","") | R10: =IF(AND(ISNUMBER(SEARCH("Espeto",N10)),ISNUMBER(SEARCH("Pavão",N10))),"SIM","") | S10: =IF(AND(ISNUMBER(SEARCH("Espeto",N10)),ISNUMBER(SEARCH("Chac",N10))),"SIM","") | T10: =IF(AND(ISNUMBER(SEARCH("Espeto",N10)),ISNUMBER(SEARCH("Madalena",N10))),"SIM","") | U10: =IF(AND(ISNUMBER(SEARCH("Espeto",N10)),ISNUMBER(SEARCH("Mariana",N10))),"SIM","") | V10: =IF(AND(ISNUMBER(SEARCH("Espeto",N10)),ISNUMBER(SEARCH("Perdizes",N10))),"SIM","") | W10: =IF(AND(ISNUMBER(SEARCH("Espeto",N10)),ISNUMBER(SEARCH("Santana",N10))),"SIM","") | X10: =IF(AND(ISNUMBER(SEARCH("Espeto",N10)),ISNUMBER(SEARCH("André",N10))),"SIM","") | Y10: =IF(AND(ISNUMBER(SEARCH("Delivery",N10)),ISNUMBER(SEARCH("Carin",N10))),"SIM","") | Z10: =IF(AND(ISNUMBER(SEARCH("Delivery",N10)),ISNUMBER(SEARCH("Lapa",N10))),"SIM","") | AA10: =IF(AND(ISNUMBER(SEARCH("Delivery",N10)),ISNUMBER(SEARCH("Tatuapé",N10))),"SIM","") | AB10: =IF(AND(ISNUMBER(SEARCH("Delivery",N10)),ISNUMBER(SEARCH("Pavão",N10))),"SIM","") | AC10: =IF(AND(ISNUMBER(SEARCH("Delivery",N10)),ISNUMBER(SEARCH("Chac",N10))),"SIM","") | AD10: =IF(AND(ISNUMBER(SEARCH("Delivery",N10)),ISNUMBER(SEARCH("Madalena",N10))),"SIM","") | AE10: =IF(AND(ISNUMBER(SEARCH("Delivery",N10)),ISNUMBER(SEARCH("Mariana",N10))),"SIM","") | AF10: =IF(AND(ISNUMBER(SEARCH("Delivery",N10)),ISNUMBER(SEARCH("Perdizes",N10))),"SIM","") | AG10: =IF(AND(ISNUMBER(SEARCH("Delivery",N10)),ISNUMBER(SEARCH("Santana",N10))),"SIM","") | AH10: =IF(AND(ISNUMBER(SEARCH("Delivery",N10)),ISNUMBER(SEARCH("André",N10))),"SIM","") | AI10: =IF(ISNUMBER(SEARCH("Interlagos",N10)),"SIM","") | AJ10: =IF(ISNUMBER(SEARCH("Quiosque",N10)),"SIM","")
A11: Protheus | B11: 001294 | C11: =IF(B11="—","—",IFERROR(VLOOKUP(B11,_Protheus_Cadastro!$A:$B,2,FALSE),"—")) | D11: =IF(B11="—",IFERROR(INDEX(_ZIG_Cadastro!$D:$D,MATCH(H11,_ZIG_Cadastro!$A:$A,0)),"Produto"),IFERROR(VLOOKUP(B11,_Protheus_Cadastro!$A:$C,3,FALSE),"—")) | E11: =IF(B11="—","—",IFERROR(VLOOKUP(B11,_Protheus_Cadastro!$A:$D,4,FALSE),"—")) | F11: =IF(ISERROR(VLOOKUP(B11,'Estrutura Protheus'!A:A,1,FALSE)),"Não","Sim") | G11: =IFERROR(INDEX(_Protheus_Cadastro!$H:$H,MATCH(B11,_Protheus_Cadastro!$A:$A,0)),"—") | H11: =IFERROR(INDEX(_ZIG_Precos!$D:$D,MATCH(I11,_ZIG_Precos!$F:$F,0)),"—") | I11: =IFERROR(VLOOKUP(B11,_Protheus_Cadastro!$A:$I,9,FALSE),"—") | J11: =IFERROR(INDEX(_ZIG_Cadastro!$B:$B,MATCH(I11,_ZIG_Cadastro!$A:$A,0)),IFERROR(INDEX(_Entradas_ZIG!$B:$B,MATCH(I11,_Entradas_ZIG!$C:$C,0)),"—")) | K11: =IFERROR(INDEX(_ZIG_Cadastro!$C:$C,MATCH(I11,_ZIG_Cadastro!$A:$A,0)),IFERROR(INDEX(_Entradas_ZIG!$D:$D,MATCH(I11,_Entradas_ZIG!$C:$C,0)),"—")) | L11: =IF(I11="","Sem SKU ZIG",IF(I11="—","Sem SKU ZIG",IF(NOT(ISERROR(MATCH(I11,_ZIG_Cadastro!$A:$A,0))),IF(EXACT(UPPER(TRIM(C11)),UPPER(TRIM(INDEX(_ZIG_Cadastro!$B:$B,MATCH(I11,_ZIG_Cadastro!$A:$A,0))))),"OK","Atencao - Nome diverge"),IF(NOT(ISERROR(MATCH(I11,_Entradas_ZIG!$C:$C,0))),"OK","Erro - SKU nao encontrado")))) | M11: =IFERROR(INDEX(_ZIG_Cadastro!$G:$G,MATCH(I11,_ZIG_Cadastro!$A:$A,0)),IF(NOT(ISERROR(MATCH(I11,_Entradas_ZIG!$C:$C,0))),"Ativo","—")) | N11: =IFERROR(INDEX(_ZIG_Cadastro!$E:$E,MATCH(I11,_ZIG_Cadastro!$A:$A,0)),IFERROR(INDEX(_Entradas_ZIG!$F:$F,MATCH(I11,_Entradas_ZIG!$C:$C,0)),"—")) | O11: =IF(AND(ISNUMBER(SEARCH("Espeto",N11)),ISNUMBER(SEARCH("Carin",N11))),"SIM","") | P11: =IF(AND(ISNUMBER(SEARCH("Espeto",N11)),ISNUMBER(SEARCH("Lapa",N11))),"SIM","") | Q11: =IF(AND(ISNUMBER(SEARCH("Espeto",N11)),ISNUMBER(SEARCH("Tatuapé",N11))),"SIM","") | R11: =IF(AND(ISNUMBER(SEARCH("Espeto",N11)),ISNUMBER(SEARCH("Pavão",N11))),"SIM","") | S11: =IF(AND(ISNUMBER(SEARCH("Espeto",N11)),ISNUMBER(SEARCH("Chac",N11))),"SIM","") | T11: =IF(AND(ISNUMBER(SEARCH("Espeto",N11)),ISNUMBER(SEARCH("Madalena",N11))),"SIM","") | U11: =IF(AND(ISNUMBER(SEARCH("Espeto",N11)),ISNUMBER(SEARCH("Mariana",N11))),"SIM","") | V11: =IF(AND(ISNUMBER(SEARCH("Espeto",N11)),ISNUMBER(SEARCH("Perdizes",N11))),"SIM","") | W11: =IF(AND(ISNUMBER(SEARCH("Espeto",N11)),ISNUMBER(SEARCH("Santana",N11))),"SIM","") | X11: =IF(AND(ISNUMBER(SEARCH("Espeto",N11)),ISNUMBER(SEARCH("André",N11))),"SIM","") | Y11: =IF(AND(ISNUMBER(SEARCH("Delivery",N11)),ISNUMBER(SEARCH("Carin",N11))),"SIM","") | Z11: =IF(AND(ISNUMBER(SEARCH("Delivery",N11)),ISNUMBER(SEARCH("Lapa",N11))),"SIM","") | AA11: =IF(AND(ISNUMBER(SEARCH("Delivery",N11)),ISNUMBER(SEARCH("Tatuapé",N11))),"SIM","") | AB11: =IF(AND(ISNUMBER(SEARCH("Delivery",N11)),ISNUMBER(SEARCH("Pavão",N11))),"SIM","") | AC11: =IF(AND(ISNUMBER(SEARCH("Delivery",N11)),ISNUMBER(SEARCH("Chac",N11))),"SIM","") | AD11: =IF(AND(ISNUMBER(SEARCH("Delivery",N11)),ISNUMBER(SEARCH("Madalena",N11))),"SIM","") | AE11: =IF(AND(ISNUMBER(SEARCH("Delivery",N11)),ISNUMBER(SEARCH("Mariana",N11))),"SIM","") | AF11: =IF(AND(ISNUMBER(SEARCH("Delivery",N11)),ISNUMBER(SEARCH("Perdizes",N11))),"SIM","") | AG11: =IF(AND(ISNUMBER(SEARCH("Delivery",N11)),ISNUMBER(SEARCH("Santana",N11))),"SIM","") | AH11: =IF(AND(ISNUMBER(SEARCH("Delivery",N11)),ISNUMBER(SEARCH("André",N11))),"SIM","") | AI11: =IF(ISNUMBER(SEARCH("Interlagos",N11)),"SIM","") | AJ11: =IF(ISNUMBER(SEARCH("Quiosque",N11)),"SIM","")
A12: Protheus | B12: 001263 | C12: =IF(B12="—","—",IFERROR(VLOOKUP(B12,_Protheus_Cadastro!$A:$B,2,FALSE),"—")) | D12: =IF(B12="—",IFERROR(INDEX(_ZIG_Cadastro!$D:$D,MATCH(H12,_ZIG_Cadastro!$A:$A,0)),"Produto"),IFERROR(VLOOKUP(B12,_Protheus_Cadastro!$A:$C,3,FALSE),"—")) | E12: =IF(B12="—","—",IFERROR(VLOOKUP(B12,_Protheus_Cadastro!$A:$D,4,FALSE),"—")) | F12: =IF(ISERROR(VLOOKUP(B12,'Estrutura Protheus'!A:A,1,FALSE)),"Não","Sim") | G12: =IFERROR(INDEX(_Protheus_Cadastro!$H:$H,MATCH(B12,_Protheus_Cadastro!$A:$A,0)),"—") | H12: =IFERROR(INDEX(_ZIG_Precos!$D:$D,MATCH(I12,_ZIG_Precos!$F:$F,0)),"—") | I12: =IFERROR(VLOOKUP(B12,_Protheus_Cadastro!$A:$I,9,FALSE),"—") | J12: =IFERROR(INDEX(_ZIG_Cadastro!$B:$B,MATCH(I12,_ZIG_Cadastro!$A:$A,0)),IFERROR(INDEX(_Entradas_ZIG!$B:$B,MATCH(I12,_Entradas_ZIG!$C:$C,0)),"—")) | K12: =IFERROR(INDEX(_ZIG_Cadastro!$C:$C,MATCH(I12,_ZIG_Cadastro!$A:$A,0)),IFERROR(INDEX(_Entradas_ZIG!$D:$D,MATCH(I12,_Entradas_ZIG!$C:$C,0)),"—")) | L12: =IF(I12="","Sem SKU ZIG",IF(I12="—","Sem SKU ZIG",IF(NOT(ISERROR(MATCH(I12,_ZIG_Cadastro!$A:$A,0))),IF(EXACT(UPPER(TRIM(C12)),UPPER(TRIM(INDEX(_ZIG_Cadastro!$B:$B,MATCH(I12,_ZIG_Cadastro!$A:$A,0))))),"OK","Atencao - Nome diverge"),IF(NOT(ISERROR(MATCH(I12,_Entradas_ZIG!$C:$C,0))),"OK","Erro - SKU nao encontrado")))) | M12: =IFERROR(INDEX(_ZIG_Cadastro!$G:$G,MATCH(I12,_ZIG_Cadastro!$A:$A,0)),IF(NOT(ISERROR(MATCH(I12,_Entradas_ZIG!$C:$C,0))),"Ativo","—")) | N12: =IFERROR(INDEX(_ZIG_Cadastro!$E:$E,MATCH(I12,_ZIG_Cadastro!$A:$A,0)),IFERROR(INDEX(_Entradas_ZIG!$F:$F,MATCH(I12,_Entradas_ZIG!$C:$C,0)),"—")) | O12: =IF(AND(ISNUMBER(SEARCH("Espeto",N12)),ISNUMBER(SEARCH("Carin",N12))),"SIM","") | P12: =IF(AND(ISNUMBER(SEARCH("Espeto",N12)),ISNUMBER(SEARCH("Lapa",N12))),"SIM","") | Q12: =IF(AND(ISNUMBER(SEARCH("Espeto",N12)),ISNUMBER(SEARCH("Tatuapé",N12))),"SIM","") | R12: =IF(AND(ISNUMBER(SEARCH("Espeto",N12)),ISNUMBER(SEARCH("Pavão",N12))),"SIM","") | S12: =IF(AND(ISNUMBER(SEARCH("Espeto",N12)),ISNUMBER(SEARCH("Chac",N12))),"SIM","") | T12: =IF(AND(ISNUMBER(SEARCH("Espeto",N12)),ISNUMBER(SEARCH("Madalena",N12))),"SIM","") | U12: =IF(AND(ISNUMBER(SEARCH("Espeto",N12)),ISNUMBER(SEARCH("Mariana",N12))),"SIM","") | V12: =IF(AND(ISNUMBER(SEARCH("Espeto",N12)),ISNUMBER(SEARCH("Perdizes",N12))),"SIM","") | W12: =IF(AND(ISNUMBER(SEARCH("Espeto",N12)),ISNUMBER(SEARCH("Santana",N12))),"SIM","") | X12: =IF(AND(ISNUMBER(SEARCH("Espeto",N12)),ISNUMBER(SEARCH("André",N12))),"SIM","") | Y12: =IF(AND(ISNUMBER(SEARCH("Delivery",N12)),ISNUMBER(SEARCH("Carin",N12))),"SIM","") | Z12: =IF(AND(ISNUMBER(SEARCH("Delivery",N12)),ISNUMBER(SEARCH("Lapa",N12))),"SIM","") | AA12: =IF(AND(ISNUMBER(SEARCH("Delivery",N12)),ISNUMBER(SEARCH("Tatuapé",N12))),"SIM","") | AB12: =IF(AND(ISNUMBER(SEARCH("Delivery",N12)),ISNUMBER(SEARCH("Pavão",N12))),"SIM","") | AC12: =IF(AND(ISNUMBER(SEARCH("Delivery",N12)),ISNUMBER(SEARCH("Chac",N12))),"SIM","") | AD12: =IF(AND(ISNUMBER(SEARCH("Delivery",N12)),ISNUMBER(SEARCH("Madalena",N12))),"SIM","") | AE12: =IF(AND(ISNUMBER(SEARCH("Delivery",N12)),ISNUMBER(SEARCH("Mariana",N12))),"SIM","") | AF12: =IF(AND(ISNUMBER(SEARCH("Delivery",N12)),ISNUMBER(SEARCH("Perdizes",N12))),"SIM","") | AG12: =IF(AND(ISNUMBER(SEARCH("Delivery",N12)),ISNUMBER(SEARCH("Santana",N12))),"SIM","") | AH12: =IF(AND(ISNUMBER(SEARCH("Delivery",N12)),ISNUMBER(SEARCH("André",N12))),"SIM","") | AI12: =IF(ISNUMBER(SEARCH("Interlagos",N12)),"SIM","") | AJ12: =IF(ISNUMBER(SEARCH("Quiosque",N12)),"SIM","")
A13: Protheus | B13: 001331 | C13: =IF(B13="—","—",IFERROR(VLOOKUP(B13,_Protheus_Cadastro!$A:$B,2,FALSE),"—")) | D13: =IF(B13="—",IFERROR(INDEX(_ZIG_Cadastro!$D:$D,MATCH(H13,_ZIG_Cadastro!$A:$A,0)),"Produto"),IFERROR(VLOOKUP(B13,_Protheus_Cadastro!$A:$C,3,FALSE),"—")) | E13: =IF(B13="—","—",IFERROR(VLOOKUP(B13,_Protheus_Cadastro!$A:$D,4,FALSE),"—")) | F13: =IF(ISERROR(VLOOKUP(B13,'Estrutura Protheus'!A:A,1,FALSE)),"Não","Sim") | G13: =IFERROR(INDEX(_Protheus_Cadastro!$H:$H,MATCH(B13,_Protheus_Cadastro!$A:$A,0)),"—") | H13: =IFERROR(INDEX(_ZIG_Precos!$D:$D,MATCH(I13,_ZIG_Precos!$F:$F,0)),"—") | I13: =IFERROR(VLOOKUP(B13,_Protheus_Cadastro!$A:$I,9,FALSE),"—") | J13: =IFERROR(INDEX(_ZIG_Cadastro!$B:$B,MATCH(I13,_ZIG_Cadastro!$A:$A,0)),IFERROR(INDEX(_Entradas_ZIG!$B:$B,MATCH(I13,_Entradas_ZIG!$C:$C,0)),"—")) | K13: =IFERROR(INDEX(_ZIG_Cadastro!$C:$C,MATCH(I13,_ZIG_Cadastro!$A:$A,0)),IFERROR(INDEX(_Entradas_ZIG!$D:$D,MATCH(I13,_Entradas_ZIG!$C:$C,0)),"—")) | L13: =IF(I13="","Sem SKU ZIG",IF(I13="—","Sem SKU ZIG",IF(NOT(ISERROR(MATCH(I13,_ZIG_Cadastro!$A:$A,0))),IF(EXACT(UPPER(TRIM(C13)),UPPER(TRIM(INDEX(_ZIG_Cadastro!$B:$B,MATCH(I13,_ZIG_Cadastro!$A:$A,0))))),"OK","Atencao - Nome diverge"),IF(NOT(ISERROR(MATCH(I13,_Entradas_ZIG!$C:$C,0))),"OK","Erro - SKU nao encontrado")))) | M13: =IFERROR(INDEX(_ZIG_Cadastro!$G:$G,MATCH(I13,_ZIG_Cadastro!$A:$A,0)),IF(NOT(ISERROR(MATCH(I13,_Entradas_ZIG!$C:$C,0))),"Ativo","—")) | N13: =IFERROR(INDEX(_ZIG_Cadastro!$E:$E,MATCH(I13,_ZIG_Cadastro!$A:$A,0)),IFERROR(INDEX(_Entradas_ZIG!$F:$F,MATCH(I13,_Entradas_ZIG!$C:$C,0)),"—")) | O13: =IF(AND(ISNUMBER(SEARCH("Espeto",N13)),ISNUMBER(SEARCH("Carin",N13))),"SIM","") | P13: =IF(AND(ISNUMBER(SEARCH("Espeto",N13)),ISNUMBER(SEARCH("Lapa",N13))),"SIM","") | Q13: =IF(AND(ISNUMBER(SEARCH("Espeto",N13)),ISNUMBER(SEARCH("Tatuapé",N13))),"SIM","") | R13: =IF(AND(ISNUMBER(SEARCH("Espeto",N13)),ISNUMBER(SEARCH("Pavão",N13))),"SIM","") | S13: =IF(AND(ISNUMBER(SEARCH("Espeto",N13)),ISNUMBER(SEARCH("Chac",N13))),"SIM","") | T13: =IF(AND(ISNUMBER(SEARCH("Espeto",N13)),ISNUMBER(SEARCH("Madalena",N13))),"SIM","") | U13: =IF(AND(ISNUMBER(SEARCH("Espeto",N13)),ISNUMBER(SEARCH("Mariana",N13))),"SIM","") | V13: =IF(AND(ISNUMBER(SEARCH("Espeto",N13)),ISNUMBER(SEARCH("Perdizes",N13))),"SIM","") | W13: =IF(AND(ISNUMBER(SEARCH("Espeto",N13)),ISNUMBER(SEARCH("Santana",N13))),"SIM","") | X13: =IF(AND(ISNUMBER(SEARCH("Espeto",N13)),ISNUMBER(SEARCH("André",N13))),"SIM","") | Y13: =IF(AND(ISNUMBER(SEARCH("Delivery",N13)),ISNUMBER(SEARCH("Carin",N13))),"SIM","") | Z13: =IF(AND(ISNUMBER(SEARCH("Delivery",N13)),ISNUMBER(SEARCH("Lapa",N13))),"SIM","") | AA13: =IF(AND(ISNUMBER(SEARCH("Delivery",N13)),ISNUMBER(SEARCH("Tatuapé",N13))),"SIM","") | AB13: =IF(AND(ISNUMBER(SEARCH("Delivery",N13)),ISNUMBER(SEARCH("Pavão",N13))),"SIM","") | AC13: =IF(AND(ISNUMBER(SEARCH("Delivery",N13)),ISNUMBER(SEARCH("Chac",N13))),"SIM","") | AD13: =IF(AND(ISNUMBER(SEARCH("Delivery",N13)),ISNUMBER(SEARCH("Madalena",N13))),"SIM","") | AE13: =IF(AND(ISNUMBER(SEARCH("Delivery",N13)),ISNUMBER(SEARCH("Mariana",N13))),"SIM","") | AF13: =IF(AND(ISNUMBER(SEARCH("Delivery",N13)),ISNUMBER(SEARCH("Perdizes",N13))),"SIM","") | AG13: =IF(AND(ISNUMBER(SEARCH("Delivery",N13)),ISNUMBER(SEARCH("Santana",N13))),"SIM","") | AH13: =IF(AND(ISNUMBER(SEARCH("Delivery",N13)),ISNUMBER(SEARCH("André",N13))),"SIM","") | AI13: =IF(ISNUMBER(SEARCH("Interlagos",N13)),"SIM","") | AJ13: =IF(ISNUMBER(SEARCH("Quiosque",N13)),"SIM","")
A14: Protheus | B14: 001396 | C14: =IF(B14="—","—",IFERROR(VLOOKUP(B14,_Protheus_Cadastro!$A:$B,2,FALSE),"—")) | D14: =IF(B14="—",IFERROR(INDEX(_ZIG_Cadastro!$D:$D,MATCH(H14,_ZIG_Cadastro!$A:$A,0)),"Produto"),IFERROR(VLOOKUP(B14,_Protheus_Cadastro!$A:$C,3,FALSE),"—")) | E14: =IF(B14="—","—",IFERROR(VLOOKUP(B14,_Protheus_Cadastro!$A:$D,4,FALSE),"—")) | F14: =IF(ISERROR(VLOOKUP(B14,'Estrutura Protheus'!A:A,1,FALSE)),"Não","Sim") | G14: =IFERROR(INDEX(_Protheus_Cadastro!$H:$H,MATCH(B14,_Protheus_Cadastro!$A:$A,0)),"—") | H14: =IFERROR(INDEX(_ZIG_Precos!$D:$D,MATCH(I14,_ZIG_Precos!$F:$F,0)),"—") | I14: =IFERROR(VLOOKUP(B14,_Protheus_Cadastro!$A:$I,9,FALSE),"—") | J14: =IFERROR(INDEX(_ZIG_Cadastro!$B:$B,MATCH(I14,_ZIG_Cadastro!$A:$A,0)),IFERROR(INDEX(_Entradas_ZIG!$B:$B,MATCH(I14,_Entradas_ZIG!$C:$C,0)),"—")) | K14: =IFERROR(INDEX(_ZIG_Cadastro!$C:$C,MATCH(I14,_ZIG_Cadastro!$A:$A,0)),IFERROR(INDEX(_Entradas_ZIG!$D:$D,MATCH(I14,_Entradas_ZIG!$C:$C,0)),"—")) | L14: =IF(I14="","Sem SKU ZIG",IF(I14="—","Sem SKU ZIG",IF(NOT(ISERROR(MATCH(I14,_ZIG_Cadastro!$A:$A,0))),IF(EXACT(UPPER(TRIM(C14)),UPPER(TRIM(INDEX(_ZIG_Cadastro!$B:$B,MATCH(I14,_ZIG_Cadastro!$A:$A,0))))),"OK","Atencao - Nome diverge"),IF(NOT(ISERROR(MATCH(I14,_Entradas_ZIG!$C:$C,0))),"OK","Erro - SKU nao encontrado")))) | M14: =IFERROR(INDEX(_ZIG_Cadastro!$G:$G,MATCH(I14,_ZIG_Cadastro!$A:$A,0)),IF(NOT(ISERROR(MATCH(I14,_Entradas_ZIG!$C:$C,0))),"Ativo","—")) | N14: =IFERROR(INDEX(_ZIG_Cadastro!$E:$E,MATCH(I14,_ZIG_Cadastro!$A:$A,0)),IFERROR(INDEX(_Entradas_ZIG!$F:$F,MATCH(I14,_Entradas_ZIG!$C:$C,0)),"—")) | O14: =IF(AND(ISNUMBER(SEARCH("Espeto",N14)),ISNUMBER(SEARCH("Carin",N14))),"SIM","") | P14: =IF(AND(ISNUMBER(SEARCH("Espeto",N14)),ISNUMBER(SEARCH("Lapa",N14))),"SIM","") | Q14: =IF(AND(ISNUMBER(SEARCH("Espeto",N14)),ISNUMBER(SEARCH("Tatuapé",N14))),"SIM","") | R14: =IF(AND(ISNUMBER(SEARCH("Espeto",N14)),ISNUMBER(SEARCH("Pavão",N14))),"SIM","") | S14: =IF(AND(ISNUMBER(SEARCH("Espeto",N14)),ISNUMBER(SEARCH("Chac",N14))),"SIM","") | T14: =IF(AND(ISNUMBER(SEARCH("Espeto",N14)),ISNUMBER(SEARCH("Madalena",N14))),"SIM","") | U14: =IF(AND(ISNUMBER(SEARCH("Espeto",N14)),ISNUMBER(SEARCH("Mariana",N14))),"SIM","") | V14: =IF(AND(ISNUMBER(SEARCH("Espeto",N14)),ISNUMBER(SEARCH("Perdizes",N14))),"SIM","") | W14: =IF(AND(ISNUMBER(SEARCH("Espeto",N14)),ISNUMBER(SEARCH("Santana",N14))),"SIM","") | X14: =IF(AND(ISNUMBER(SEARCH("Espeto",N14)),ISNUMBER(SEARCH("André",N14))),"SIM","") | Y14: =IF(AND(ISNUMBER(SEARCH("Delivery",N14)),ISNUMBER(SEARCH("Carin",N14))),"SIM","") | Z14: =IF(AND(ISNUMBER(SEARCH("Delivery",N14)),ISNUMBER(SEARCH("Lapa",N14))),"SIM","") | AA14: =IF(AND(ISNUMBER(SEARCH("Delivery",N14)),ISNUMBER(SEARCH("Tatuapé",N14))),"SIM","") | AB14: =IF(AND(ISNUMBER(SEARCH("Delivery",N14)),ISNUMBER(SEARCH("Pavão",N14))),"SIM","") | AC14: =IF(AND(ISNUMBER(SEARCH("Delivery",N14)),ISNUMBER(SEARCH("Chac",N14))),"SIM","") | AD14: =IF(AND(ISNUMBER(SEARCH("Delivery",N14)),ISNUMBER(SEARCH("Madalena",N14))),"SIM","") | AE14: =IF(AND(ISNUMBER(SEARCH("Delivery",N14)),ISNUMBER(SEARCH("Mariana",N14))),"SIM","") | AF14: =IF(AND(ISNUMBER(SEARCH("Delivery",N14)),ISNUMBER(SEARCH("Perdizes",N14))),"SIM","") | AG14: =IF(AND(ISNUMBER(SEARCH("Delivery",N14)),ISNUMBER(SEARCH("Santana",N14))),"SIM","") | AH14: =IF(AND(ISNUMBER(SEARCH("Delivery",N14)),ISNUMBER(SEARCH("André",N14))),"SIM","") | AI14: =IF(ISNUMBER(SEARCH("Interlagos",N14)),"SIM","") | AJ14: =IF(ISNUMBER(SEARCH("Quiosque",N14)),"SIM","")
... A793: Protheus | B793: 99999 | C793: =IF(B793="—","—",IFERROR(VLOOKUP(B793,_Protheus_Cadastro!$A:$B,2,FALSE),"—")) | D793: =IF(B793="—",IFERROR(INDEX(_ZIG_Cadastro!$D:$D,MATCH(H793,_ZIG_Cadastro!$A:$A,0)),"Produto"),IFERROR(VLOOKUP(B793,_Protheus_Cadastro!$A:$C,3,FALSE),"—")) | E793: =IF(B793="—","—",IFERROR(VLOOKUP(B793,_Protheus_Cadastro!$A:$D,4,FALSE),"—")) | F793: =IF(ISERROR(VLOOKUP(B793,'Estrutura Protheus'!A:A,1,FALSE)),"Não","Sim") | G793: =IFERROR(INDEX(_Protheus_Cadastro!$H:$H,MATCH(B793,_Protheus_Cadastro!$A:$A,0)),"—") | H793: =IFERROR(INDEX(_ZIG_Precos!$D:$D,MATCH(I793,_ZIG_Precos!$F:$F,0)),"—") | I793: =IFERROR(VLOOKUP(B793,_Protheus_Cadastro!$A:$I,9,FALSE),"—") | J793: =IFERROR(INDEX(_ZIG_Cadastro!$B:$B,MATCH(I793,_ZIG_Cadastro!$A:$A,0)),IFERROR(INDEX(_Entradas_ZIG!$B:$B,MATCH(I793,_Entradas_ZIG!$C:$C,0)),"—")) | K793: =IFERROR(INDEX(_ZIG_Cadastro!$C:$C,MATCH(I793,_ZIG_Cadastro!$A:$A,0)),IFERROR(INDEX(_Entradas_ZIG!$D:$D,MATCH(I793,_Entradas_ZIG!$C:$C,0)),"—")) | L793: =IF(I793="","Sem SKU ZIG",IF(I793="—","Sem SKU ZIG",IF(NOT(ISERROR(MATCH(I793,_ZIG_Cadastro!$A:$A,0))),IF(EXACT(UPPER(TRIM(C793)),UPPER(TRIM(INDEX(_ZIG_Cadastro!$B:$B,MATCH(I793,_ZIG_Cadastro!$A:$A,0))))),"OK","Atencao - Nome diverge"),IF(NOT(ISERROR(MATCH(I793,_Entradas_ZIG!$C:$C,0))),"OK","Erro - SKU nao encontrado")))) | M793: =IFERROR(INDEX(_ZIG_Cadastro!$G:$G,MATCH(I793,_ZIG_Cadastro!$A:$A,0)),IF(NOT(ISERROR(MATCH(I793,_Entradas_ZIG!$C:$C,0))),"Ativo","—")) | N793: =IFERROR(INDEX(_ZIG_Cadastro!$E:$E,MATCH(I793,_ZIG_Cadastro!$A:$A,0)),IFERROR(INDEX(_Entradas_ZIG!$F:$F,MATCH(I793,_Entradas_ZIG!$C:$C,0)),"—")) | O793: =IF(AND(ISNUMBER(SEARCH("Espeto",N793)),ISNUMBER(SEARCH("Carin",N793))),"SIM","") | P793: =IF(AND(ISNUMBER(SEARCH("Espeto",N793)),ISNUMBER(SEARCH("Lapa",N793))),"SIM","") | Q793: =IF(AND(ISNUMBER(SEARCH("Espeto",N793)),ISNUMBER(SEARCH("Tatuapé",N793))),"SIM","") | R793: =IF(AND(ISNUMBER(SEARCH("Espeto",N793)),ISNUMBER(SEARCH("Pavão",N793))),"SIM","") | S793: =IF(AND(ISNUMBER(SEARCH("Espeto",N793)),ISNUMBER(SEARCH("Chac",N793))),"SIM","") | T793: =IF(AND(ISNUMBER(SEARCH("Espeto",N793)),ISNUMBER(SEARCH("Madalena",N793))),"SIM","") | U793: =IF(AND(ISNUMBER(SEARCH("Espeto",N793)),ISNUMBER(SEARCH("Mariana",N793))),"SIM","") | V793: =IF(AND(ISNUMBER(SEARCH("Espeto",N793)),ISNUMBER(SEARCH("Perdizes",N793))),"SIM","") | W793: =IF(AND(ISNUMBER(SEARCH("Espeto",N793)),ISNUMBER(SEARCH("Santana",N793))),"SIM","") | X793: =IF(AND(ISNUMBER(SEARCH("Espeto",N793)),ISNUMBER(SEARCH("André",N793))),"SIM","") | Y793: =IF(AND(ISNUMBER(SEARCH("Delivery",N793)),ISNUMBER(SEARCH("Carin",N793))),"SIM","") | Z793: =IF(AND(ISNUMBER(SEARCH("Delivery",N793)),ISNUMBER(SEARCH("Lapa",N793))),"SIM","") | AA793: =IF(AND(ISNUMBER(SEARCH("Delivery",N793)),ISNUMBER(SEARCH("Tatuapé",N793))),"SIM","") | AB793: =IF(AND(ISNUMBER(SEARCH("Delivery",N793)),ISNUMBER(SEARCH("Pavão",N793))),"SIM","") | AC793: =IF(AND(ISNUMBER(SEARCH("Delivery",N793)),ISNUMBER(SEARCH("Chac",N793))),"SIM","") | AD793: =IF(AND(ISNUMBER(SEARCH("Delivery",N793)),ISNUMBER(SEARCH("Madalena",N793))),"SIM","") | AE793: =IF(AND(ISNUMBER(SEARCH("Delivery",N793)),ISNUMBER(SEARCH("Mariana",N793))),"SIM","") | AF793: =IF(AND(ISNUMBER(SEARCH("Delivery",N793)),ISNUMBER(SEARCH("Perdizes",N793))),"SIM","") | AG793: =IF(AND(ISNUMBER(SEARCH("Delivery",N793)),ISNUMBER(SEARCH("Santana",N793))),"SIM","") | AH793: =IF(AND(ISNUMBER(SEARCH("Delivery",N793)),ISNUMBER(SEARCH("André",N793))),"SIM","") | AI793: =IF(ISNUMBER(SEARCH("Interlagos",N793)),"SIM","") | AJ793: =IF(ISNUMBER(SEARCH("Quiosque",N793)),"SIM","")

Sheet _ZIG_Cadastro
A1: SKU (Código ZIG) | B1: Nome | C1: Categoria | D1: Tipo | E1: Locais | F1: ID Sistema | G1: Situação | H1: Última Atualização: 13/05/2026
A2: 7898905687807 | B2: EXPRESSO AMENO | C2: A CAFE | D2: Produto | E2: Quintal do Espeto Lapa , Quintal do Espeto Santo André, Quintal do Espeto Chac Sto Antonio, Quintal do Espeto Santana, Quintal do Espeto V. Mariana, Quintal do Espeto Perdizes, Quintal do Espeto Tatuapé, Quintal do Espeto V. Madalena, Quintal do Espeto Carinás, Quintal do Espeto Pavão | F2: 783165d5-261b-45b1-bf32-e093cbc855c1 | G2: =IF(E2="","Inativo",IF(SUMPRODUCT(--(ISNUMBER(SEARCH({"Lapa","Santana","Mariana","Perdizes","André","Tatuapé","Madalena","Carinás","Pavão","Chac"},E2))))>0,"Ativo","Inativo"))
A3: 7898905687808 | B3: EXPRESSO VIBRANTE | C3: A CAFE | D3: Produto | E3: Quintal do Espeto Lapa , Quintal do Espeto Santo André, Quintal do Espeto Chac Sto Antonio, Quintal do Espeto Santana, Quintal do Espeto V. Mariana, Quintal do Espeto Perdizes, Quintal do Espeto Tatuapé, Quintal do Espeto V. Madalena, Quintal do Espeto Carinás, Quintal do Espeto Pavão | F3: 1fa87ca7-b4a7-4a7d-9bca-819c542d3097 | G3: =IF(E3="","Inativo",IF(SUMPRODUCT(--(ISNUMBER(SEARCH({"Lapa","Santana","Mariana","Perdizes","André","Tatuapé","Madalena","Carinás","Pavão","Chac"},E3))))>0,"Ativo","Inativo"))
A4: 7898905687809 | B4: EXPRESSO DECAF | C4: A CAFE | D4: Produto | E4: Quintal do Espeto Lapa , Quintal do Espeto Santo André, Quintal do Espeto Chac Sto Antonio, Quintal do Espeto Santana, Quintal do Espeto V. Mariana, Quintal do Espeto Perdizes, Quintal do Espeto Tatuapé, Quintal do Espeto V. Madalena, Quintal do Espeto Carinás, Quintal do Espeto Pavão | F4: 364182ae-2e91-47b4-aba2-40949b93cf6f | G4: =IF(E4="","Inativo",IF(SUMPRODUCT(--(ISNUMBER(SEARCH({"Lapa","Santana","Mariana","Perdizes","André","Tatuapé","Madalena","Carinás","Pavão","Chac"},E4))))>0,"Ativo","Inativo"))
A5: 78989056877256 | B5: Double chopp | C5: A CHOPP BRAHMA | D5: Produto | E5: Quintal do Espeto Santana, Quintal do Espeto Perdizes, Quintal do Espeto V. Madalena, Quintal do Espeto Carinás, Quintal do Espeto Pavão | F5: afafc3f0-4a36-4203-a19b-649a288b4b04 | G5: =IF(E5="","Inativo",IF(SUMPRODUCT(--(ISNUMBER(SEARCH({"Lapa","Santana","Mariana","Perdizes","André","Tatuapé","Madalena","Carinás","Pavão","Chac"},E5))))>0,"Ativo","Inativo"))
A6: 78989056877292 | B6: CHOPP OKTOBERFEST 500 ML | C6: A CHOPP BRAHMA | D6: Produto | F6: fb1d0df2-9ee7-4196-be49-13e3e60d27b9 | G6: =IF(E6="","Inativo",IF(SUMPRODUCT(--(ISNUMBER(SEARCH({"Lapa","Santana","Mariana","Perdizes","André","Tatuapé","Madalena","Carinás","Pavão","Chac"},E6))))>0,"Ativo","Inativo"))
A7: 80101 | B7: CHOPP BRAHMA CANECA | C7: A CHOPP BRAHMA | D7: Produto | E7: Quintal do Espeto Lapa , Quintal do Espeto Santo André, Quintal do Espeto Chac Sto Antonio, Quintal do Espeto Santana, Quintal do Espeto V. Mariana, Quintal do Espeto Perdizes, Quintal do Espeto Tatuapé, Quintal do Espeto V. Madalena, Quintal do Espeto Carinás, Quintal do Espeto Pavão, Quintal do Espeto Interlagos, Quintal do Espeto Recargas/Bônus | F7: 0e0cb7d1-6896-4a6f-ad2e-8b868426e8b9 | G7: =IF(E7="","Inativo",IF(SUMPRODUCT(--(ISNUMBER(SEARCH({"Lapa","Santana","Mariana","Perdizes","André","Tatuapé","Madalena","Carinás","Pavão","Chac"},E7))))>0,"Ativo","Inativo"))
A8: 0001 | B8: COMBO RED BULL MELAO | C8: A BEBIDAS NÃO ALCOÓLICAS | D8: Produto | E8: Quintal do Espeto Santana | F8: 6ec8c48e-a998-4449-ba77-e0ef68287b4f | G8: =IF(E8="","Inativo",IF(SUMPRODUCT(--(ISNUMBER(SEARCH({"Lapa","Santana","Mariana","Perdizes","André","Tatuapé","Madalena","Carinás","Pavão","Chac"},E8))))>0,"Ativo","Inativo"))
A9: 71001 | B9: AGUA S/ GAS | C9: A BEBIDAS NÃO ALCOÓLICAS | D9: Produto | E9: Quintal do Espeto Lapa , Quintal do Espeto Santo André, Quintal do Espeto Chac Sto Antonio, Quintal do Espeto Santana, Quintal do Espeto V. Mariana, Quintal do Espeto Perdizes, Quintal do Espeto Tatuapé, Quintal do Espeto V. Madalena, Quintal do Espeto Carinás, Quintal do Espeto Pavão, Quintal do Espeto Interlagos, Quintal do Espeto Recargas/Bônus | F9: 34bc7e25-9a58-411a-b15b-ba9ba1eda1da | G9: =IF(E9="","Inativo",IF(SUMPRODUCT(--(ISNUMBER(SEARCH({"Lapa","Santana","Mariana","Perdizes","André","Tatuapé","Madalena","Carinás","Pavão","Chac"},E9))))>0,"Ativo","Inativo"))
A10: 71002 | B10: AGUA TONICA | C10: A BEBIDAS NÃO ALCOÓLICAS | D10: Produto | E10: Quintal do Espeto Lapa , Quintal do Espeto Santo André, Quintal do Espeto Chac Sto Antonio, Quintal do Espeto Santana, Quintal do Espeto V. Mariana, Quintal do Espeto Perdizes, Quintal do Espeto Tatuapé, Quintal do Espeto V. Madalena, Quintal do Espeto Carinás, Quintal do Espeto Pavão, Quintal do Espeto Interlagos, Quintal do Espeto Recargas/Bônus | F10: 6b153949-4f1c-4297-acff-73e2c1cd609e | G10: =IF(E10="","Inativo",IF(SUMPRODUCT(--(ISNUMBER(SEARCH({"Lapa","Santana","Mariana","Perdizes","André","Tatuapé","Madalena","Carinás","Pavão","Chac"},E10))))>0,"Ativo","Inativo"))
A11: 71003 | B11: PEPSI | C11: A BEBIDAS NÃO ALCOÓLICAS | D11: Produto | E11: Delivery Interlagos, Quintal do Espeto Lapa , Quintal do Espeto Santo André, Quintal do Espeto Chac Sto Antonio, Delivery Lapa, Delivery Carinás, Delivery Vila Madalena, Delivery Tatuapé, Delivery Chac. Sto Antonio, Quintal do Espeto Santana, Quintal do Espeto V. Mariana, Delivery Santo André, Delivery Pavão, Delivery V. Mariana, Delivery Perdizes, Quintal do Espeto Perdizes, Delivery Santana, Quintal do Espeto Tatuapé, Quintal do Espeto V. Madalena, Quintal do Espeto Carinás, Quintal do Espeto Pavão, Quintal do Espeto Interlagos, Quintal do Espeto Recargas/Bônus | F11: dc1914d4-06d2-46b5-95e0-bd3871c65227 | G11: =IF(E11="","Inativo",IF(SUMPRODUCT(--(ISNUMBER(SEARCH({"Lapa","Santana","Mariana","Perdizes","André","Tatuapé","Madalena","Carinás","Pavão","Chac"},E11))))>0,"Ativo","Inativo"))
A12: 71004 | B12: SUKITA | C12: A BEBIDAS NÃO ALCOÓLICAS | D12: Produto | E12: Quintal do Espeto Lapa , Quintal do Espeto Santo André, Quintal do Espeto Chac Sto Antonio, Quintal do Espeto Santana, Quintal do Espeto V. Mariana, Quintal do Espeto Perdizes, Quintal do Espeto Tatuapé, Quintal do Espeto V. Madalena, Quintal do Espeto Carinás, Quintal do Espeto Pavão, Quintal do Espeto Interlagos, Quintal do Espeto Recargas/Bônus | F12: 9c0c357b-a6e8-4794-8b8d-aefa5c524016 | G12: =IF(E12="","Inativo",IF(SUMPRODUCT(--(ISNUMBER(SEARCH({"Lapa","Santana","Mariana","Perdizes","André","Tatuapé","Madalena","Carinás","Pavão","Chac"},E12))))>0,"Ativo","Inativo"))
A13: 71005 | B13: GUARANA | C13: A BEBIDAS NÃO ALCOÓLICAS | D13: Produto | E13: Delivery Interlagos, Quintal do Espeto Lapa , Quintal do Espeto Santo André, Quintal do Espeto Chac Sto Antonio, Delivery Lapa, Delivery Carinás, Delivery Vila Madalena, Delivery Tatuapé, Delivery Chac. Sto Antonio, Quintal do Espeto Santana, Quintal do Espeto V. Mariana, Delivery Santo André, Delivery Pavão, Delivery V. Mariana, Delivery Perdizes, Quintal do Espeto Perdizes, Delivery Santana, Quintal do Espeto Tatuapé, Quintal do Espeto V. Madalena, Quintal do Espeto Carinás, Quintal do Espeto Pavão, Quintal do Espeto Interlagos, Quintal do Espeto Recargas/Bônus | F13: 0da698a1-b944-4667-92a5-5902a5a5043b | G13: =IF(E13="","Inativo",IF(SUMPRODUCT(--(ISNUMBER(SEARCH({"Lapa","Santana","Mariana","Perdizes","André","Tatuapé","Madalena","Carinás","Pavão","Chac"},E13))))>0,"Ativo","Inativo"))
A14: 71006 | B14: SODA LIMONADA | C14: A BEBIDAS NÃO ALCOÓLICAS | D14: Produto | E14: Delivery Interlagos, Quintal do Espeto Lapa , Quintal do Espeto Santo André, Quintal do Espeto Chac Sto Antonio, Delivery Lapa, Delivery Carinás, Delivery Vila Madalena, Delivery Tatuapé, Delivery Chac. Sto Antonio, Quintal do Espeto Santana, Quintal do Espeto V. Mariana, Delivery Santo André, Delivery Pavão, Delivery V. Mariana, Delivery Perdizes, Quintal do Espeto Perdizes, Delivery Santana, Quintal do Espeto Tatuapé, Quintal do Espeto V. Madalena, Quintal do Espeto Carinás, Quintal do Espeto Pavão, Quintal do Espeto Interlagos, Quintal do Espeto Recargas/Bônus | F14: e5fcc179-a311-4526-b471-b7f1fad91f6e | G14: =IF(E14="","Inativo",IF(SUMPRODUCT(--(ISNUMBER(SEARCH({"Lapa","Santana","Mariana","Perdizes","André","Tatuapé","Madalena","Carinás","Pavão","Chac"},E14))))>0,"Ativo","Inativo"))
A15: 71007 | B15: H2OH! | C15: A BEBIDAS NÃO ALCOÓLICAS | D15: Produto | E15: Quintal do Espeto Lapa , Quintal do Espeto Santo André, Quintal do Espeto Chac Sto Antonio, Quintal do Espeto Santana, Quintal do Espeto V. Mariana, Quintal do Espeto Perdizes, Quintal do Espeto Tatuapé, Quintal do Espeto V. Madalena, Quintal do Espeto Carinás, Quintal do Espeto Pavão, Quintal do Espeto Interlagos, Quintal do Espeto Recargas/Bônus | F15: 728f645e-bf3b-4706-a717-3bcfcf16bfc1 | G15: =IF(E15="","Inativo",IF(SUMPRODUCT(--(ISNUMBER(SEARCH({"Lapa","Santana","Mariana","Perdizes","André","Tatuapé","Madalena","Carinás","Pavão","Chac"},E15))))>0,"Ativo","Inativo"))
A16: 71008 | B16: AGUA TONICA DIET | C16: A BEBIDAS NÃO ALCOÓLICAS | D16: Produto | E16: Quintal do Espeto Lapa , Quintal do Espeto Santo André, Quintal do Espeto Chac Sto Antonio, Quintal do Espeto Santana, Quintal do Espeto V. Mariana, Quintal do Espeto Perdizes, Quintal do Espeto Tatuapé, Quintal do Espeto V. Madalena, Quintal do Espeto Carinás, Quintal do Espeto Pavão, Quintal do Espeto Interlagos, Quintal do Espeto Recargas/Bônus | F16: 7e9fcf72-266d-48db-9ed1-82b3f0d7930c | G16: =IF(E16="","Inativo",IF(SUMPRODUCT(--(ISNUMBER(SEARCH({"Lapa","Santana","Mariana","Perdizes","André","Tatuapé","Madalena","Carinás","Pavão","Chac"},E16))))>0,"Ativo","Inativo"))
A17: 71009 | B17: PEPSI LIGHT | C17: A BEBIDAS NÃO ALCOÓLICAS | D17: Produto | E17: Delivery Interlagos, Quintal do Espeto Lapa , Quintal do Espeto Santo André, Quintal do Espeto Chac Sto Antonio, Delivery Lapa, Delivery Carinás, Delivery Vila Madalena, Delivery Tatuapé, Delivery Chac. Sto Antonio, Quintal do Espeto Santana, Quintal do Espeto V. Mariana, Delivery Santo André, Delivery Pavão, Delivery V. Mariana, Delivery Perdizes, Quintal do Espeto Perdizes, Delivery Santana, Quintal do Espeto Tatuapé, Quintal do Espeto V. Madalena, Quintal do Espeto Carinás, Quintal do Espeto Pavão, Quintal do Espeto Interlagos, Quintal do Espeto Recargas/Bônus | F17: 59f7af6c-1b88-4d24-a5e7-3a3a4578de52 | G17: =IF(E17="","Inativo",IF(SUMPRODUCT(--(ISNUMBER(SEARCH({"Lapa","Santana","Mariana","Perdizes","André","Tatuapé","Madalena","Carinás","Pavão","Chac"},E17))))>0,"Ativo","Inativo"))
A18: 71011 | B18: GUARANA ANTARTICA ZERO | C18: A BEBIDAS NÃO ALCOÓLICAS | D18: Produto | E18: Delivery Interlagos, Quintal do Espeto Lapa , Quintal do Espeto Santo André, Quintal do Espeto Chac Sto Antonio, Delivery Lapa, Delivery Carinás, Delivery Vila Madalena, Delivery Tatuapé, Delivery Chac. Sto Antonio, Quintal do Espeto Santana, Quintal do Espeto V. Mariana, Delivery Santo André, Delivery Pavão, Delivery V. Mariana, Delivery Perdizes, Quintal do Espeto Perdizes, Delivery Santana, Quintal do Espeto Tatuapé, Quintal do Espeto V. Madalena, Quintal do Espeto Carinás, Quintal do Espeto Pavão, Quintal do Espeto Interlagos, Quintal do Espeto Recargas/Bônus | F18: 32c6871f-be04-45c8-98aa-3f4968fc7210 | G18: =IF(E18="","Inativo",IF(SUMPRODUCT(--(ISNUMBER(SEARCH({"Lapa","Santana","Mariana","Perdizes","André","Tatuapé","Madalena","Carinás","Pavão","Chac"},E18))))>0,"Ativo","Inativo"))
... A105: 789890568773454 | B105: ESPETO DE FRANGO - TURBO | C105: ESPETOS CLÁSSICOS | D105: Produto | E105: Delivery Carinás, Delivery Tatuapé, Delivery Santo André, Delivery Santana | F105: 4666510e-37e3-4b8f-929e-9175c4ef91c9 | G105: =IF(E105="","Inativo",IF(SUMPRODUCT(--(ISNUMBER(SEARCH({"Lapa","Santana","Mariana","Perdizes","André","Tatuapé","Madalena","Carinás","Pavão","Chac"},E105))))>0,"Ativo","Inativo"))
A106: 9003135 | B106: CLÁSSICOS | C106: ESPETOS CLÁSSICOS | D106: Produto | F106: 7c37ccec-69fe-4406-8f87-e7705fa70c78 | G106: =IF(E106="","Inativo",IF(SUMPRODUCT(--(ISNUMBER(SEARCH({"Lapa","Santana","Mariana","Perdizes","André","Tatuapé","Madalena","Carinás","Pavão","Chac"},E106))))>0,"Ativo","Inativo"))
A107: 10042 | B107: CUIABANA | C107: SELEÇÃO PREMIUM | D107: Produto | E107: Delivery Interlagos, Quintal do Espeto Lapa , Quintal do Espeto Santo André, Quintal do Espeto Chac Sto Antonio, Delivery Lapa, Delivery Carinás, Delivery Vila Madalena, Delivery Tatuapé, Delivery Chac. Sto Antonio, Quintal do Espeto Santana, Quintal do Espeto V. Mariana, Delivery Santo André, Delivery Pavão, Delivery V. Mariana, Delivery Perdizes, Quintal do Espeto Perdizes, Delivery Santana, Quintal do Espeto Tatuapé, Quintal do Espeto V. Madalena, Quintal do Espeto Carinás, Quintal do Espeto Pavão, Quintal do Espeto Interlagos, Quintal do Espeto Recargas/Bônus | F107: 15b991d9-ea2d-4451-98d9-14cbcbe06474 | G107: =IF(E107="","Inativo",IF(SUMPRODUCT(--(ISNUMBER(SEARCH({"Lapa","Santana","Mariana","Perdizes","André","Tatuapé","Madalena","Carinás","Pavão","Chac"},E107))))>0,"Ativo","Inativo"))
A108: 40001 | B108: CAMARAO BRASA | C108: SELEÇÃO PREMIUM | D108: Produto | E108: Delivery Interlagos, Quintal do Espeto Lapa , Quintal do Espeto Santo André, Quintal do Espeto Chac Sto Antonio, Delivery Lapa, Delivery Carinás, Delivery Vila Madalena, Delivery Tatuapé, Delivery Chac. Sto Antonio, Quintal do Espeto Santana, Quintal do Espeto V. Mariana, Delivery Santo André, Delivery Pavão, Delivery V. Mariana, Delivery Perdizes, Quintal do Espeto Perdizes, Delivery Santana, Quintal do Espeto Tatuapé, Quintal do Espeto V. Madalena, Quintal do Espeto Carinás, Quintal do Espeto Pavão, Quintal do Espeto Interlagos, Quintal do Espeto Recargas/Bônus | F108: 69870b84-fb9c-48dd-94a1-54033b4c6dac | G108: =IF(E108="","Inativo",IF(SUMPRODUCT(--(ISNUMBER(SEARCH({"Lapa","Santana","Mariana","Perdizes","André","Tatuapé","Madalena","Carinás","Pavão","Chac"},E108))))>0,"Ativo","Inativo"))
A109: 40007 | B109: SHIMEJI | C109: SELEÇÃO PREMIUM | D109: Produto | E109: Quintal do Espeto Lapa , Quintal do Espeto Santo André, Quintal do Espeto Chac Sto Antonio, Quintal do Espeto Santana, Quintal do Espeto V. Mariana, Quintal do Espeto Perdizes, Quintal do Espeto Tatuapé, Quintal do Espeto V. Madalena, Quintal do Espeto Carinás, Quintal do Espeto Pavão, Quintal do Espeto Interlagos, Quintal do Espeto Recargas/Bônus | F109: 95eaa444-8382-40d2-8515-3096508b7104 | G109: =IF(E109="","Inativo",IF(SUMPRODUCT(--(ISNUMBER(SEARCH({"Lapa","Santana","Mariana","Perdizes","André","Tatuapé","Madalena","Carinás","Pavão","Chac"},E109))))>0,"Ativo","Inativo"))
A110: 40009 | B110: SALSICHAO C/ PROVOLONE | C110: SELEÇÃO PREMIUM | D110: Produto | E110: Delivery Interlagos, Quintal do Espeto Lapa , Quintal do Espeto Santo André, Quintal do Espeto Chac Sto Antonio, Delivery Lapa, Delivery Carinás, Delivery Vila Madalena, Delivery Tatuapé, Delivery Chac. Sto Antonio, Quintal do Espeto Santana, Quintal do Espeto V. Mariana, Delivery Santo André, Delivery Pavão, Delivery V. Mariana, Delivery Perdizes, Quintal do Espeto Perdizes, Delivery Santana, Quintal do Espeto Tatuapé, Quintal do Espeto V. Madalena, Quintal do Espeto Carinás, Quintal do Espeto Pavão, Quintal do Espeto Interlagos, Quintal do Espeto Recargas/Bônus | F110: f7a341a5-a770-473a-a91e-a43193a83b69 | G110: =IF(E110="","Inativo",IF(SUMPRODUCT(--(ISNUMBER(SEARCH({"Lapa","Santana","Mariana","Perdizes","André","Tatuapé","Madalena","Carinás","Pavão","Chac"},E110))))>0,"Ativo","Inativo"))
A111: 40016 | B111: PICANHA | C111: SELEÇÃO PREMIUM | D111: Produto | E111: Quintal do Espeto Lapa , Quintal do Espeto Santo André, Quintal do Espeto Chac Sto Antonio, Quintal do Espeto Santana, Quintal do Espeto V. Mariana, Quintal do Espeto Perdizes, Quintal do Espeto Tatuapé, Quintal do Espeto V. Madalena, Quintal do Espeto Carinás, Quintal do Espeto Pavão, Quintal do Espeto Interlagos, Quintal do Espeto Recargas/Bônus | F111: 7f4e6fb5-b666-4346-a766-72c2812fac16 | G111: =IF(E111="","Inativo",IF(SUMPRODUCT(--(ISNUMBER(SEARCH({"Lapa","Santana","Mariana","Perdizes","André","Tatuapé","Madalena","Carinás","Pavão","Chac"},E111))))>0,"Ativo","Inativo"))
A112: 40020 | B112: CARRE DE CORDEIRO | C112: SELEÇÃO PREMIUM | D112: Produto | E112: Quintal do Espeto Lapa , Quintal do Espeto Santo André, Quintal do Espeto Chac Sto Antonio, Quintal do Espeto Santana, Quintal do Espeto V. Mariana, Quintal do Espeto Perdizes, Quintal do Espeto Tatuapé, Quintal do Espeto V. Madalena, Quintal do Espeto Carinás, Quintal do Espeto Pavão, Quintal do Espeto Interlagos, Quintal do Espeto Recargas/Bônus | F112: 5c55e3d1-52c3-40b2-9338-beebcdfb66f6 | G112: =IF(E112="","Inativo",IF(SUMPRODUCT(--(ISNUMBER(SEARCH({"Lapa","Santana","Mariana","Perdizes","André","Tatuapé","Madalena","Carinás","Pavão","Chac"},E112))))>0,"Ativo","Inativo"))
A113: 40022 | B113: FILE MIGNON BOVINO | C113: SELEÇÃO PREMIUM | D113: Produto | E113: Delivery Interlagos, Quintal do Espeto Lapa , Quintal do Espeto Santo André, Quintal do Espeto Chac Sto Antonio, Delivery Lapa, Delivery Carinás, Delivery Vila Madalena, Delivery Tatuapé, Delivery Chac. Sto Antonio, Quintal do Espeto Santana, Quintal do Espeto V. Mariana, Delivery Santo André, Delivery Pavão, Delivery V. Mariana, Delivery Perdizes, Quintal do Espeto Perdizes, Delivery Santana, Quintal do Espeto Tatuapé, Quintal do Espeto V. Madalena, Quintal do Espeto Carinás, Quintal do Espeto Pavão, Quintal do Espeto Interlagos, Quintal do Espeto Recargas/Bônus | F113: d154257e-ad1e-4451-a619-e917f07f4d43 | G113: =IF(E113="","Inativo",IF(SUMPRODUCT(--(ISNUMBER(SEARCH({"Lapa","Santana","Mariana","Perdizes","André","Tatuapé","Madalena","Carinás","Pavão","Chac"},E113))))>0,"Ativo","Inativo"))
A114: 789890568772111 | B114: ESPETO MEDALHÃO MANDIOCA | C114: SELEÇÃO PREMIUM | D114: Produto | E114: Quintal do Espeto Lapa , Quintal do Espeto Santo André, Quintal do Espeto Chac Sto Antonio, Quintal do Espeto Santana, Quintal do Espeto V. Mariana, Quintal do Espeto Perdizes, Quintal do Espeto Tatuapé, Quintal do Espeto V. Madalena, Quintal do Espeto Carinás, Quintal do Espeto Pavão | F114: e13d8731-0477-4c30-98f0-9a8be50f8e17 | G114: =IF(E114="","Inativo",IF(SUMPRODUCT(--(ISNUMBER(SEARCH({"Lapa","Santana","Mariana","Perdizes","André","Tatuapé","Madalena","Carinás","Pavão","Chac"},E114))))>0,"Ativo","Inativo"))
A115: 789890568772112 | B115: ESPETO PROVOLONE DEFUMADO | C115: SELEÇÃO PREMIUM | D115: Produto | E115: Quintal do Espeto Lapa , Quintal do Espeto Santo André, Quintal do Espeto Chac Sto Antonio, Quintal do Espeto Santana, Quintal do Espeto V. Mariana, Quintal do Espeto Perdizes, Quintal do Espeto Tatuapé, Quintal do Espeto V. Madalena, Quintal do Espeto Carinás, Quintal do Espeto Pavão | F115: 0ea10e70-8dbe-4260-aaf9-fb11624baa2b | G115: =IF(E115="","Inativo",IF(SUMPRODUCT(--(ISNUMBER(SEARCH({"Lapa","Santana","Mariana","Perdizes","André","Tatuapé","Madalena","Carinás","Pavão","Chac"},E115))))>0,"Ativo","Inativo"))
A116: 789890568772113 | B116: ESPETO MEDALHAO ALCATRA | C116: SELEÇÃO PREMIUM | D116: Produto | E116: Quintal do Espeto Lapa , Quintal do Espeto Santo André, Quintal do Espeto Chac Sto Antonio, Quintal do Espeto Santana, Quintal do Espeto V. Mariana, Quintal do Espeto Perdizes, Quintal do Espeto Tatuapé, Quintal do Espeto V. Madalena, Quintal do Espeto Carinás, Quintal do Espeto Pavão | F116: e1595f39-b850-4571-95ad-a8a7be406017 | G116: =IF(E116="","Inativo",IF(SUMPRODUCT(--(ISNUMBER(SEARCH({"Lapa","Santana","Mariana","Perdizes","André","Tatuapé","Madalena","Carinás","Pavão","Chac"},E116))))>0,"Ativo","Inativo"))
A117: 789890568772114 | B117: ESPETO MEDALHÃO DE FRANGO | C117: SELEÇÃO PREMIUM | D117: Produto | E117: Quintal do Espeto Lapa , Quintal do Espeto Santo André, Quintal do Espeto Chac Sto Antonio, Quintal do Espeto Santana, Quintal do Espeto V. Mariana, Quintal do Espeto Perdizes, Quintal do Espeto Tatuapé, Quintal do Espeto V. Madalena, Quintal do Espeto Carinás, Quintal do Espeto Pavão | F117: c0ef4e2e-0176-4029-987a-0193df4d75a6 | G117: =IF(E117="","Inativo",IF(SUMPRODUCT(--(ISNUMBER(SEARCH({"Lapa","Santana","Mariana","Perdizes","André","Tatuapé","Madalena","Carinás","Pavão","Chac"},E117))))>0,"Ativo","Inativo"))
A118: 9003337 | B118: COSTELA BOVINA | C118: SELEÇÃO PREMIUM | D118: Produto | E118: Quintal do Espeto Lapa , Quintal do Espeto Santo André, Quintal do Espeto Chac Sto Antonio, Quintal do Espeto Santana, Quintal do Espeto V. Mariana, Quintal do Espeto Perdizes, Quintal do Espeto Tatuapé, Quintal do Espeto V. Madalena, Quintal do Espeto Carinás, Quintal do Espeto Pavão, Quintal do Espeto Interlagos, Quintal do Espeto Recargas/Bônus | F118: 05efde93-ec52-43d8-bb74-01ab7139e709 | G118: =IF(E118="","Inativo",IF(SUMPRODUCT(--(ISNUMBER(SEARCH({"Lapa","Santana","Mariana","Perdizes","André","Tatuapé","Madalena","Carinás","Pavão","Chac"},E118))))>0,"Ativo","Inativo"))
... A184: 9003482 | B184: GIN TANQUERAY DOSE | C184: A DESTILADOS | D184: Produto | E184: Quintal do Espeto Lapa , Quintal do Espeto Santo André, Quintal do Espeto Chac Sto Antonio, Quintal do Espeto Santana, Quintal do Espeto V. Mariana, Quintal do Espeto Perdizes, Quintal do Espeto Tatuapé, Quintal do Espeto V. Madalena, Quintal do Espeto Carinás, Quintal do Espeto Pavão, Quintal do Espeto Interlagos, Quintal do Espeto Recargas/Bônus | F184: e905f763-96c0-47f7-91d0-8dde2d8114a5 | G184: =IF(E184="","Inativo",IF(SUMPRODUCT(--(ISNUMBER(SEARCH({"Lapa","Santana","Mariana","Perdizes","André","Tatuapé","Madalena","Carinás","Pavão","Chac"},E184))))>0,"Ativo","Inativo"))
A185: 21069094 | B185: VINHO CASA DE TANGO 750 ML TT | C185: VINHOS TINTOS | D185: Produto | F185: 7b5d973f-98c3-4594-b3b1-771352891b87 | G185: =IF(E185="","Inativo",IF(SUMPRODUCT(--(ISNUMBER(SEARCH({"Lapa","Santana","Mariana","Perdizes","André","Tatuapé","Madalena","Carinás","Pavão","Chac"},E185))))>0,"Ativo","Inativo"))
A186: 21069095 | B186: VINHO GALLO REI | C186: VINHOS TINTOS | D186: Produto | E186: Quintal do Espeto Lapa , Quintal do Espeto Santo André, Quintal do Espeto Chac Sto Antonio, Quintal do Espeto Santana, Quintal do Espeto V. Mariana, Quintal do Espeto Perdizes, Quintal do Espeto Tatuapé, Quintal do Espeto V. Madalena, Quintal do Espeto Carinás, Quintal do Espeto Pavão, Quintal do Espeto Recargas/Bônus | F186: 49c13390-2ad6-4e0c-898f-f37c86193bdc | G186: =IF(E186="","Inativo",IF(SUMPRODUCT(--(ISNUMBER(SEARCH({"Lapa","Santana","Mariana","Perdizes","André","Tatuapé","Madalena","Carinás","Pavão","Chac"},E186))))>0,"Ativo","Inativo"))
A187: 300066 | B187: ANTARES CARMENERE 750 ml | C187: VINHOS TINTOS | D187: Produto | E187: Quintal do Espeto Lapa , Quintal do Espeto Santo André, Quintal do Espeto Chac Sto Antonio, Quintal do Espeto Santana, Quintal do Espeto V. Mariana, Quintal do Espeto Perdizes, Quintal do Espeto Tatuapé, Quintal do Espeto V. Madalena, Quintal do Espeto Carinás, Quintal do Espeto Pavão, Quintal do Espeto Interlagos, Quintal do Espeto Recargas/Bônus | F187: d2a3e5ca-5e26-4cea-8265-7c50b097292c | G187: =IF(E187="","Inativo",IF(SUMPRODUCT(--(ISNUMBER(SEARCH({"Lapa","Santana","Mariana","Perdizes","André","Tatuapé","Madalena","Carinás","Pavão","Chac"},E187))))>0,"Ativo","Inativo"))
A188: 300202 | B188: LAMBRUSCO | C188: VINHOS TINTOS | D188: Produto | E188: Quintal do Espeto Lapa , Quintal do Espeto Santo André, Quintal do Espeto Chac Sto Antonio, Quintal do Espeto Santana, Quintal do Espeto V. Mariana, Quintal do Espeto Perdizes, Quintal do Espeto Tatuapé, Quintal do Espeto V. Madalena, Quintal do Espeto Carinás, Quintal do Espeto Pavão, Quintal do Espeto Interlagos, Quintal do Espeto Recargas/Bônus | F188: ba178f21-f5f6-41ee-b90c-dc2cf6362573 | G188: =IF(E188="","Inativo",IF(SUMPRODUCT(--(ISNUMBER(SEARCH({"Lapa","Santana","Mariana","Perdizes","André","Tatuapé","Madalena","Carinás","Pavão","Chac"},E188))))>0,"Ativo","Inativo"))
A189: 7898905687190 | B189: NORTON PORTEÑO MALBEC | C189: VINHOS TINTOS | D189: Produto | E189: Quintal do Espeto Lapa , Quintal do Espeto Santo André, Quintal do Espeto Chac Sto Antonio, Quintal do Espeto Santana, Quintal do Espeto V. Mariana, Quintal do Espeto Perdizes, Quintal do Espeto Tatuapé, Quintal do Espeto V. Madalena, Quintal do Espeto Carinás, Quintal do Espeto Pavão, Quintal do Espeto Interlagos, Quintal do Espeto Recargas/Bônus | F189: 61fabcc8-6c25-4496-89ac-127b1a30f8ba | G189: =IF(E189="","Inativo",IF(SUMPRODUCT(--(ISNUMBER(SEARCH({"Lapa","Santana","Mariana","Perdizes","André","Tatuapé","Madalena","Carinás","Pavão","Chac"},E189))))>0,"Ativo","Inativo"))
A190: 789890568772117 | B190: VINHO TINTO PORTUGUES TERRA DEL REI ALENTEJO 750ML | C190: VINHOS TINTOS | D190: Produto | E190: Quintal do Espeto Lapa , Quintal do Espeto Santo André, Quintal do Espeto Chac Sto Antonio, Quintal do Espeto Santana, Quintal do Espeto Perdizes, Quintal do Espeto Tatuapé, Quintal do Espeto V. Madalena, Quintal do Espeto Carinás, Quintal do Espeto Pavão | F190: 3b8c7504-4449-4d5b-9052-4ef9680bd602 | G190: =IF(E190="","Inativo",IF(SUMPRODUCT(--(ISNUMBER(SEARCH({"Lapa","Santana","Mariana","Perdizes","André","Tatuapé","Madalena","Carinás","Pavão","Chac"},E190))))>0,"Ativo","Inativo"))
A191: 789890568772119 | B191: VINHO CHILENO VISTANA CABERNET SAUVINGON 375ML | C191: VINHOS TINTOS | D191: Produto | E191: Quintal do Espeto Lapa , Quintal do Espeto Santo André, Quintal do Espeto Chac Sto Antonio, Quintal do Espeto Santana, Quintal do Espeto V. Mariana, Quintal do Espeto Perdizes, Quintal do Espeto Tatuapé, Quintal do Espeto V. Madalena, Quintal do Espeto Carinás, Quintal do Espeto Pavão | F191: 64faf0ca-26f7-47b4-9f42-e34cef1ccb74 | G191: =IF(E191="","Inativo",IF(SUMPRODUCT(--(ISNUMBER(SEARCH({"Lapa","Santana","Mariana","Perdizes","André","Tatuapé","Madalena","Carinás","Pavão","Chac"},E191))))>0,"Ativo","Inativo"))
A192: 789890568772120 | B192: VINHO CHILENO VISTANA CABERNET MERLOT 375ML | C192: VINHOS TINTOS | D192: Produto | E192: Quintal do Espeto Lapa , Quintal do Espeto Santo André, Quintal do Espeto Chac Sto Antonio, Quintal do Espeto Santana, Quintal do Espeto V. Mariana, Quintal do Espeto Perdizes, Quintal do Espeto Tatuapé, Quintal do Espeto V. Madalena, Quintal do Espeto Carinás, Quintal do Espeto Pavão | F192: bed47a49-4a31-4d9a-b454-d3bcfac32e0f | G192: =IF(E192="","Inativo",IF(SUMPRODUCT(--(ISNUMBER(SEARCH({"Lapa","Santana","Mariana","Perdizes","André","Tatuapé","Madalena","Carinás","Pavão","Chac"},E192))))>0,"Ativo","Inativo"))
A193: 789890568772123 | B193: VINHO ARGENTINO ALFREDO ROCA MALBEC 375ML | C193: VINHOS TINTOS | D193: Produto | E193: Quintal do Espeto Lapa , Quintal do Espeto Santo André, Quintal do Espeto Chac Sto Antonio, Quintal do Espeto Santana, Quintal do Espeto V. Mariana, Quintal do Espeto Perdizes, Quintal do Espeto Tatuapé, Quintal do Espeto V. Madalena, Quintal do Espeto Carinás, Quintal do Espeto Pavão | F193: b8f6780c-6ecb-40b5-aba8-8bd1e1a3520e | G193: =IF(E193="","Inativo",IF(SUMPRODUCT(--(ISNUMBER(SEARCH({"Lapa","Santana","Mariana","Perdizes","André","Tatuapé","Madalena","Carinás","Pavão","Chac"},E193))))>0,"Ativo","Inativo"))
A194: 789890568772124 | B194: VINHO ARGENTINO ALFREDO ROCA CHARDONNAY 375ML | C194: VINHOS TINTOS | D194: Produto | E194: Quintal do Espeto Lapa , Quintal do Espeto Santo André, Quintal do Espeto Chac Sto Antonio, Quintal do Espeto Santana, Quintal do Espeto V. Mariana, Quintal do Espeto Perdizes, Quintal do Espeto Tatuapé, Quintal do Espeto V. Madalena, Quintal do Espeto Carinás, Quintal do Espeto Pavão | F194: 74c44ae2-f977-4bf3-bb5f-44ca3325b8b3 | G194: =IF(E194="","Inativo",IF(SUMPRODUCT(--(ISNUMBER(SEARCH({"Lapa","Santana","Mariana","Perdizes","André","Tatuapé","Madalena","Carinás","Pavão","Chac"},E194))))>0,"Ativo","Inativo"))
A195: 789890568772125 | B195: VINHO ESPANHOL PATA NEGRA ORO TEMPRANILLO 750ML | C195: VINHOS TINTOS | D195: Produto | E195: Quintal do Espeto Lapa , Quintal do Espeto Santo André, Quintal do Espeto Chac Sto Antonio, Quintal do Espeto Santana, Quintal do Espeto V. Mariana, Quintal do Espeto Perdizes, Quintal do Espeto Tatuapé, Quintal do Espeto V. Madalena, Quintal do Espeto Carinás, Quintal do Espeto Pavão | F195: 7794589e-2162-4aba-8b3d-775846930128 | G195: =IF(E195="","Inativo",IF(SUMPRODUCT(--(ISNUMBER(SEARCH({"Lapa","Santana","Mariana","Perdizes","André","Tatuapé","Madalena","Carinás","Pavão","Chac"},E195))))>0,"Ativo","Inativo"))
A196: 789890568772128 | B196: VINHO ITALIANO LAMBRUSCO VILLA FABRIZIA TINTO 750ML | C196: VINHOS TINTOS | D196: Produto | E196: Quintal do Espeto Lapa , Quintal do Espeto Santo André, Quintal do Espeto Chac Sto Antonio, Quintal do Espeto Santana, Quintal do Espeto V. Mariana, Quintal do Espeto Perdizes, Quintal do Espeto Tatuapé, Quintal do Espeto V. Madalena, Quintal do Espeto Carinás, Quintal do Espeto Pavão | F196: 01e6fa72-660d-45cc-a5b6-36599ca6fa1e | G196: =IF(E196="","Inativo",IF(SUMPRODUCT(--(ISNUMBER(SEARCH({"Lapa","Santana","Mariana","Perdizes","André","Tatuapé","Madalena","Carinás","Pavão","Chac"},E196))))>0,"Ativo","Inativo"))
A197: 789890568772129 | B197: VINHO FRANCES MONTMEYRAC TINTO 750 ML | C197: VINHOS TINTOS | D197: Produto | E197: Quintal do Espeto Lapa , Quintal do Espeto Santo André, Quintal do Espeto Chac Sto Antonio, Quintal do Espeto Santana, Quintal do Espeto V. Mariana, Quintal do Espeto Perdizes, Quintal do Espeto Tatuapé, Quintal do Espeto V. Madalena, Quintal do Espeto Carinás, Quintal do Espeto Pavão | F197: 3e38a78f-16bd-4732-aa31-a882206ae4a5 | G197: =IF(E197="","Inativo",IF(SUMPRODUCT(--(ISNUMBER(SEARCH({"Lapa","Santana","Mariana","Perdizes","André","Tatuapé","Madalena","Carinás","Pavão","Chac"},E197))))>0,"Ativo","Inativo"))
... A534: 9003562 | B534: RODIZIO DE CLÁSSICOS KIDS | C534: PROMOÇÃO | D534: Produto | E534: Quintal do Espeto Lapa , Quintal do Espeto Santo André, Quintal do Espeto Chac Sto Antonio, Quintal do Espeto Santana, Quintal do Espeto V. Mariana, Quintal do Espeto Perdizes, Quintal do Espeto Tatuapé, Quintal do Espeto V. Madalena, Quintal do Espeto Carinás, Quintal do Espeto Pavão, Quintal do Espeto Interlagos, Quintal do Espeto Recargas/Bônus | F534: d823ccab-3f32-4629-b4e0-6903329b3b17 | G534: =IF(E534="","Inativo",IF(SUMPRODUCT(--(ISNUMBER(SEARCH({"Lapa","Santana","Mariana","Perdizes","André","Tatuapé","Madalena","Carinás","Pavão","Chac"},E534))))>0,"Ativo","Inativo"))

Sheet _Entradas_ZIG
A1: LOJA | B1: Nome (Entrada) | C1: SKU | D1: Categoria | E1: Valor | F1: Local Normalizado | G1: Última Atualização: 07/05/2026
A2: VILA MARIANA | B2: ENTRADA MUSICO | C2: 7898905687352 | D2: 0 ENTRADAS VIPS | F2: Quintal do Espeto V. Mariana
A3: VILA MARIANA | B3: ENTRADA SÁBADO NOITE | C3: 47541 | D3: 6 ENTRADAS SABADO | E3: 7 | F3: Quintal do Espeto V. Mariana
A4: VILA MARIANA | B4: ENTRADA TERÇA FEIRA | C4: 511003 | D4: 2 ENTRADAS TERÇA-FEIRA | E4: 7 | F4: Quintal do Espeto V. Mariana
A5: VILA MARIANA | B5: ENTRADA QUINTA FEIRA | C5: 511007 | D5: 4 ENTRADAS QUINTA-FEIRA | E5: 7 | F5: Quintal do Espeto V. Mariana
A6: VILA MARIANA | B6: ENTRADA DOMINGO NOITE | C6: 511031 | D6: 7 ENTRADAS DOMINGO | E6: 7 | F6: Quintal do Espeto V. Mariana
A7: VILA MARIANA | B7: ENTRADA ANIVERSARIO | C7: 511081 | D7: 0 ENTRADAS VIPS | F7: Quintal do Espeto V. Mariana
A8: VILA MARIANA | B8: ENTRADA SÁBADO DIA | C8: 99388 | D8: 6 ENTRADAS SABADO | E8: 7 | F8: Quintal do Espeto V. Mariana
A9: VILA MARIANA | B9: SEGUNDA | C9: 61581 | D9: 1 ENTRADAS SEGUNDA-FEIRA | E9: 7 | F9: Quintal do Espeto V. Mariana
A10: VILA MARIANA | B10: ENTRADA VIP | C10: 9003594 | D10: 0 ENTRADAS VIPS | F10: Quintal do Espeto V. Mariana
A11: VILA MARIANA | B11: ENTRADA QUARTA FEIRA | C11: 71616 | D11: 3 ENTRADAS QUARTA-FEIRA | E11: 7 | F11: Quintal do Espeto V. Mariana
A12: VILA MARIANA | B12: ENTRADA DOMINGO DIA | C12: 42193 | D12: 7 ENTRADAS DOMINGO | E12: 7 | F12: Quintal do Espeto V. Mariana
A13: VILA MARIANA | B13: ENTRADA SEXTA FEIRA | C13: 10989 | D13: 5 ENTRADAS SEXTA-FEIRA | E13: 7 | F13: Quintal do Espeto V. Mariana
A14: PERDIZES | B14: ENTRADA MUSICO | C14: 7898905687358 | D14: 0 ENTRADAS VIPS | F14: Quintal do Espeto Perdizes
A15: PERDIZES | B15: ENTRADA SÁBADO NOITE | C15: 511015 | D15: 6 ENTRADAS SABADO | E15: 7 | F15: Quintal do Espeto Perdizes
A16: PERDIZES | B16: ENTRADA TERÇA FEIRA | C16: 77506 | D16: 2 ENTRADAS TERÇA-FEIRA | E16: 7 | F16: Quintal do Espeto Perdizes
A17: PERDIZES | B17: ENTRADA QUINTA FEIRA | C17: 74216 | D17: 4 ENTRADAS QUINTA-FEIRA | E17: 7 | F17: Quintal do Espeto Perdizes
A18: PERDIZES | B18: ENTRADA DOMINGO NOITE | C18: 94875 | D18: 7 ENTRADAS DOMINGO | E18: 7 | F18: Quintal do Espeto Perdizes
A19: PERDIZES | B19: ENTRADA ANIVERSARIO | C19: 63376 | D19: 0 ENTRADAS VIPS | F19: Quintal do Espeto Perdizes
A20: PERDIZES | B20: ENTRADA SÁBADO DIA | C20: 37724 | D20: 6 ENTRADAS SABADO | E20: 7 | F20: Quintal do Espeto Perdizes
A21: PERDIZES | B21: SEGUNDA | C21: 66068 | D21: 1 ENTRADAS SEGUNDA-FEIRA | E21: 7 | F21: Quintal do Espeto Perdizes
A22: PERDIZES | B22: ENTRADA VIP | C22: 22148 | D22: 0 ENTRADAS VIPS | F22: Quintal do Espeto Perdizes
A23: PERDIZES | B23: ENTRADA QUARTA FEIRA | C23: 34362 | D23: 3 ENTRADAS QUARTA-FEIRA | E23: 7 | F23: Quintal do Espeto Perdizes
A24: PERDIZES | B24: ENTRADA DOMINGO DIA | C24: 72728 | D24: 7 ENTRADAS DOMINGO | E24: 7 | F24: Quintal do Espeto Perdizes
A25: PERDIZES | B25: ENTRADA SEXTA FEIRA | C25: 511009 | D25: 5 ENTRADAS SEXTA-FEIRA | E25: 7 | F25: Quintal do Espeto Perdizes
A26: CARINAS | B26: ENTRADA VIP COLABORADORES | C26: 9003592 | D26: 0 ENTRADAS VIPS(RESTAURADA) | F26: Quintal do Espeto Carinás
A27: CARINAS | B27: ENTRADA MUSICO | C27: 7898905687353 | D27: 0 ENTRADAS VIPS | F27: Quintal do Espeto Carinás
A28: CARINAS | B28: ENTRADA SHOW GERIATRICOS | C28: 9003636 | D28: 8 ENTRADAS SHOW | E28: 41382.4 | F28: Quintal do Espeto Carinás
A29: CARINAS | B29: BRINCADEIRA 10. | C29: 78989056877145 | D29: OUTROS | E29: 20 | F29: Quintal do Espeto Carinás
A30: CARINAS | B30: CRIANÇAS EVENTO KIDS | C30: 78989056877147 | D30: OUTROS | F30: Quintal do Espeto Carinás
A31: CARINAS | B31: ENTRADA FLAMENGO TICKET 360 | C31: 9003131 | D31: ENTRADAS TORCIDAS DE FUTEBOL | E31: 50 | F31: Quintal do Espeto Carinás
A32: CARINAS | B32: ENTRADA DOMINGO | C32: 511041 | D32: ENTRADA DOMINGO | E32: 10 | F32: Quintal do Espeto Carinás
A33: CARINAS | B33: ENTRADA QUINTA FEIRA | C33: 95063 | D33: 4 ENTRADAS QUINTA-FEIRA | E33: 20 | F33: Quintal do Espeto Carinás
A34: CARINAS | B34: ENTRADA DOMINGO NOITE - APOS AS 17;00 | C34: 9003129 | D34: 7 ENTRADAS DOMINGO | E34: 20 | F34: Quintal do Espeto Carinás
A35: CARINAS | B35: ENTRADA DOMINGO | C35: 9003580 | D35: ENTRADA DOMINGO | E35: 30 | F35: Quintal do Espeto Carinás
A36: CARINAS | B36: ENTRADA VIP GARRAFAS | C36: 9003591 | D36: 0 ENTRADAS VIPS(RESTAURADA) | F36: Quintal do Espeto Carinás
A37: CARINAS | B37: ENTRADA TERCA FEIRA | C37: 54039 | D37: 2 ENTRADAS TERÇA-FEIRA | E37: 15 | F37: Quintal do Espeto Carinás
A38: CARINAS | B38: ENTRADA FLAMENGO | C38: 15952 | D38: ENTRADAS TORCIDAS DE FUTEBOL | E38: 10 | F38: Quintal do Espeto Carinás
A39: CARINAS | B39: ENTRADA TORCIDA INTER | C39: 9003130 | D39: ENTRADAS TORCIDAS DE FUTEBOL | F39: Quintal do Espeto Carinás
A40: CARINAS | B40: PASSAPORTE DIVERSÃO (ENTRADA + KIT MASSINHA) | C40: 78989056877393 | D40: ESPAÇO KIDS | E40: 29.9 | F40: Quintal do Espeto Carinás
A41: CARINAS | B41: ENTRADA SABADO | C41: 69104 | D41: 6 ENTRADAS SABADO | E41: 25 | F41: Quintal do Espeto Carinás
A42: CARINAS | B42: SABADO | C42: 78989056877143 | D42: OUTROS | E42: 15 | F42: Quintal do Espeto Carinás
A43: CARINAS | B43: ENTRADA MULHER | C43: 9003581 | D43: 5 ENTRADAS SEXTA-FEIRA | E43: 15 | F43: Quintal do Espeto Carinás
A44: CARINAS | B44: ENTRADA SEXTA HOMEN | C44: 511011 | D44: 5 ENTRADAS SEXTA-FEIRA | E44: 20 | F44: Quintal do Espeto Carinás
A45: CARINAS | B45: FICHA MAQUINA PELUCIA | C45: 7898905687604 | D45: OUTROS | E45: 6 | F45: Quintal do Espeto Carinás
A46: CARINAS | B46: ENTRADA QUARTA FEIRA | C46: 511005 | D46: ENTRADAS | E46: 10 | F46: Quintal do Espeto Carinás
A47: CARINAS | B47: ENTRADA VIP | C47: 9003136 | D47: 0 ENTRADAS VIPS | F47: Quintal do Espeto Carinás
A48: CARINAS | B48: ENTRADA DOMINGO NOITE | C48: 9003128 | D48: 7 ENTRADAS DOMINGO | F48: Quintal do Espeto Carinás
A49: CARINAS | B49: ENTRADA VIP PROMOTER | C49: 9003590 | D49: 0 ENTRADAS VIPS(RESTAURADA) | F49: Quintal do Espeto Carinás
A50: CARINAS | B50: BRINQUEDOS INFLAVEIS | C50: 78989056877144 | D50: OUTROS | E50: 10 | F50: Quintal do Espeto Carinás
A51: CARINAS | B51: BRINCADEIRA 1.DOCES | C51: 78989056877142 | D51: OUTROS | E51: 3 | F51: Quintal do Espeto Carinás
A52: CARINAS | B52: ENTRADA ANIVERSÁRIO | C52: 46078 | D52: 0 ENTRADAS VIPS(RESTAURADA) | F52: Quintal do Espeto Carinás
A53: CARINAS | B53: ENTRADA SEGUNDA FEIRA | C53: 40006 | D53: 1 ENTRADAS SEGUNDA-FEIRA | E53: 30 | F53: Quintal do Espeto Carinás
A54: CARINAS | B54: PULG TICKETS | C54: 511025 | D54: 0 ENTRADAS VIPS | F54: Quintal do Espeto Carinás
A55: CARINAS | B55: ENTRADA TICKET360 | C55: 9003572 | D55: 8 ENTRADAS SHOW | E55: 80 | F55: Quintal do Espeto Carinás
A56: LAPA | B56: ENTRADA TICKET 360 VIP | C56: 9003583 | D56: 0 ENTRADAS | F56: Quintal do Espeto Lapa
A57: LAPA | B57: ENTRADA MUSICO | C57: 7898905687356 | D57: 0 ENTRADAS VIPS | F57: Quintal do Espeto Lapa
A58: LAPA | B58: ENTRADA TERCA FEIRA | C58: 68817 | D58: 2 ENTRADAS TERÇA-FEIRA | E58: 10 | F58: Quintal do Espeto Lapa
A59: LAPA | B59: ENTRADA SEXTA FEIRA | C59: 4976 | D59: 5 ENTRADAS SEXTA-FEIRA | E59: 7 | F59: Quintal do Espeto Lapa
A60: LAPA | B60: ENTRADA SEGUNDA FEIRA | C60: 2601 | D60: 1 ENTRADAS SEGUNDA FEIRA | E60: 10 | F60: Quintal do Espeto Lapa
A61: LAPA | B61: ENTRADA DOMINGO | C61: 5644 | D61: 7 ENTRADAS DOMINGO | E61: 7 | F61: Quintal do Espeto Lapa
A62: LAPA | B62: ENTRADA LAPA | C62: 78989056877175 | D62: 0 ENTRADAS | E62: 7 | F62: Quintal do Espeto Lapa
A63: LAPA | B63: ENTRADA SABADO NOITE | C63: 28138 | D63: 6 ENTRADAS SABADO | E63: 7 | F63: Quintal do Espeto Lapa
A64: LAPA | B64: ENTRADA SABADO DIA | C64: 17879 | D64: 6 ENTRADAS SABADO | E64: 7 | F64: Quintal do Espeto Lapa
A65: LAPA | B65: ENTRADA ANIVERSARIO | C65: 27005 | D65: 0 ENTRADAS | F65: Quintal do Espeto Lapa
A66: LAPA | B66: ENTRADA VIP | C66: 26740 | D66: 0 ENTRADAS | F66: Quintal do Espeto Lapa
A67: LAPA | B67: ENTRADA QUINTA FEIRA | C67: 14669 | D67: 4 ENTRADAS QUINTA-FEIRA | E67: 7 | F67: Quintal do Espeto Lapa
A68: LAPA | B68: ENTRADA VIP LAPA | C68: 78989056877176 | D68: 0 ENTRADAS | F68: Quintal do Espeto Lapa
A69: LAPA | B69: ENTRADA QUARTA FEIRA | C69: 21069091 | D69: 3 ENTRADAS QUARTA-FEIRA | E69: 7 | F69: Quintal do Espeto Lapa
A70: TATUAPÉ | B70: ENTRADA VIP | C70: 52524 | D70: 0 ENTRADAS VIPS | F70: Quintal do Espeto Tatuapé
A71: TATUAPÉ | B71: Entrada Ticket | C71: 70996 | D71: 8 ENTRADAS SHOW | F71: Quintal do Espeto Tatuapé
A72: TATUAPÉ | B72: MENOR DE IDADE | C72: 9003588 | D72: ENTRADAS | F72: Quintal do Espeto Tatuapé
A73: TATUAPÉ | B73: ENTRADA DOMINGO 02 | C73: 9003630 | D73: 0 ENTRADAS VIPS | E73: 10 | F73: Quintal do Espeto Tatuapé
A74: TATUAPÉ | B74: ENTRADA SEXTA FEIRA | C74: 3775 | D74: 7 DOMINGO | E74: 20 | F74: Quintal do Espeto Tatuapé
A75: TATUAPÉ | B75: QUINTA FEIRA | C75: 78989056877136 | D75: 4 ENTRADAS QUINTA-FEIRA | E75: 15 | F75: Quintal do Espeto Tatuapé
A76: TATUAPÉ | B76: ENTRADA TERÇA FEIRA | C76: 9003587 | D76: 2 TERÇA FEIRA | E76: 15 | F76: Quintal do Espeto Tatuapé
A77: TATUAPÉ | B77: ENTRADA QUARTA FEIRA | C77: 78989056877139 | D77: 7 DOMINGO | E77: 15 | F77: Quintal do Espeto Tatuapé
A78: TATUAPÉ | B78: ENTRADA MUSICO | C78: 7898905687560 | D78: 0 ENTRADAS VIPS | F78: Quintal do Espeto Tatuapé
A79: TATUAPÉ | B79: SABADO | C79: 9003201 | D79: ENTRADAS | E79: 25 | F79: Quintal do Espeto Tatuapé
A80: TATUAPÉ | B80: ENTRADA TERÇA FEIRA | C80: 46064 | D80: 2 ENTRADAS TERÇA-FEIRA | E80: 15 | F80: Quintal do Espeto Tatuapé
A81: TATUAPÉ | B81: ENTRADA ANIVERSARIO | C81: 33670 | D81: 0 ENTRADAS VIPS | F81: Quintal do Espeto Tatuapé
A82: TATUAPÉ | B82: QUINTA FEIRA | C82: 9003181 | D82: 4 QUINTA-FEIRA | E82: 15 | F82: Quintal do Espeto Tatuapé
A83: TATUAPÉ | B83: ENTRADA SEXTA | C83: 9003200 | D83: 5 ENTRADA SEXTA-FEIRA | E83: 20 | F83: Quintal do Espeto Tatuapé
A84: TATUAPÉ | B84: ENTRADA SHOW 03 | C84: 9003577 | D84: ENTRADA DOMINGO | E84: 40 | F84: Quintal do Espeto Tatuapé
A85: TATUAPÉ | B85: FICHA MAQUIA PELUCIA | C85: 7898905687601 | D85: OUTROS | E85: 6 | F85: Quintal do Espeto Tatuapé
A86: TATUAPÉ | B86: TERÇA ADULTO | C86: 78989056877140 | D86: OUTROS | E86: 20 | F86: Quintal do Espeto Tatuapé
A87: TATUAPÉ | B87: TERÇA CRIANÇA | C87: 60709 | D87: ENTRADA DOMINGO | E87: 15 | F87: Quintal do Espeto Tatuapé
A88: TATUAPÉ | B88: SABADO | C88: 511017 | D88: 6 ENTRADA SABADO | E88: 25 | F88: Quintal do Espeto Tatuapé
A89: TATUAPÉ | B89: ENTRADA segunda | C89: 9003182 | D89: 1 ENTRADA SEGUNDA-FEIRA | E89: 15 | F89: Quintal do Espeto Tatuapé
A90: TATUAPÉ | B90: ENTRADA QUARTA FEIRA | C90: 82764 | D90: 3 ENTRADA QUARTA-FEIRA | E90: 15 | F90: Quintal do Espeto Tatuapé
A91: TATUAPÉ | B91: ENTRADA SHOW | C91: 78989056877138 | D91: OUTROS | E91: 50 | F91: Quintal do Espeto Tatuapé
A92: TATUAPÉ | B92: ENTRADA SHOW 02 | C92: 78989056877137 | D92: OUTROS | E92: 30 | F92: Quintal do Espeto Tatuapé
A93: TATUAPÉ | B93: ENTRADA 60+ | C93: 78989056877141 | D93: 0 ENTRADAS VIPS | F93: Quintal do Espeto Tatuapé
A94: TATUAPÉ | B94: ENTRADA SABADO | C94: 80679 | D94: 6 ENTRADA SABADO | E94: 25 | F94: Quintal do Espeto Tatuapé
A95: TATUAPÉ | B95: ENTRADA VIP COLABORADORES | C95: 9003589 | D95: 0 ENTRADAS VIPS(RESTAURADA) | F95: Quintal do Espeto Tatuapé
A96: TATUAPÉ | B96: INFLAVEIS | C96: 9003635 | D96: INFLAVEIS | E96: 10 | F96: Quintal do Espeto Tatuapé
A97: PAVÃO | B97: ENTRADA SEXTA FEIRA | C97: 48483 | D97: 5 ENTRADAS SEXTA-FEIRA | E97: 7 | F97: Quintal do Espeto Pavão
A98: PAVÃO | B98: ENTRADA ANIVERSARIO | C98: 1206 | D98: 0 ENTRADAS | F98: Quintal do Espeto Pavão
A99: PAVÃO | B99: LIGA DO BEM | C99: 511001 | D99: Entradas | E99: 10 | F99: Quintal do Espeto Pavão
A100: PAVÃO | B100: ENTRADA MUSICO | C100: 7898905687357 | D100: 0 ENTRADAS VIPS | F100: Quintal do Espeto Pavão
...

Sheet _Protheus_Cadastro
A1: Código | B1: Descrição | C1: Tipo | D1: Unidade | E1: Grupo | F1: Compra/Venda | G1: Últ. Preço (R$) | H1: Bloqueado | I1: Cód. Venda (ZIG) | J1: Última Atualização: 13/05/2026
A2: 001408 | B2: ** COM COLARINHO ** | C2: GN | D2: UN | E2: 0105 | F2: Venda | G2: 12.43 | H2: Não | I2: 9003688
A3: 001257 | B3: **ABACAXI** | C3: GN | D3: UN | E3: 0100 | F3: Venda | G3: 0 | H3: Não | I3: 9003137
A4: 001266 | B4: **ACUCAR** | C4: GN | D4: UN | E4: 0105 | F4: Venda | G4: 0 | H4: Não | I4: 9003622
A5: 001267 | B5: **ADOCANTE** | C5: GN | D5: UN | E5: 0105 | F5: Venda | G5: 0 | H5: Não | I5: 9003627
A6: 001329 | B6: **BEEFEATER DRINKS** | C6: GN | D6: UN | E6: 0101 | F6: Venda | G6: 0 | H6: Não | I6: 7898905687145
A7: 001330 | B7: **BEEFEATER PINK DRINKS** | C7: GN | D7: UN | E7: 0101 | F7: Venda | G7: 0 | H7: Não | I7: 7898905687146
A8: 001260 | B8: **COADA** | C8: GN | D8: UN | E8: 0105 | F8: Venda | G8: 0 | H8: Não | I8: 9003197
A9: 001313 | B9: **COM GELO** | C9: GN | D9: UN | E9: 0105 | F9: Venda | G9: 0 | H9: Não | I9: 9003687
A10: 001294 | B10: **FRUTAS VERDES** | C10: GN | D10: UN | E10: 0100 | F10: Venda | G10: 0 | H10: Não | I10: 9003617
A11: 001263 | B11: **FRUTAS VERMELHAS ** | C11: GN | D11: UN | E11: 0105 | F11: Venda | G11: 0 | H11: Não | I11: 9003616
A12: 001331 | B12: **GIN KAWAI PINK DRINKS** | C12: GN | D12: UN | E12: 0101 | F12: Venda | G12: 0 | H12: Não | I12: 7898905687147
A13: 001396 | B13: **GIN SALT DRINKS** | C13: GN | D13: UN | E13: 0101 | F13: Venda | G13: 0 | H13: Não | I13: 7898905687192
A14: 001305 | B14: **GORDONS DRINKS** | C14: GN | D14: UN | E14: 0101 | F14: Venda | G14: 0 | H14: Sim
A15: 001295 | B15: **LIMA DA PERSIA** | C15: GN | D15: UN | E15: 0100 | F15: Venda | G15: 0 | H15: Não | I15: 9003618
A16: 001265 | B16: **LIMAO** | C16: GN | D16: UN | E16: 0105 | F16: Venda | G16: 0 | H16: Não | I16: 9003621
A17: 001262 | B17: **MARACUJA** | C17: GN | D17: UN | E17: 0105 | F17: Venda | G17: 0 | H17: Não | I17: 9003615
A18: 001293 | B18: **MISTA DE UVA** | C18: GN | D18: UN | E18: 0100 | F18: Venda | G18: 0 | H18: Sim
A19: 001261 | B19: **MORANGO** | C19: GN | D19: UN | E19: 0105 | F19: Venda | G19: 0 | H19: Não | I19: 9003614
A20: 001258 | B20: **NAO FAZER** | C20: GN | D20: UN | E20: 0105 | F20: Venda | G20: 0 | H20: Não | I20: 9003138
A21: 001259 | B21: **SEM ACUCAR** | C21: GN | D21: UN | E21: 0105 | F21: Venda | G21: 0 | H21: Não | I21: 9003139
A22: 001289 | B22: **SEM COLARINHO** | C22: GN | D22: UN | E22: 0105 | F22: Venda | G22: 0 | H22: Não | I22: 9003186
A23: 001268 | B23: **SEM GELO** | C23: GN | D23: UN | E23: 0105 | F23: Venda | G23: 0 | H23: Não | I23: 9003628
A24: 001296 | B24: **TANGERINA C/ CANELA** | C24: GN | D24: UN | E24: 0100 | F24: Venda | G24: 0 | H24: Sim
A25: 001264 | B25: **TANGERINA C/ LIMAO ROSA E P/ | C25: GN | D25: UN | E25: 0105 | F25: Venda | G25: 0 | H25: Não | I25: 9003620
A26: 001306 | B26: **TANQUERAY DRINKS** | C26: GN | D26: UN | E26: 0101 | F26: Venda | G26: 0 | H26: Não | I26: 9003659
A27: 010315 | B27: **XAROPE LIMAO SICILIANO** | C27: GN | D27: UN | E27: 0100 | F27: Venda | G27: 0 | H27: Não | I27: 7898905687801
A28: 010316 | B28: **XAROPE MARACUJA** | C28: GN | D28: UN | E28: 0100 | F28: Venda | G28: 0 | H28: Não | I28: 7898905687802
A29: 010317 | B29: **XAROPE MAÇA VERDE** | C29: GN | D29: UN | E29: 0100 | F29: Venda | G29: 0 | H29: Não | I29: 7898905687803
A30: 010314 | B30: **XAROPE MORANGO** | C30: GN | D30: UN | E30: 0100 | F30: Venda | G30: 0 | H30: Não | I30: 7898905687800
A31: 009476 | B31: *CACHAÇA* | C31: GN | D31: UN | E31: 0105 | F31: Venda | G31: 0 | H31: Não | I31: 78989056877249
A32: 009478 | B32: *SAKE* | C32: GN | D32: UN | E32: 0105 | F32: Venda | G32: 0 | H32: Não | I32: 78989056877247
A33: 009477 | B33: *VODKA NACIONAL* | C33: GN | D33: UN | E33: 0105 | F33: Venda | G33: 0 | H33: Não | I33: 78989056877248
A34: 009475 | B34: 2 ESPETOS CLÁSSICOS + SALADA | C34: GN | D34: UN | E34: 0107 | F34: Venda | G34: 0 | H34: Não | I34: 78989056877339
A35: 009308 | B35: 3M FITA ANTIDERRAPANTE 50X5M PRETA | C35: MC | D35: PC | E35: 0132 | F35: Compras | G35: 57.12 | H35: Não
A36: 000794 | B36: ABACAXI C/ CHOCOLATE | C36: PA | D36: UN | E36: 0100 | F36: Venda | G36: 0 | H36: Não | I36: 50001
A37: 001368 | B37: ABACAXI CAFE DA MANHA | C37: PA | D37: UN | E37: 0100 | F37: Venda | G37: 0 | H37: Não | I37: 7898905687183
A38: 000798 | B38: ABACAXI NA BRASA C/ MEL E RAS | C38: PA | D38: UN | E38: 0100 | F38: Venda | G38: 0 | H38: Sim
A39: 000487 | B39: ABACAXI PEROLA FRUTA | C39: MP | D39: KG | E39: 0036 | F39: Compras | G39: 6.75 | H39: Não
A40: 001750 | B40: ABADA | C40: ME | D40: UN | E40: 0068 | F40: Compras | G40: 0 | H40: Sim
A41: 009566 | B41: ABASTECIMENTO DE GAS GLP | C41: MC | D41: KG | E41: 0142 | F41: Compras | G41: 22.2986 | H41: Não
A42: 002124 | B42: ABOBORA ASSADA | C42: PA | D42: UN | E42: 0121 | F42: Venda | G42: 0 | H42: Não | I42: 78989056877316
A43: 000624 | B43: ABOBORA JAPONESA | C43: MP | D43: KG | E43: 0036 | F43: Compras | G43: 5.19 | H43: Não
A44: 001972 | B44: ABOBORA SECA | C44: MP | D44: KG | E44: 0036 | F44: Compras | G44: 4.99 | H44: Não
A45: 000459 | B45: ABOBRINHA ITALIANA | C45: MP | D45: KG | E45: 0036 | F45: Compras | G45: 9.54 | H45: Não
A46: 009666 | B46: ABRACADEIRA NYLON 3,6X250MM | C46: MC | D46: PC | E46: 0132 | F46: Compras | G46: 0 | H46: Não
A47: 009349 | B47: ABRACADEIRA PLASTICO | C47: MC | D47: PC | E47: 0132 | F47: Compras | G47: 0.18 | H47: Não
A48: 010365 | B48: ABRACADEIRA RSF 3/4 19X25 INOX MANGUEIRA | C48: MC | D48: UN | E48: 0132 | F48: Compras | G48: 0 | H48: Não
A49: 009442 | B49: ABRACADEIRA TIPO C | C49: MC | D49: UN | E49: 0132 | F49: Compras | G49: 1.98 | H49: Não
A50: 009443 | B50: ABRACADEIRA TIPO C 3/4 | C50: MC | D50: UN | E50: 0132 | F50: Compras | G50: 1.8 | H50: Não
A51: 009429 | B51: ABRACADEIRA TIPO D COM CUNHA 1/2 | C51: MC | D51: UN | E51: 0132 | F51: Compras | G51: 3.2 | H51: Não
A52: 010168 | B52: ABRACADEIRA TIPO U | C52: MC | D52: UN | E52: 0132 | F52: Compras | G52: 1 | H52: Não
A53: 000522 | B53: ABRIDOR DE GARRAFA 11CM | C53: MC | D53: UN | E53: 0079 | F53: Compras | G53: 4.6 | H53: Não
A54: 000559 | B54: ABRIDOR DE LATA 9 CM | C54: MC | D54: UN | E54: 0079 | F54: Compras | G54: 5.6 | H54: Não
A55: 000537 | B55: ABRIDOR DE VINHO 12 CM | C55: MC | D55: UN | E55: 0079 | F55: Compras | G55: 22.7 | H55: Não
A56: 009484 | B56: ABSOLUT ANIVERSARIANTE | C56: GN | D56: UN | E56: 0107 | F56: Venda | G56: 0 | H56: Não | I56: 7898905687709
A57: 001037 | B57: ABSOLUT DOSE | C57: PA | D57: UN | E57: 0119 | F57: Venda | G57: 0 | H57: Não | I57: 89552
A58: 000338 | B58: ABSOLUT ELYX | C58: MR | D58: LT | E58: 0119 | F58: Venda | G58: 0 | H58: Sim
A59: 000757 | B59: ABSOLUT EXTRAKT | C59: MR | D59: LT | E59: 0055 | G59: 0 | H59: Sim
A60: 000698 | B60: ABSOLUT FLAVOR CITRON | C60: MR | D60: LT | E60: 0119 | F60: Venda | G60: 0 | H60: Sim
A61: 000700 | B61: ABSOLUT FLAVOR VANILLA 750ML | C61: ME | D61: LT | E61: 0055 | F61: Compras | G61: 0 | H61: Não
A62: 000049 | B62: ABSOLUT GARRAFA | C62: MR | D62: UN | E62: 0119 | F62: Venda | G62: 0 | H62: Não | I62: 102120
A63: 009940 | B63: ACABAMENTO PARA CAIXA DE DESCARGA EMBUTIDA | C63: MC | D63: UN | E63: 0132 | F63: Compras | G63: 88.04 | H63: Não
A64: 001131 | B64: ACAFRAO | C64: MR | D64: KG | E64: 0029 | G64: 0 | H64: Sim
A65: 010359 | B65: ACCESS POINT UNIFI U6 PRO | C65: MC | D65: UN | E65: 0006 | F65: Compras | G65: 0 | H65: Não
A66: 000425 | B66: ACEM PECA FUNCIONARIO | C66: MC | D66: KG | E66: 0013 | F66: Compras | G66: 29 | H66: Não
A67: 009658 | B67: ACIDO 5L | C67: MC | D67: UN | E67: 0132 | F67: Compras | G67: 13.9 | H67: Não
A68: 000374 | B68: ACUCAR REFINADO UNIAO | C68: MP | D68: KG | E68: 0029 | F68: Compras | G68: 3.45 | H68: Não
A69: 000375 | B69: ACUCAR SACHE UNIAO | C69: MC | D69: CX | E69: 0029 | F69: Compras | G69: 21.318 | H69: Não
A70: 009497 | B70: ADAPTADOR 2P + T BENJAMIN 10A | C70: MC | D70: UN | E70: 0132 | F70: Compras | G70: 0 | H70: Não
A71: 009444 | B71: ADAPTADOR C/ FLANGE E ANEL 3/4 X 25MM | C71: MC | D71: UN | E71: 0132 | F71: Compras | G71: 3 | H71: Não
A72: 009781 | B72: ADAPTADOR DE INTERNET HUB 4 PORTAS | C72: MC | D72: UN | E72: 0006 | F72: Compras | G72: 0 | H72: Não
A73: 009493 | B73: ADAPTADOR DE MANGUEIRA FEMEA | C73: MC | D73: UN | E73: 0132 | F73: Compras | G73: 0 | H73: Não
A74: 009355 | B74: ADAPTADOR PARA CONDULETE 03/4 | C74: MC | D74: UN | E74: 0132 | F74: Compras | G74: 2 | H74: Não
A75: 010127 | B75: ADAPTADOR PARA MANDRIL | C75: MC | D75: UN | E75: 0132 | F75: Compras | G75: 0 | H75: Não
A76: 009782 | B76: ADAPTADOR USB INTERNET | C76: MC | D76: UN | E76: 0006 | F76: Compras | G76: 0 | H76: Não
... A90: 000334 | B90: AGUA C/ GAS | C90: ME | D90: UN | E90: 0021 | F90: Compras | G90: 1.575 | H90: Não
A91: 000890 | B91: AGUA C/ GAS | C91: MR | D91: UN | E91: 0088 | F91: Venda | G91: 0 | H91: Não | I91: 71014
A92: 002182 | B92: AGUA C/ GAS RUA | C92: MR | D92: UN | E92: 0088 | F92: Venda | G92: 0 | H92: Não | I92: 78989056877363
A93: 009577 | B93: AGUA C/ GAS CARNAVAL | C93: MR | D93: UN | E93: 0088 | F93: Venda | G93: 0 | H93: Sim
A94: 000892 | B94: AGUA DE COCO | C94: MR | D94: UN | E94: 0088 | F94: Venda | G94: 0 | H94: Não | I94: 71018
A95: 000380 | B95: AGUA DE COCO 330ML | C95: ME | D95: UN | E95: 0021 | F95: Compras | G95: 5.08 | H95: Não
A96: 001993 | B96: AGUA LINDOYA 500ML | C96: MC | D96: KG | E96: 0052 | F96: Compras | G96: 0 | H96: Sim
A97: 001375 | B97: AGUA POTAVEL | C97: MC | D97: UN | E97: 0136 | F97: Compras | G97: 700 | H97: Não
A98: 000333 | B98: AGUA S/ GAS | C98: ME | D98: UN | E98: 0021 | F98: Compras | G98: 1.4417 | H98: Não
A99: 000878 | B99: AGUA S/ GAS | C99: MR | D99: UN | E99: 0088 | F99: Venda | G99: 1.595 | H99: Não | I99: 71001
A100: 009578 | B100: AGUA S/ GAS CARNAVAL | C100: MR | D100: UN | E100: 0088 | F100: Venda | G100: 0 | H100: Sim
A101: 002183 | B101: AGUA S/ GAS RUA | C101: MR | D101: UN | E101: 0088 | F101: Venda | G101: 0 | H101: Não | I101: 78989056877362
A102: 000103 | B102: AGUA SANITARIA COM 5 LITROS | C102: MC | D102: UN | E102: 0075 | F102: Compras | G102: 9.98 | H102: Não
A103: 000879 | B103: AGUA TONICA | C103: MR | D103: UN | E103: 0111 | F103: Venda | G103: 0 | H103: Não | I103: 71002
A104: 000885 | B104: AGUA TONICA DIET | C104: MR | D104: UN | E104: 0111 | F104: Venda | G104: 0 | H104: Não | I104: 71008
A105: 001188 | B105: AGUARDENTE DE CANA | C105: PI | D105: LT | E105: 0090 | F105: Venda | G105: 12.49 | H105: Sim
A106: 001191 | B106: AGUARDENTE DE CANA OURO | C106: PI | D106: LT | E106: 0090 | F106: Venda | G106: 0 | H106: Sim
A107: 001190 | B107: AGUARDENTE DE CANA PRATA | C107: PI | D107: LT | E107: 0090 | F107: Venda | G107: 0 | H107: Sim
A108: 002255 | B108: ALCATRA BOVINO BIFE - COMPRAS | C108: MC | D108: KG | E108: 0013 | F108: Compras | G108: 54.4 | H108: Não
A109: 000104 | B109: ALCOOL EM GEL BARRICA | C109: MC | D109: UN | E109: 0075 | F109: Compras | G109: 79.9 | H109: Não
A110: 000974 | B110: ALCOOL GEL 70 ANTISEPTICO | C110: MC | D110: UN | E110: 0075 | F110: Compras | G110: 6.26 | H110: Não
A111: 000076 | B111: ALCOOL GEL 70% 500G | C111: MC | D111: UN | E111: 0074 | F111: Compras | G111: 7.5 | H111: Sim
A112: 000239 | B112: ALCOOL LIQUIDO 70% | C112: MC | D112: UN | E112: 0075 | F112: Compras | G112: 7.6666 | H112: Não
A113: 000668 | B113: ALECRIM | C113: MP | D113: KG | E113: 0036 | F113: Compras | G113: 91.43 | H113: Não
...

Sheet _ZIG_Precos
A1: EXPORTAÇÃO CONSOLIDADA — Todos os canais | Apenas Produtos | N1: Última Atualização: 13/05/2026
A2: Nome * | B2: Tipo Produto | C2: Categoria | D2: Preço (R$) | E2: Preço (cts) | F2: SKU/EAN | G2: NCM | H2: CEST | I2: Grupo Fiscal | J2: Perfil Fiscal | K2: Estocável | L2: Un. Medida | M2: Canal/Unidade
A3: 2 ESPETOS CLÁSSICOS + SALADA | B3: Refeicao | C3: DELIVERY | D3: 39.9 | E3: 3990 | F3: 78989056877339 | G3: 21069090 | I3: Alimentos - 5102 | J3: Carinás | K3: Não | L3: Unidades | M3: Delivery
A4: ABACAXI C/ CHOCOLATE | D4: 18.99 | E4: 1899 | F4: 50001 | G4: 21069090 | I4: Alimentos - 5102 | J4: Carinás | K4: Sim | L4: Unidades | M4: Carinás + SA + Delivery
A5: ABACAXI CAFE DA MANHA | C5: A CAFÉ DA MANHA | D5: 0 | E5: 0 | F5: 7898905687183 | G5: 8043000 | I5: Alimentos - 5102 | J5: Carinás | K5: Sim | L5: Unidades | M5: Carinás + SA
A6: ABOBORA ASSADA | D6: 10.99 | E6: 1099 | F6: 78989056877316 | G6: 21069090 | K6: Sim | L6: Unidades | M6: Carinás + SA
A7: ABOBRINHA | D7: 10.99 | E7: 1099 | F7: 20001 | G7: 21069090 | I7: Alimentos - 5102 | J7: Carinás | K7: Sim | L7: Unidades | M7: Carinás + SA + Delivery
A8: ABSOLUT ANIVERSARIANTE | D8: 0 | E8: 0 | F8: 7898905687709 | G8: 22030000 | I8: Bebidas - 5405 - 1 | J8: Carinás | K8: Sim | L8: Unidades | M8: Carinás + SA
A9: ABSOLUT DOSE | D9: 26 | E9: 2600 | F9: 89552 | G9: 22086000 | I9: Alimentos - 5102 | J9: Carinás | K9: Sim | L9: Unidades | M9: Carinás + SA
